Workbook

Sheet Source
C1: . | W1: 1.2 | X1: 1.2 | Z1: 1.2 | AD1: D IN STORE ITEMS | AI1: Single Unit Amounts | AR1: Margins | BB1: Final Margin Including Rebate | BG1: Item UPC | BH1: Case UPC | BJ1: Flyer Description | BK1: Story | BM1: Mainframe Description | BN1: Size | BO1: MS
A2: Item No. | B2: Item Details | C2: Minor Category | D2: CLMS | E2: Ad Code | F2: Ad Location Code | G2: Feature & Insert Code | H2: Limit | I2: Region | J2: Supplier Case Cost | K2: OI | L2: chq | M2: crc | N2: Count Recount By Inner | O2: Special Net Price | P2: Special Unit Price | Q2: ho | R2: Scan Back | S2: Scan Back / Unit | T2: Ad SRP | W2: AAA | X2: Yukon | Z2: A | AA2: Store % GP Rate | AC2: AAA | AD2: Yukon | AE2: AAA/AA | AF2: A | AH2: AAA | AI2: Yukon | AJ2: AAA/AA | AK2: A | AM2: NON EDBV Base Cost | AN2: Case Weight | AO2: Case Pack | AP2: Invoice Cost | AQ2: EDBV | AR2: AAA | AS2: Yukon | AT2: AAA/AA | AU2: A | BB2: AAA | BC2: Yukon | BD2: AAA/AA | BE2: A | BI2: 1 file notes | BP2: canada | BQ2: 13 | BR2: 14 | BS2: SNS | BT2: $ | BU2: kraft | BV2: nestle | BW2: mccormick | BX2: hq 2/9/26 | BY2: hq 3/3/26 | CA2: ho | CB2: 2 File notes | CC2: 1280 3/16/26 | CE2: ad code | CF2: cost | CG2: oi | CH2: chq | CI2: crc | CJ2: cost | CK2: oi | CL2: chq | CM2: crc | CN2: notes | CO2: srp | CP2: Ad SRP-old | CQ2: diff
A3: 780353 | B3: C-GOLD MILK CHOC VAN BAR 8 X 5 EA | C3: 010518110105 | D3: L M S | E3: A | F3: F | G3: F | I3: ALL | J3: 41.27 | O3: 41.27 | P3: 5.15875 | Q3: 2 | T3: 1 / $4.99 | U3: 1 | V3: $4.99 | W3: 1 /4.99 | X3: 5.99 | Z3: 5.49 | AA3: 0.030395541 | AC3: 5.99 | AD3: 7.19 | AE3: 6.19 | AF3: 7.19 | AH3: =IF(W3<>"",(RIGHT(W3,LEN(W3)-SEARCH("/",W3,1)))/U3,"") -> 4.99 | AI3: =IF(X3<>"",X3,"") -> 5.99 | AJ3: =IF(Y3<>"",Y3,"") | AK3: =IF(Z3<>"",Z3,"") -> 5.49 | AM3: 41.74 | AN3: 7.6 | AO3: 8 | AP3: =(AM3 * 1.05) - L3 - Q3 - K3 -> 41.827 | AQ3: N | AR3: =(((AH3)-((AP3/AO3) + ((AN3 * 0.03)/AO3)))/AH3)*100 -> -5.3481964 | AS3: =(((AI3)-((AP3/AO3) + ((AN3 * 0.3)/AO3)))/AI3)*100 -> 7.9570117 | AT3: =(((AJ3)-((AP3/AO3) + ((AN3 * 0.03)/AO3)))/AJ3)*100 -> #VALUE! | AU3: =(((AK3)-((AP3/AO3) + ((AN3 * 0.07)/AO3)))/AK3)*100 -> 3.5541894 | BB3: =(((AH3)-(((AP3/AO3) + ((AN3 * 0.03)/AO3))-AW3))/AH3)*100 -> -5.3481964 | BC3: =(((AI3)-(((AP3/AO3) + ((AN3 * 0.3)/AO3))-AX3))/AI3)*100 -> 7.9570117 | BD3: =(((AJ3)-(((AP3/AO3) + ((AN3 * 0.03)/AO3))-AY3))/AJ3)*100 -> #VALUE! | BE3: =(((AK3)-(((AP3/AO3) + ((AN3 * 0.15)/AO3))-AZ3))/AK3)*100 -> 2.1698543 | BG3: 0005731613224 | BH3: 0057316132243 | BJ3: Co-op Gold Ice Cream or Frozen Yogurt 1.5 L or Novelties Package of 4 - 12 | BM3: C-GOLD MILK CHOC VAN BAR | BN3: 5 | BO3: EA | BP3: 780353 | BQ3: #N/A | BR3: DNK | BS3: 22 | BT3: 16622.27 | BX3: 8.29 | BY3: 8.29 | BZ3: =BY3-BX3 -> 0 | CC3: =VLOOKUP(A3,'[1]RPT 1280 - Edmonton'!$1:$1048576,4,0) -> #N/A | CE3: EA | CF3: 41.27 | CG3: 0 | CH3: 0 | CI3: 0 | CJ3: =CF3-J3 -> 0 | CK3: =CG3-K3 -> 0 | CL3: =CH3-L3 -> 0 | CM3: =CI3-M3 -> 0 | CO3: 4.99 | CP3: 4.99 | CQ3: =CP3-CO3 -> 0
A4: 780312 | B4: C.GOLD CHC ALMD I/CRM BAR 8 X 5 EA | C4: 010518110105 | D4: L M S | E4: A | F4: F | G4: F | J4: =J3 -> 41.27 | O4: =O3 -> 41.27 | P4: =P3 -> 5.15875 | Q4: 2 | W4: 1 /4.99 | X4: 5.99 | Z4: 5.49 | AH4: =IF(W4<>"",(RIGHT(W4,LEN(W4)-SEARCH("/",W4,1)))/U4,"") -> #VALUE! | AI4: =IF(X4<>"",X4,"") -> 5.99 | AJ4: =IF(Y4<>"",Y4,"") | AK4: =IF(Z4<>"",Z4,"") -> 5.49 | BG4: 0005731613225 | BH4: 0057316132250 | BJ4: Co-op Gold Ice Cream or Frozen Yogurt 1.5 L or Novelties Package of 4 - 12 | BM4: C.GOLD CHC ALMD I/CRM BAR | BN4: 5 | BO4: EA | BP4: 780312 | BQ4: #N/A | BR4: DNK | BS4: 14 | BT4: 24284.54 | BX4: 8.29 | BY4: 8.29 | BZ4: =BY4-BX4 -> 0 | CC4: =VLOOKUP(A4,'[1]RPT 1280 - Edmonton'!$1:$1048576,4,0) -> #N/A | CE4: EA | CF4: 41.27 | CG4: 0 | CH4: 0 | CI4: 0 | CJ4: =CF4-J4 -> 0 | CK4: =CG4-K4 -> 0 | CL4: =CH4-L4 -> 0 | CM4: =CI4-M4 -> 0
A5: 780288 | B5: C.GOLD DARK CHC I/CRM BAR 8 X 5 EA | C5: 010518110105 | D5: L M S | E5: A | F5: F | G5: F | J5: =J4 -> 41.27 | O5: =O4 -> 41.27 | P5: =P4 -> 5.15875 | Q5: 2 | W5: 1 /4.99 | X5: 5.99 | Z5: 5.49 | AH5: =IF(W5<>"",(RIGHT(W5,LEN(W5)-SEARCH("/",W5,1)))/U5,"") -> #VALUE! | AI5: =IF(X5<>"",X5,"") -> 5.99 | AJ5: =IF(Y5<>"",Y5,"") | AK5: =IF(Z5<>"",Z5,"") -> 5.49 | BG5: 0005731613226 | BH5: 0057316132267 | BJ5: Co-op Gold Ice Cream or Frozen Yogurt 1.5 L or Novelties Package of 4 - 12 | BM5: C.GOLD DARK CHC I/CRM BAR | BN5: 5 | BO5: EA | BP5: 780288 | BQ5: #N/A | BR5: DNK | BS5: 28 | BT5: 10886.76 | BX5: 8.29 | BY5: 8.29 | BZ5: =BY5-BX5 -> 0 | CC5: =VLOOKUP(A5,'[1]RPT 1280 - Edmonton'!$1:$1048576,4,0) -> #N/A | CE5: EA | CF5: 41.27 | CG5: 0 | CH5: 0 | CI5: 0 | CJ5: =CF5-J5 -> 0 | CK5: =CG5-K5 -> 0 | CL5: =CH5-L5 -> 0 | CM5: =CI5-M5 -> 0
A6: 6399646 | B6: C.GOLD BEACH PARTY IC/CRM -Z 4 X 1.5 LT | C6: 010513110105 | D6: L M S | E6: A | F6: F | G6: F | I6: ALL | J6: 20.41 | O6: 20.41 | P6: 5.1025 | Q6: 4 | T6: 1 / $4.99 | U6: 1 | V6: $4.99 | W6: 1 /4.99 | X6: 5.99 | Z6: 5.49 | AA6: 0.028796092 | AC6: 5.99 | AD6: 7.19 | AE6: 6.19 | AF6: 7.19 | AH6: =IF(W6<>"",(RIGHT(W6,LEN(W6)-SEARCH("/",W6,1)))/U6,"") -> 4.99 | AI6: =IF(X6<>"",X6,"") -> 5.99 | AJ6: =IF(Y6<>"",Y6,"") | AK6: =IF(Z6<>"",Z6,"") -> 5.49 | AM6: 22 | AN6: 9.7 | AO6: 4 | AP6: =(AM6 * 1.05) - L6 - Q6 - K6 -> 19.1 | AQ6: N | AR6: =(((AH6)-((AP6/AO6) + ((AN6 * 0.03)/AO6)))/AH6)*100 -> 2.8507014 | AS6: =(((AI6)-((AP6/AO6) + ((AN6 * 0.3)/AO6)))/AI6)*100 -> 8.1385643 | AT6: =(((AJ6)-((AP6/AO6) + ((AN6 * 0.03)/AO6)))/AJ6)*100 -> #VALUE! | AU6: =(((AK6)-((AP6/AO6) + ((AN6 * 0.07)/AO6)))/AK6)*100 -> 9.931694 | BB6: =(((AH6)-(((AP6/AO6) + ((AN6 * 0.03)/AO6))-AW6))/AH6)*100 -> 2.8507014 | BC6: =(((AI6)-(((AP6/AO6) + ((AN6 * 0.3)/AO6))-AX6))/AI6)*100 -> 8.1385643 | BD6: =(((AJ6)-(((AP6/AO6) + ((AN6 * 0.03)/AO6))-AY6))/AJ6)*100 -> #VALUE! | BE6: =(((AK6)-(((AP6/AO6) + ((AN6 * 0.15)/AO6))-AZ6))/AK6)*100 -> 6.3979964 | BG6: 0005731621052 | BH6: 0057316210521 | BJ6: Co-op Gold Ice Cream or Frozen Yogurt 1.5 L or Novelties Package of 4 - 12 | BM6: C.GOLD BEACH PARTY IC/CRM -Z | BN6: 1.5 | BO6: LT | BP6: 6399646 | BQ6: #N/A | BR6: DNK | BS6: 26 | BT6: 3667.66 | BX6: 7.19 | BY6: 7.19 | BZ6: =BY6-BX6 -> 0 | CC6: =VLOOKUP(A6,'[1]RPT 1280 - Edmonton'!$1:$1048576,4,0) -> #N/A | CE6: EA | CF6: 20.41 | CG6: 0 | CH6: 0 | CI6: 0 | CJ6: =CF6-J6 -> 0 | CK6: =CG6-K6 -> 0 | CL6: =CH6-L6 -> 0 | CM6: =CI6-M6 -> 0 | CO6: 4.99 | CP6: 4.99 | CQ6: =CP6-CO6 -> 0
A7: 6442164 | B7: CG COOKIE DOUGH I/C BAR -Z 8 X 5 EA | C7: 010518110117 | D7: L M S | E7: A | F7: F | G7: F | I7: ALL | J7: 42.84 | O7: 42.84 | P7: 5.355 | Q7: 3 | T7: 1 / $4.99 | U7: 1 | V7: $4.99 | W7: 1 /4.99 | X7: 5.99 | Z7: 5.49 | AA7: 0.02907515 | AC7: 5.99 | AD7: 7.19 | AE7: 6.19 | AF7: 7.19 | AH7: =IF(W7<>"",(RIGHT(W7,LEN(W7)-SEARCH("/",W7,1)))/U7,"") -> 4.99 | AI7: =IF(X7<>"",X7,"") -> 5.99 | AJ7: =IF(Y7<>"",Y7,"") | AK7: =IF(Z7<>"",Z7,"") -> 5.49 | AM7: 43.45 | AN7: 5.29 | AO7: 8 | AP7: =(AM7 * 1.05) - L7 - Q7 - K7 -> 42.6225 | AQ7: N | AR7: =(((AH7)-((AP7/AO7) + ((AN7 * 0.03)/AO7)))/AH7)*100 -> -7.1673347 | AS7: =(((AI7)-((AP7/AO7) + ((AN7 * 0.3)/AO7)))/AI7)*100 -> 7.7431135 | AT7: =(((AJ7)-((AP7/AO7) + ((AN7 * 0.03)/AO7)))/AJ7)*100 -> #VALUE! | AU7: =(((AK7)-((AP7/AO7) + ((AN7 * 0.07)/AO7)))/AK7)*100 -> 2.1111111 | BB7: =(((AH7)-(((AP7/AO7) + ((AN7 * 0.03)/AO7))-AW7))/AH7)*100 -> -7.1673347 | BC7: =(((AI7)-(((AP7/AO7) + ((AN7 * 0.3)/AO7))-AX7))/AI7)*100 -> 7.7431135 | BD7: =(((AJ7)-(((AP7/AO7) + ((AN7 * 0.03)/AO7))-AY7))/AJ7)*100 -> #VALUE! | BE7: =(((AK7)-(((AP7/AO7) + ((AN7 * 0.15)/AO7))-AZ7))/AK7)*100 -> 1.147541 | BG7: 0005731621255 | BH7: 0057316212556 | BI7: 6524854 | BJ7: Co-op Gold Ice Cream or Frozen Yogurt 1.5 L or Novelties Package of 4 - 12 | BM7: CG COOKIE DOUGH I/C BAR -Z | BN7: 5 | BO7: EA | BP7: 6442164 | BQ7: #N/A | BR7: DNK | BS7: 51 | BT7: 593.02 | BX7: 8.79 | BY7: 8.79 | BZ7: =BY7-BX7 -> 0 | CB7: should these be keyed into ad - pk chnge-no they don’t have stop buys | CC7: =VLOOKUP(A7,'[1]RPT 1280 - Edmonton'!$1:$1048576,4,0) -> #N/A | CE7: EA | CF7: 42.84 | CG7: 0 | CH7: 0 | CI7: 0 | CJ7: =CF7-J7 -> 0 | CK7: =CG7-K7 -> 0 | CL7: =CH7-L7 -> 0 | CM7: =CI7-M7 -> 0 | CO7: 4.99 | CP7: 4.99 | CQ7: =CP7-CO7 -> 0
A8: 6442156 | B8: CG STWBRY CHSCAKE I/C BAR -Z 8 X 5 EA | C8: 010518110117 | D8: L M S | E8: A | F8: F | G8: F | J8: =J7 -> 42.84 | O8: =O7 -> 42.84 | P8: =P7 -> 5.355 | Q8: 3 | W8: 1 /4.99 | X8: 5.99 | Z8: 5.49 | AH8: =IF(W8<>"",(RIGHT(W8,LEN(W8)-SEARCH("/",W8,1)))/U8,"") -> #VALUE! | AI8: =IF(X8<>"",X8,"") -> 5.99 | AJ8: =IF(Y8<>"",Y8,"") | AK8: =IF(Z8<>"",Z8,"") -> 5.49 | BG8: 0005731621254 | BH8: 0057316212549 | BI8: 6524847-notyet they don’t have stop buys | BM8: CG STWBRY CHSCAKE I/C BAR -Z | BN8: 5 | BO8: EA | BP8: 6442156 | BQ8: #N/A | BR8: DNK | BS8: 50 | BT8: 989.96 | BX8: 8.79 | BY8: 8.79 | BZ8: =BY8-BX8 -> 0 | CC8: =VLOOKUP(A8,'[1]RPT 1280 - Edmonton'!$1:$1048576,4,0) -> #N/A | CE8: EA | CF8: 42.84 | CG8: 0 | CH8: 0 | CI8: 0 | CJ8: =CF8-J8 -> 0 | CK8: =CG8-K8 -> 0 | CL8: =CH8-L8 -> 0 | CM8: =CI8-M8 -> 0
A9: 6499271 | B9: CG OLD FASHIONED VAN I/C -NEW 4 X 1.5 LT | C9: 010513110100 | D9: L M S | E9: A | F9: F | G9: F | I9: ALL | J9: 21.14 | O9: 21.14 | P9: 5.285 | Q9: 3.2 | T9: 1 / $4.99 | U9: 1 | V9: $4.99 | W9: 1 /4.99 | X9: 5.99 | Z9: 5.49 | AA9: 0.028210421 | AC9: 5.99 | AD9: 7.19 | AE9: 6.19 | AF9: 7.19 | AH9: =IF(W9<>"",(RIGHT(W9,LEN(W9)-SEARCH("/",W9,1)))/U9,"") -> 4.99 | AI9: =IF(X9<>"",X9,"") -> 5.99 | AJ9: =IF(Y9<>"",Y9,"") | AK9: =IF(Z9<>"",Z9,"") -> 5.49 | AM9: 22.64 | AN9: 8.84 | AO9: 4 | AP9: =(AM9 * 1.05) - L9 - Q9 - K9 -> 20.572 | AQ9: N | AR9: =(((AH9)-((AP9/AO9) + ((AN9 * 0.03)/AO9)))/AH9)*100 -> -4.3947896 | AS9: =(((AI9)-((AP9/AO9) + ((AN9 * 0.3)/AO9)))/AI9)*100 -> 3.0717863 | AT9: =(((AJ9)-((AP9/AO9) + ((AN9 * 0.03)/AO9)))/AJ9)*100 -> #VALUE! | AU9: =(((AK9)-((AP9/AO9) + ((AN9 * 0.07)/AO9)))/AK9)*100 -> 3.5027322 | BB9: =(((AH9)-(((AP9/AO9) + ((AN9 * 0.03)/AO9))-AW9))/AH9)*100 -> -4.3947896 | BC9: =(((AI9)-(((AP9/AO9) + ((AN9 * 0.3)/AO9))-AX9))/AI9)*100 -> 3.0717863 | BD9: =(((AJ9)-(((AP9/AO9) + ((AN9 * 0.03)/AO9))-AY9))/AJ9)*100 -> #VALUE! | BE9: =(((AK9)-(((AP9/AO9) + ((AN9 * 0.15)/AO9))-AZ9))/AK9)*100 -> 0.28233151 | BG9: 0005731621715 | BH9: 0057316217155 | BJ9: Co-op Gold Ice Cream or Frozen Yogurt 1.5 L or Novelties Package of 4 - 12 | BM9: CG OLD FASHIONED VAN I/C -NEW | BN9: 1.5 | BO9: LT | BQ9: #N/A | BR9: DNK | BS9: 7 | BT9: 10924.05 | BX9: 7.19 | BY9: 7.19 | BZ9: =BY9-BX9 -> 0 | CC9: =VLOOKUP(A9,'[1]RPT 1280 - Edmonton'!$1:$1048576,4,0) -> #N/A | CE9: EA | CF9: 21.14 | CG9: 0 | CH9: 0 | CI9: 0 | CJ9: =CF9-J9 -> 0 | CK9: =CG9-K9 -> 0 | CL9: =CH9-L9 -> 0 | CM9: =CI9-M9 -> 0 | CO9: 4.99 | CP9: 4.99 | CQ9: =CP9-CO9 -> 0
A10: 6500722 | B10: CG BLK CHERRY FROZ YOGURT -NEW 4 X 1.5 LT | C10: 010513110100 | D10: L M S | E10: A | F10: F | G10: F | J10: =J9 -> 21.14 | O10: =O9 -> 21.14 | P10: =P9 -> 5.285 | Q10: 3 | W10: 1 /4.99 | X10: 5.99 | Z10: 5.49 | AH10: =IF(W10<>"",(RIGHT(W10,LEN(W10)-SEARCH("/",W10,1)))/U10,"") -> #VALUE! | AI10: =IF(X10<>"",X10,"") -> 5.99 | AJ10: =IF(Y10<>"",Y10,"") | AK10: =IF(Z10<>"",Z10,"") -> 5.49 | BG10: 0005731621747 | BH10: 0057316217476 | BJ10: Co-op Gold Ice Cream or Frozen Yogurt 1.5 L or Novelties Package of 4 - 12 | BM10: CG BLK CHERRY FROZ YOGURT -NEW | BN10: 1.5 | BO10: LT | BQ10: #N/A | BR10: DNK | BS10: 39 | BT10: 910.07 | BX10: 7.19 | BY10: 7.19 | BZ10: =BY10-BX10 -> 0 | CC10: =VLOOKUP(A10,'[1]RPT 1280 - Edmonton'!$1:$1048576,4,0) -> #N/A | CE10: EA | CF10: 21.14 | CG10: 0 | CH10: 0 | CI10: 0 | CJ10: =CF10-J10 -> 0 | CK10: =CG10-K10 -> 0 | CL10: =CH10-L10 -> 0 | CM10: =CI10-M10 -> 0
A11: 6500565 | B11: CG FUDGE SUNDAE SPRME I/C -NEW 4 X 1.5 LT | C11: 010513110100 | D11: L M S | E11: A | F11: F | G11: F | J11: =J10 -> 21.14 | O11: =O10 -> 21.14 | P11: =P10 -> 5.285 | Q11: 3.2 | W11: 1 /4.99 | X11: 5.99 | Z11: 5.49 | AH11: =IF(W11<>"",(RIGHT(W11,LEN(W11)-SEARCH("/",W11,1)))/U11,"") -> #VALUE! | AI11: =IF(X11<>"",X11,"") -> 5.99 | AJ11: =IF(Y11<>"",Y11,"") | AK11: =IF(Z11<>"",Z11,"") -> 5.49 | BG11: 0005731621718 | BH11: 0057316217186 | BM11: CG FUDGE SUNDAE SPRME I/C -NEW | BN11: 1.5 | BO11: LT | BQ11: #N/A | BR11: DNK | BS11: 25 | BT11: 3553.88 | BX11: 7.19 | BY11: 7.19 | BZ11: =BY11-BX11 -> 0 | CC11: =VLOOKUP(A11,'[1]RPT 1280 - Edmonton'!$1:$1048576,4,0) -> #N/A | CE11: EA | CF11: 21.14 | CG11: 0 | CH11: 0 | CI11: 0 | CJ11: =CF11-J11 -> 0 | CK11: =CG11-K11 -> 0 | CL11: =CH11-L11 -> 0 | CM11: =CI11-M11 -> 0
A12: 6500557 | B12: CG MAPLE WALNUT ICE CREAM -NEW 4 X 1.5 LT | C12: 010513110100 | D12: L M S | E12: A | F12: F | G12: F | J12: =J11 -> 21.14 | O12: =O11 -> 21.14 | P12: =P11 -> 5.285 | Q12: 3.2 | W12: 1 /4.99 | X12: 5.99 | Z12: 5.49 | AH12: =IF(W12<>"",(RIGHT(W12,LEN(W12)-SEARCH("/",W12,1)))/U12,"") -> #VALUE! | AI12: =IF(X12<>"",X12,"") -> 5.99 | AJ12: =IF(Y12<>"",Y12,"") | AK12: =IF(Z12<>"",Z12,"") -> 5.49 | BG12: 0005731621717 | BH12: 0057316217179 | BM12: CG MAPLE WALNUT ICE CREAM -NEW | BN12: 1.5 | BO12: LT | BQ12: #N/A | BR12: DNK | BS12: 16 | BT12: 3737.35 | BX12: 7.19 | BY12: 7.19 | BZ12: =BY12-BX12 -> 0 | CC12: =VLOOKUP(A12,'[1]RPT 1280 - Edmonton'!$1:$1048576,4,0) -> #N/A | CE12: EA | CF12: 21.14 | CG12: 0 | CH12: 0 | CI12: 0 | CJ12: =CF12-J12 -> 0 | CK12: =CG12-K12 -> 0 | CL12: =CH12-L12 -> 0 | CM12: =CI12-M12 -> 0
A13: 6500532 | B13: CG CHOC PEANUT BUTTER I/C -NEW 4 X 1.5 LT | C13: 010513110100 | D13: L M S | E13: A | F13: F | G13: F | J13: =J12 -> 21.14 | O13: =O12 -> 21.14 | P13: =P12 -> 5.285 | Q13: 3 | W13: 1 /4.99 | X13: 5.99 | Z13: 5.49 | AH13: =IF(W13<>"",(RIGHT(W13,LEN(W13)-SEARCH("/",W13,1)))/U13,"") -> #VALUE! | AI13: =IF(X13<>"",X13,"") -> 5.99 | AJ13: =IF(Y13<>"",Y13,"") | AK13: =IF(Z13<>"",Z13,"") -> 5.49 | BG13: 0005731621716 | BH13: 0057316217162 | BJ13: Co-op Gold Ice Cream or Frozen Yogurt 1.5 L or Novelties Package of 4 - 12 | BM13: CG CHOC PEANUT BUTTER I/C -NEW | BN13: 1.5 | BO13: LT | BQ13: #N/A | BR13: DNK | BS13: 14 | BT13: 10589.59 | BX13: 7.19 | BY13: 7.19 | BZ13: =BY13-BX13 -> 0 | CC13: =VLOOKUP(A13,'[1]RPT 1280 - Edmonton'!$1:$1048576,4,0) -> #N/A | CE13: EA | CF13: 21.14 | CG13: 0 | CH13: 0 | CI13: 0 | CJ13: =CF13-J13 -> 0 | CK13: =CG13-K13 -> 0 | CL13: =CH13-L13 -> 0 | CM13: =CI13-M13 -> 0
A14: 6500649 | B14: CG STRWBRRIES & CREME I/C -NEW 4 X 1.5 LT | C14: 010513110100 | D14: L M S | E14: A | F14: F | G14: F | J14: =J13 -> 21.14 | O14: =O13 -> 21.14 | P14: =P13 -> 5.285 | Q14: 3 | W14: 1 /4.99 | X14: 5.99 | Z14: 5.49 | AH14: =IF(W14<>"",(RIGHT(W14,LEN(W14)-SEARCH("/",W14,1)))/U14,"") -> #VALUE! | AI14: =IF(X14<>"",X14,"") -> 5.99 | AJ14: =IF(Y14<>"",Y14,"") | AK14: =IF(Z14<>"",Z14,"") -> 5.49 | BG14: 0005731621720 | BH14: 0057316217209 | BM14: CG STRWBRRIES & CREME I/C -NEW | BN14: 1.5 | BO14: LT | BQ14: #N/A | BR14: DNK | BS14: 20 | BT14: 3063.44 | BX14: 7.19 | BY14: 7.19 | BZ14: =BY14-BX14 -> 0 | CC14: =VLOOKUP(A14,'[1]RPT 1280 - Edmonton'!$1:$1048576,4,0) -> #N/A | CE14: EA | CF14: 21.14 | CG14: 0 | CH14: 0 | CI14: 0 | CJ14: =CF14-J14 -> 0 | CK14: =CG14-K14 -> 0 | CL14: =CH14-L14 -> 0 | CM14: =CI14-M14 -> 0
A15: 6500573 | B15: CG VANILLA NSA ICE CREAM -NEW 4 X 1.5 LT | C15: 010513110100 | D15: L M S | E15: A | F15: F | G15: F | J15: =J14 -> 21.14 | O15: =O14 -> 21.14 | P15: =P14 -> 5.285 | Q15: 3 | W15: 1 /4.99 | X15: 5.99 | Z15: 5.49 | AH15: =IF(W15<>"",(RIGHT(W15,LEN(W15)-SEARCH("/",W15,1)))/U15,"") -> #VALUE! | AI15: =IF(X15<>"",X15,"") -> 5.99 | AJ15: =IF(Y15<>"",Y15,"") | AK15: =IF(Z15<>"",Z15,"") -> 5.49 | BG15: 0005731621719 | BH15: 0057316217193 | BM15: CG VANILLA NSA ICE CREAM -NEW | BN15: 1.5 | BO15: LT | BQ15: #N/A | BR15: DNK | BS15: 31 | BT15: 2778.49 | BX15: 7.19 | BY15: 7.19 | BZ15: =BY15-BX15 -> 0 | CC15: =VLOOKUP(A15,'[1]RPT 1280 - Edmonton'!$1:$1048576,4,0) -> #N/A | CE15: EA | CF15: 21.14 | CG15: 0 | CH15: 0 | CI15: 0 | CJ15: =CF15-J15 -> 0 | CK15: =CG15-K15 -> 0 | CL15: =CH15-L15 -> 0 | CM15: =CI15-M15 -> 0
A16: 6500706 | B16: CG VANILLA FROZEN YOGURT -NEW 4 X 1.5 LT | C16: 010513110100 | D16: L M S | E16: A | F16: F | G16: F | J16: =J15 -> 21.14 | O16: =O15 -> 21.14 | P16: =P15 -> 5.285 | Q16: 3 | W16: 1 /4.99 | X16: 5.99 | Z16: 5.49 | AH16: =IF(W16<>"",(RIGHT(W16,LEN(W16)-SEARCH("/",W16,1)))/U16,"") -> #VALUE! | AI16: =IF(X16<>"",X16,"") -> 5.99 | AJ16: =IF(Y16<>"",Y16,"") | AK16: =IF(Z16<>"",Z16,"") -> 5.49 | BG16: 0005731621749 | BH16: 0057316217490 | BM16: CG VANILLA FROZEN YOGURT -NEW | BN16: 1.5 | BO16: LT | BQ16: #N/A | BR16: DNK | BS16: 33 | BT16: 2095.96 | BX16: 7.19 | BY16: 7.19 | BZ16: =BY16-BX16 -> 0 | CC16: =VLOOKUP(A16,'[1]RPT 1280 - Edmonton'!$1:$1048576,4,0) -> #N/A | CE16: EA | CF16: 21.14 | CG16: 0 | CH16: 0 | CI16: 0 | CJ16: =CF16-J16 -> 0 | CK16: =CG16-K16 -> 0 | CL16: =CH16-L16 -> 0 | CM16: =CI16-M16 -> 0
A17: 6500698 | B17: CG HEAVENLY HASH I/CREAM -NEW 4 X 1.5 LT | C17: 010513110100 | D17: L M S | E17: A | F17: F | G17: F | J17: =J16 -> 21.14 | O17: =O16 -> 21.14 | P17: =P16 -> 5.285 | Q17: 3 | W17: 1 /4.99 | X17: 5.99 | Z17: 5.49 | AH17: =IF(W17<>"",(RIGHT(W17,LEN(W17)-SEARCH("/",W17,1)))/U17,"") -> #VALUE! | AI17: =IF(X17<>"",X17,"") -> 5.99 | AJ17: =IF(Y17<>"",Y17,"") | AK17: =IF(Z17<>"",Z17,"") -> 5.49 | BG17: 0005731621724 | BH17: 0057316217247 | BM17: CG HEAVENLY HASH I/CREAM -NEW | BN17: 1.5 | BO17: LT | BQ17: #N/A | BR17: DNK | BS17: 26 | BT17: 3519.2 | BX17: 7.19 | BY17: 7.19 | BZ17: =BY17-BX17 -> 0 | CC17: =VLOOKUP(A17,'[1]RPT 1280 - Edmonton'!$1:$1048576,4,0) -> #N/A | CE17: EA | CF17: 21.14 | CG17: 0 | CH17: 0 | CI17: 0 | CJ17: =CF17-J17 -> 0 | CK17: =CG17-K17 -> 0 | CL17: =CH17-L17 -> 0 | CM17: =CI17-M17 -> 0
A18: 6500664 | B18: CG BUTTERSCTCH CRUNCH I/C -NEW 4 X 1.5 LT | C18: 010513110100 | D18: L M S | E18: A | F18: F | G18: F | J18: =J17 -> 21.14 | O18: =O17 -> 21.14 | P18: =P17 -> 5.285 | Q18: 3 | W18: 1 /4.99 | X18: 5.99 | Z18: 5.49 | AH18: =IF(W18<>"",(RIGHT(W18,LEN(W18)-SEARCH("/",W18,1)))/U18,"") -> #VALUE! | AI18: =IF(X18<>"",X18,"") -> 5.99 | AJ18: =IF(Y18<>"",Y18,"") | AK18: =IF(Z18<>"",Z18,"") -> 5.49 | BG18: 0005731621722 | BH18: 0057316217223 | BM18: CG BUTTERSCTCH CRUNCH I/C -NEW | BN18: 1.5 | BO18: LT | BQ18: #N/A | BR18: DNK | BS18: 19 | BT18: 5243.89 | BX18: 7.19 | BY18: 7.19 | BZ18: =BY18-BX18 -> 0 | CC18: =VLOOKUP(A18,'[1]RPT 1280 - Edmonton'!$1:$1048576,4,0) -> #N/A | CE18: EA | CF18: 21.14 | CG18: 0 | CH18: 0 | CI18: 0 | CJ18: =CF18-J18 -> 0 | CK18: =CG18-K18 -> 0 | CL18: =CH18-L18 -> 0 | CM18: =CI18-M18 -> 0
A19: 6500656 | B19: CG CHOCOLATE EXPLSION I/C -NEW 4 X 1.5 LT | C19: 010513110100 | D19: L M S | E19: A | F19: F | G19: F | J19: =J18 -> 21.14 | O19: =O18 -> 21.14 | P19: =P18 -> 5.285 | Q19: 3 | W19: 1 /4.99 | X19: 5.99 | Z19: 5.49 | AH19: =IF(W19<>"",(RIGHT(W19,LEN(W19)-SEARCH("/",W19,1)))/U19,"") -> #VALUE! | AI19: =IF(X19<>"",X19,"") -> 5.99 | AJ19: =IF(Y19<>"",Y19,"") | AK19: =IF(Z19<>"",Z19,"") -> 5.49 | BG19: 0005731621721 | BH19: 0057316217216 | BM19: CG CHOCOLATE EXPLSION I/C -NEW | BN19: 1.5 | BO19: LT | BQ19: #N/A | BR19: DNK | BS19: 19 | BT19: 4091.36 | BX19: 7.19 | BY19: 7.19 | BZ19: =BY19-BX19 -> 0 | CC19: =VLOOKUP(A19,'[1]RPT 1280 - Edmonton'!$1:$1048576,4,0) -> #N/A | CE19: EA | CF19: 21.14 | CG19: 0 | CH19: 0 | CI19: 0 | CJ19: =CF19-J19 -> 0 | CK19: =CG19-K19 -> 0 | CL19: =CH19-L19 -> 0 | CM19: =CI19-M19 -> 0
A20: 6500714 | B20: CG STRWBRY FROZEN YOGURT -NEW 4 X 1.5 LT | C20: 010513110100 | D20: L M S | E20: A | F20: F | G20: F | J20: =J19 -> 21.14 | O20: =O19 -> 21.14 | P20: =P19 -> 5.285 | Q20: 3 | W20: 1 /4.99 | X20: 5.99 | Z20: 5.49 | AH20: =IF(W20<>"",(RIGHT(W20,LEN(W20)-SEARCH("/",W20,1)))/U20,"") -> #VALUE! | AI20: =IF(X20<>"",X20,"") -> 5.99 | AJ20: =IF(Y20<>"",Y20,"") | AK20: =IF(Z20<>"",Z20,"") -> 5.49 | BG20: 0005731621748 | BH20: 0057316217483 | BM20: CG STRWBRY FROZEN YOGURT -NEW | BN20: 1.5 | BO20: LT | BQ20: #N/A | BR20: DNK | BS20: 37 | BT20: 1266.63 | BX20: 7.19 | BY20: 7.19 | BZ20: =BY20-BX20 -> 0 | CC20: =VLOOKUP(A20,'[1]RPT 1280 - Edmonton'!$1:$1048576,4,0) -> #N/A | CE20: EA | CF20: 21.14 | CG20: 0 | CH20: 0 | CI20: 0 | CJ20: =CF20-J20 -> 0 | CK20: =CG20-K20 -> 0 | CL20: =CH20-L20 -> 0 | CM20: =CI20-M20 -> 0
A21: 6500979 | B21: C.GOLD UNICORN IC POP -Z 4 X 12 EA | C21: 010518110105 | D21: L M S | E21: A | F21: F | G21: F | I21: ALL | J21: 19.86 | O21: 19.86 | P21: 4.965 | Q21: 2 | T21: 1 / $4.99 | U21: 1 | V21: $4.99 | W21: 1 /4.99 | X21: 5.99 | Z21: 5.49 | AA21: 0.032561122 | AC21: 5.99 | AD21: 7.19 | AE21: 6.19 | AF21: 7.19 | AH21: =IF(W21<>"",(RIGHT(W21,LEN(W21)-SEARCH("/",W21,1)))/U21,"") -> 4.99 | AI21: =IF(X21<>"",X21,"") -> 5.99 | AJ21: =IF(Y21<>"",Y21,"") | AK21: =IF(Z21<>"",Z21,"") -> 5.49 | AM21: 19.96 | AN21: 7.6 | AO21: 4 | AP21: =(AM21 * 1.05) - L21 - Q21 - K21 -> 18.958 | AQ21: N | AR21: =(((AH21)-((AP21/AO21) + ((AN21 * 0.03)/AO21)))/AH21)*100 -> 3.8777555 | AS21: =(((AI21)-((AP21/AO21) + ((AN21 * 0.3)/AO21)))/AI21)*100 -> 11.360601 | AT21: =(((AJ21)-((AP21/AO21) + ((AN21 * 0.03)/AO21)))/AJ21)*100 -> #VALUE! | AU21: =(((AK21)-((AP21/AO21) + ((AN21 * 0.07)/AO21)))/AK21)*100 -> 11.247723 | BB21: =(((AH21)-(((AP21/AO21) + ((AN21 * 0.03)/AO21))-AW21))/AH21)*100 -> 3.8777555 | BC21: =(((AI21)-(((AP21/AO21) + ((AN21 * 0.3)/AO21))-AX21))/AI21)*100 -> 11.360601 | BD21: =(((AJ21)-(((AP21/AO21) + ((AN21 * 0.03)/AO21))-AY21))/AJ21)*100 -> #VALUE! | BE21: =(((AK21)-(((AP21/AO21) + ((AN21 * 0.15)/AO21))-AZ21))/AK21)*100 -> 8.4790528 | BG21: 0005731621584 | BH21: 0057316215847 | BJ21: Co-op Gold Ice Cream or Frozen Yogurt 1.5 L or Novelties Package of 4 - 12 | BM21: C.GOLD UNICORN IC POP -Z | BN21: 12 | BO21: EA | BQ21: #N/A | BR21: DNK | BS21: 49 | BT21: 674.89 | BX21: 8.29 | BY21: 7.79 | BZ21: =BY21-BX21 -> -0.5 | CC21: =VLOOKUP(A21,'[1]RPT 1280 - Edmonton'!$1:$1048576,4,0) -> #N/A | CE21: EA | CF21: 19.86 | CG21: 0 | CH21: 0 | CI21: 0 | CJ21: =CF21-J21 -> 0 | CK21: =CG21-K21 -> 0 | CL21: =CH21-L21 -> 0 | CM21: =CI21-M21 -> 0 | CO21: 4.99 | CP21: 4.99 | CQ21: =CP21-CO21 -> 0
A22: 6500680 | B22: CG CHERRIES & CHOC I/CRM -NEW 4 X 1.5 LT | C22: 010513110100 | D22: L M S | E22: A | F22: F | G22: F | I22: ALL | J22: 20.51 | O22: 20.51 | P22: 5.1275 | Q22: 3 | T22: 1 / $4.99 | U22: 1 | V22: $4.99 | W22: 1 /4.99 | X22: 5.99 | Z22: 5.49 | AA22: 0.029427355 | AC22: 5.99 | AD22: 7.19 | AE22: 6.19 | AF22: 7.19 | AH22: =IF(W22<>"",(RIGHT(W22,LEN(W22)-SEARCH("/",W22,1)))/U22,"") -> 4.99 | AI22: =IF(X22<>"",X22,"") -> 5.99 | AJ22: =IF(Y22<>"",Y22,"") | AK22: =IF(Z22<>"",Z22,"") -> 5.49 | AM22: 22.64 | AN22: 8.44 | AO22: 4 | AP22: =(AM22 * 1.05) - L22 - Q22 - K22 -> 20.772 | AQ22: N | AR22: =(((AH22)-((AP22/AO22) + ((AN22 * 0.03)/AO22)))/AH22)*100 -> -5.3366733 | AS22: =(((AI22)-((AP22/AO22) + ((AN22 * 0.3)/AO22)))/AI22)*100 -> 2.7378965 | AT22: =(((AJ22)-((AP22/AO22) + ((AN22 * 0.03)/AO22)))/AJ22)*100 -> #VALUE! | AU22: =(((AK22)-((AP22/AO22) + ((AN22 * 0.07)/AO22)))/AK22)*100 -> 2.71949 | BB22: =(((AH22)-(((AP22/AO22) + ((AN22 * 0.03)/AO22))-AW22))/AH22)*100 -> -5.3366733 | BC22: =(((AI22)-(((AP22/AO22) + ((AN22 * 0.3)/AO22))-AX22))/AI22)*100 -> 2.7378965 | BD22: =(((AJ22)-(((AP22/AO22) + ((AN22 * 0.03)/AO22))-AY22))/AJ22)*100 -> #VALUE! | BE22: =(((AK22)-(((AP22/AO22) + ((AN22 * 0.15)/AO22))-AZ22))/AK22)*100 -> -0.35519126 | BG22: 0005731621723 | BH22: 0057316217230 | BM22: CG CHERRIES & CHOC I/CRM -NEW | BN22: 1.5 | BO22: LT | BQ22: #N/A | BR22: DNK | BX22: 7.19 | BY22: 7.19 | BZ22: =BY22-BX22 -> 0 | CC22: =VLOOKUP(A22,'[1]RPT 1280 - Edmonton'!$1:$1048576,4,0) -> #N/A | CE22: EA | CF22: 20.51 | CG22: 0 | CH22: 0 | CI22: 0 | CJ22: =CF22-J22 -> 0 | CK22: =CG22-K22 -> 0 | CL22: =CH22-L22 -> 0 | CM22: =CI22-M22 -> 0 | CO22: 4.99 | CP22: 4.99 | CQ22: =CP22-CO22 -> 0
A23: 6520761 | B23: CG SSNL CREME BRULEE I/C -Z 4 X 1.5 LT | C23: 010513110107 | D23: L M S | E23: A | F23: F | G23: F | I23: ALL | J23: 22.02 | O23: 22.02 | P23: 5.505 | Q23: 3 | T23: 1 / $4.99 | U23: 1 | V23: $4.99 | W23: 1 /4.99 | X23: 5.99 | Z23: 5.49 | AA23: 0.029616232 | AC23: 5.99 | AD23: 7.19 | AE23: 6.19 | AF23: 7.19 | AH23: =IF(W23<>"",(RIGHT(W23,LEN(W23)-SEARCH("/",W23,1)))/U23,"") -> 4.99 | AI23: =IF(X23<>"",X23,"") -> 5.99 | AJ23: =IF(Y23<>"",Y23,"") | AK23: =IF(Z23<>"",Z23,"") -> 5.49 | AM23: 23.67 | AN23: 6.98 | AO23: 4 | AP23: =(AM23 * 1.05) - L23 - Q23 - K23 -> 21.8535 | AQ23: N | AR23: =(((AH23)-((AP23/AO23) + ((AN23 * 0.03)/AO23)))/AH23)*100 -> -10.535571 | AS23: =(((AI23)-((AP23/AO23) + ((AN23 * 0.3)/AO23)))/AI23)*100 -> 0.052170284 | AT23: =(((AJ23)-((AP23/AO23) + ((AN23 * 0.03)/AO23)))/AJ23)*100 -> #VALUE! | AU23: =(((AK23)-((AP23/AO23) + ((AN23 * 0.07)/AO23)))/AK23)*100 -> -1.7399818 | BB23: =(((AH23)-(((AP23/AO23) + ((AN23 * 0.03)/AO23))-AW23))/AH23)*100 -> -10.535571 | BC23: =(((AI23)-(((AP23/AO23) + ((AN23 * 0.3)/AO23))-AX23))/AI23)*100 -> 0.052170284 | BD23: =(((AJ23)-(((AP23/AO23) + ((AN23 * 0.03)/AO23))-AY23))/AJ23)*100 -> #VALUE! | BE23: =(((AK23)-(((AP23/AO23) + ((AN23 * 0.15)/AO23))-AZ23))/AK23)*100 -> -4.2827869 | BG23: 0005731621845 | BH23: 0057316218459 | BI23: disc-d status | BM23: CG SSNL CREME BRULEE I/C -Z | BN23: 1.5 | BO23: LT | BQ23: #N/A | BR23: DNK | BX23: 7.19 | BY23: 7.19 | BZ23: =BY23-BX23 -> 0 | CC23: =VLOOKUP(A23,'[1]RPT 1280 - Edmonton'!$1:$1048576,4,0) -> #N/A | CE23: EA | CF23: 22.02 | CG23: 0 | CH23: 0 | CI23: 0 | CJ23: =CF23-J23 -> 0 | CK23: =CG23-K23 -> 0 | CL23: =CH23-L23 -> 0 | CM23: =CI23-M23 -> 0 | CO23: 4.99 | CP23: 4.99 | CQ23: =CP23-CO23 -> 0
A24: 6520753 | B24: CG SSNL PUMPKIN CHAI I/C -Z 4 X 1.5 LT | C24: 010513110107 | D24: L M S | E24: A | F24: F | G24: F | J24: =J23 -> 22.02 | O24: =O23 -> 22.02 | P24: =P23 -> 5.505 | Q24: 4 | W24: 1 /4.99 | X24: 5.99 | Z24: 5.49 | AH24: =IF(W24<>"",(RIGHT(W24,LEN(W24)-SEARCH("/",W24,1)))/U24,"") -> #VALUE! | AI24: =IF(X24<>"",X24,"") -> 5.99 | AJ24: =IF(Y24<>"",Y24,"") | AK24: =IF(Z24<>"",Z24,"") -> 5.49 | BG24: 0005731621846 | BH24: 0057316218466 | BM24: CG SSNL PUMPKIN CHAI I/C -Z | BN24: 1.5 | BO24: LT | BQ24: #N/A | BR24: DNK | BX24: 7.19 | BY24: 7.19 | BZ24: =BY24-BX24 -> 0 | CC24: =VLOOKUP(A24,'[1]RPT 1280 - Edmonton'!$1:$1048576,4,0) -> #N/A | CE24: EA | CF24: 22.02 | CG24: 0 | CH24: 0 | CI24: 0 | CJ24: =CF24-J24 -> 0 | CK24: =CG24-K24 -> 0 | CL24: =CH24-L24 -> 0 | CM24: =CI24-M24 -> 0
A25: 6524789 | B25: C.GOLD CHC ALMD I/C BAR 4PK 8 X 4 EA | C25: 010518110106 | D25: L M S | E25: A | F25: F | G25: F | I25: ALL | J25: 37.44 | O25: 37.44 | P25: 4.68 | Q25: 2 | T25: 1 / $4.99 | U25: 1 | V25: $4.99 | W25: 1 /4.99 | X25: 5.99 | Z25: 5.49 | AA25: 0.02909519 | AC25: 5.99 | AD25: 7.19 | AE25: 6.19 | AF25: 7.19 | AH25: =IF(W25<>"",(RIGHT(W25,LEN(W25)-SEARCH("/",W25,1)))/U25,"") -> 4.99 | AI25: =IF(X25<>"",X25,"") -> 5.99 | AJ25: =IF(Y25<>"",Y25,"") | AK25: =IF(Z25<>"",Z25,"") -> 5.49 | AM25: 37.73 | AN25: 5.21 | AO25: 8 | AP25: =(AM25 * 1.05) - L25 - Q25 - K25 -> 37.6165 | AQ25: N | AR25: =(((AH25)-((AP25/AO25) + ((AN25 * 0.03)/AO25)))/AH25)*100 -> 5.3787575 | AS25: =(((AI25)-((AP25/AO25) + ((AN25 * 0.3)/AO25)))/AI25)*100 -> 18.239775 | AT25: =(((AJ25)-((AP25/AO25) + ((AN25 * 0.03)/AO25)))/AJ25)*100 -> #VALUE! | AU25: =(((AK25)-((AP25/AO25) + ((AN25 * 0.07)/AO25)))/AK25)*100 -> 13.521858 | BB25: =(((AH25)-(((AP25/AO25) + ((AN25 * 0.03)/AO25))-AW25))/AH25)*100 -> 5.3787575 | BC25: =(((AI25)-(((AP25/AO25) + ((AN25 * 0.3)/AO25))-AX25))/AI25)*100 -> 18.239775 | BD25: =(((AJ25)-(((AP25/AO25) + ((AN25 * 0.03)/AO25))-AY25))/AJ25)*100 -> #VALUE! | BE25: =(((AK25)-(((AP25/AO25) + ((AN25 * 0.15)/AO25))-AZ25))/AK25)*100 -> 12.57286 | BG25: 0005731621673 | BH25: 0057316216738 | BJ25: Co-op Gold Ice Cream or Frozen Yogurt 1.5 L or Novelties Package of 4 - 12 | BM25: C.GOLD CHC ALMD I/C BAR 4PK | BN25: 4 | BO25: EA | BQ25: #N/A | BR25: DNK | BX25: 7.29 | BY25: 7.29 | BZ25: =BY25-BX25 -> 0 | CC25: =VLOOKUP(A25,'[1]RPT 1280 - Edmonton'!$1:$1048576,4,0) -> #N/A | CE25: EA | CF25: 37.44 | CG25: 0 | CH25: 0 | CI25: 0 | CJ25: =CF25-J25 -> 0 | CK25: =CG25-K25 -> 0 | CL25: =CH25-L25 -> 0 | CM25: =CI25-M25 -> 0 | CO25: 4.99 | CP25: 4.99 | CQ25: =CP25-CO25 -> 0
A26: 6524839 | B26: C.GOLD PRALINE I/C BAR 4PK 8 X 4 EA | C26: 010518110106 | D26: L M S | E26: A | F26: F | G26: F | J26: =J25 -> 37.44 | O26: =O25 -> 37.44 | P26: =P25 -> 4.68 | Q26: 2 | W26: 1 /4.99 | X26: 5.99 | Z26: 5.49 | AH26: =IF(W26<>"",(RIGHT(W26,LEN(W26)-SEARCH("/",W26,1)))/U26,"") -> #VALUE! | AI26: =IF(X26<>"",X26,"") -> 5.99 | AJ26: =IF(Y26<>"",Y26,"") | AK26: =IF(Z26<>"",Z26,"") -> 5.49 | BG26: 0005731621675 | BH26: 0057316216752 | BJ26: Co-op Gold Ice Cream or Frozen Yogurt 1.5 L or Novelties Package of 4 - 12 | BM26: C.GOLD PRALINE I/C BAR 4PK | BN26: 4 | BO26: EA | BQ26: #N/A | BR26: DNK | BX26: 7.29 | BY26: 7.29 | BZ26: =BY26-BX26 -> 0 | CC26: =VLOOKUP(A26,'[1]RPT 1280 - Edmonton'!$1:$1048576,4,0) -> #N/A | CE26: EA | CF26: 37.44 | CG26: 0 | CH26: 0 | CI26: 0 | CJ26: =CF26-J26 -> 0 | CK26: =CG26-K26 -> 0 | CL26: =CH26-L26 -> 0 | CM26: =CI26-M26 -> 0
A27: 6524813 | B27: C.GOLD DARK CHC I/C BAR 4PK 8 X 4 EA | C27: 010518110106 | D27: L M S | E27: A | F27: F | G27: F | J27: =J26 -> 37.44 | O27: =O26 -> 37.44 | P27: =P26 -> 4.68 | Q27: 2 | W27: 1 /4.99 | X27: 5.99 | Z27: 5.49 | AH27: =IF(W27<>"",(RIGHT(W27,LEN(W27)-SEARCH("/",W27,1)))/U27,"") -> #VALUE! | AI27: =IF(X27<>"",X27,"") -> 5.99 | AJ27: =IF(Y27<>"",Y27,"") | AK27: =IF(Z27<>"",Z27,"") -> 5.49 | BG27: 0005731621674 | BH27: 0057316216745 | BJ27: Co-op Gold Ice Cream or Frozen Yogurt 1.5 L or Novelties Package of 4 - 12 | BM27: C.GOLD DARK CHC I/C BAR 4PK | BN27: 4 | BO27: EA | BQ27: #N/A | BR27: DNK | BX27: 7.29 | BY27: 7.29 | BZ27: =BY27-BX27 -> 0 | CC27: =VLOOKUP(A27,'[1]RPT 1280 - Edmonton'!$1:$1048576,4,0) -> #N/A | CE27: EA | CF27: 37.44 | CG27: 0 | CH27: 0 | CI27: 0 | CJ27: =CF27-J27 -> 0 | CK27: =CG27-K27 -> 0 | CL27: =CH27-L27 -> 0 | CM27: =CI27-M27 -> 0
A28: 6524805 | B28: C.GOLD MILK CHOC VAN BAR 4PK 8 X 4 EA | C28: 010518110106 | D28: L M S | E28: A | F28: F | G28: F | I28: ALL | J28: 36.77 | O28: 36.77 | P28: 4.59625 | Q28: 2 | T28: 1 / $4.99 | U28: 1 | V28: $4.99 | W28: 1 /4.99 | X28: 5.99 | Z28: 5.49 | AA28: 0.030994238 | AC28: 5.99 | AD28: 7.19 | AE28: 6.19 | AF28: 7.19 | AH28: =IF(W28<>"",(RIGHT(W28,LEN(W28)-SEARCH("/",W28,1)))/U28,"") -> 4.99 | AI28: =IF(X28<>"",X28,"") -> 5.99 | AJ28: =IF(Y28<>"",Y28,"") | AK28: =IF(Z28<>"",Z28,"") -> 5.49 | AM28: 37.73 | AN28: 5.21 | AO28: 8 | AP28: =(AM28 * 1.05) - L28 - Q28 - K28 -> 37.6165 | AQ28: N | AR28: =(((AH28)-((AP28/AO28) + ((AN28 * 0.03)/AO28)))/AH28)*100 -> 5.3787575 | AS28: =(((AI28)-((AP28/AO28) + ((AN28 * 0.3)/AO28)))/AI28)*100 -> 18.239775 | AT28: =(((AJ28)-((AP28/AO28) + ((AN28 * 0.03)/AO28)))/AJ28)*100 -> #VALUE! | AU28: =(((AK28)-((AP28/AO28) + ((AN28 * 0.07)/AO28)))/AK28)*100 -> 13.521858 | BB28: =(((AH28)-(((AP28/AO28) + ((AN28 * 0.03)/AO28))-AW28))/AH28)*100 -> 5.3787575 | BC28: =(((AI28)-(((AP28/AO28) + ((AN28 * 0.3)/AO28))-AX28))/AI28)*100 -> 18.239775 | BD28: =(((AJ28)-(((AP28/AO28) + ((AN28 * 0.03)/AO28))-AY28))/AJ28)*100 -> #VALUE! | BE28: =(((AK28)-(((AP28/AO28) + ((AN28 * 0.15)/AO28))-AZ28))/AK28)*100 -> 12.57286 | BG28: 0005731621672 | BH28: 0057316216721 | BJ28: Co-op Gold Ice Cream or Frozen Yogurt 1.5 L or Novelties Package of 4 - 12 | BM28: C.GOLD MILK CHOC VAN BAR 4PK | BN28: 4 | BO28: EA | BQ28: #N/A | BR28: DNK | BX28: 7.29 | BY28: 7.29 | BZ28: =BY28-BX28 -> 0 | CC28: =VLOOKUP(A28,'[1]RPT 1280 - Edmonton'!$1:$1048576,4,0) -> #N/A | CE28: EA | CF28: 36.77 | CG28: 0 | CH28: 0 | CI28: 0 | CJ28: =CF28-J28 -> 0 | CK28: =CG28-K28 -> 0 | CL28: =CH28-L28 -> 0 | CM28: =CI28-M28 -> 0 | CO28: 4.99 | CP28: 4.99 | CQ28: =CP28-CO28 -> 0
A29: 6546832 | B29: CG RASPBERRY LEMON SORBET | E29: A | Q29: 2 | W29: 1 /4.99 | X29: 5.99 | Z29: 5.49 | BY29: 7.29 | BZ29: =BY29-BX29 -> 7.29 | CC29: =VLOOKUP(A29,'[1]RPT 1280 - Edmonton'!$1:$1048576,4,0) -> #N/A
A30: 6546840 | B30: CG DRGNFRT MANGO SORBET | E30: A | Q30: 2 | W30: 1 /4.99 | X30: 5.99 | Z30: 5.49 | BY30: 7.29 | BZ30: =BY30-BX30 -> 7.29 | CC30: =VLOOKUP(A30,'[1]RPT 1280 - Edmonton'!$1:$1048576,4,0) -> #N/A
A31: 216713 | B31: FRISKIES CHEF'S BLEND 1 X 7.5 KG | C31: 010132130390 | D31: L M S | E31: D | F31: F | G31: F | I31: E | J31: 21.98 | M31: 4 | O31: 21.98 | P31: 21.98 | Q31: 4 | T31: 1 / $20.99 | U31: 1 | V31: $20.99 | W31: 1/26.99 | X31: 32.99 | Z31: 27.99 | AA31: 0.10080515 | AC31: 25.19 | AD31: 30.19 | AE31: 26.59 | AF31: 28.79 | AH31: =IF(W31<>"",(RIGHT(W31,LEN(W31)-SEARCH("/",W31,1)))/U31,"") -> 26.99 | AI31: =IF(X31<>"",X31,"") -> 32.99 | AJ31: =IF(Y31<>"",Y31,"") | AK31: =IF(Z31<>"",Z31,"") -> 27.99 | AM31: 22.6 | AN31: 16.86 | AO31: 1 | AP31: =(AM31 * 1.05) - L31 - Q31 - K31 -> 19.73 | AQ31: N | AR31: =(((AH31)-((AP31/AO31) + ((AN31 * 0.03)/AO31)))/AH31)*100 -> 25.024824 | AS31: =(((AI31)-((AP31/AO31) + ((AN31 * 0.3)/AO31)))/AI31)*100 -> 24.862079 | AT31: =(((AJ31)-((AP31/AO31) + ((AN31 * 0.03)/AO31)))/AJ31)*100 -> #VALUE! | AU31: =(((AK31)-((AP31/AO31) + ((AN31 * 0.07)/AO31)))/AK31)*100 -> 25.294034 | BB31: =(((AH31)-(((AP31/AO31) + ((AN31 * 0.03)/AO31))-AW31))/AH31)*100 -> 25.024824 | BC31: =(((AI31)-(((AP31/AO31) + ((AN31 * 0.3)/AO31))-AX31))/AI31)*100 -> 24.862079 | BD31: =(((AJ31)-(((AP31/AO31) + ((AN31 * 0.03)/AO31))-AY31))/AJ31)*100 -> #VALUE! | BE31: =(((AK31)-(((AP31/AO31) + ((AN31 * 0.15)/AO31))-AZ31))/AK31)*100 -> 20.47517 | BG31: 0005580022392 | BH31: 0055800223920 | BJ31: Friskies Cat Food 7.26 - 7.5 kg | BM31: FRISKIES CHEF S BLEND | BN31: 7.5 | BO31: KG | BQ31: #N/A | BR31: #N/A | BS31: 26 | BT31: 44923.88 | BV31: 216713 | BX31: 27.49 | BY31: 27.49 | BZ31: =BY31-BX31 -> 0 | CA31: -2.4 | CC31: =VLOOKUP(A31,'[1]RPT 1280 - Edmonton'!$1:$1048576,4,0) -> #N/A | CE31: AA | CF31: 21.98 | CG31: 0 | CH31: 0 | CI31: 4 | CJ31: =CF31-J31 -> 0 | CK31: =CG31-K31 -> 0 | CL31: =CH31-L31 -> 0 | CM31: =CI31-M31 -> 0 | CO31: 20.99 | CP31: 20.99 | CQ31: =CP31-CO31 -> 0
A32: 6240923 | B32: FRISKIES 7 FLAVOUR CAT FD 1 X 7.26 KG | C32: 010132130390 | D32: L M S | E32: D | F32: F | G32: F | I32: S | J32: 21.98 | M32: 4 | O32: 21.98 | P32: 21.98 | Q32: 4 | T32: 1 / $20.99 | U32: 1 | V32: $20.99 | W32: 1/26.99 | X32: 32.99 | Z32: 27.99 | AA32: 0.059483087 | AC32: 25.19 | AD32: 30.19 | AE32: 26.59 | AF32: 28.79 | AH32: =IF(W32<>"",(RIGHT(W32,LEN(W32)-SEARCH("/",W32,1)))/U32,"") -> 26.99 | AI32: =IF(X32<>"",X32,"") -> 32.99 | AJ32: =IF(Y32<>"",Y32,"") | AK32: =IF(Z32<>"",Z32,"") -> 27.99 | AM32: 22.6 | AN32: 16.86 | AO32: 1 | AP32: =(AM32 * 1.05) - L32 - Q32 - K32 -> 19.73 | AQ32: N | AR32: =(((AH32)-((AP32/AO32) + ((AN32 * 0.03)/AO32)))/AH32)*100 -> 25.024824 | AS32: =(((AI32)-((AP32/AO32) + ((AN32 * 0.3)/AO32)))/AI32)*100 -> 24.862079 | AT32: =(((AJ32)-((AP32/AO32) + ((AN32 * 0.03)/AO32)))/AJ32)*100 -> #VALUE! | AU32: =(((AK32)-((AP32/AO32) + ((AN32 * 0.07)/AO32)))/AK32)*100 -> 25.294034 | BB32: =(((AH32)-(((AP32/AO32) + ((AN32 * 0.03)/AO32))-AW32))/AH32)*100 -> 25.024824 | BC32: =(((AI32)-(((AP32/AO32) + ((AN32 * 0.3)/AO32))-AX32))/AI32)*100 -> 24.862079 | BD32: =(((AJ32)-(((AP32/AO32) + ((AN32 * 0.03)/AO32))-AY32))/AJ32)*100 -> #VALUE! | BE32: =(((AK32)-(((AP32/AO32) + ((AN32 * 0.15)/AO32))-AZ32))/AK32)*100 -> 20.47517 | BG32: 0005580024905 | BH32: 0055800249050 | BJ32: Friskies Cat Food 7.26 - 7.5 kg | BM32: FRISKIES 7 FLAVOUR CAT FD | BN32: 7.26 | BO32: KG | BQ32: #N/A | BR32: #N/A | BS32: 29 | BT32: 31146.39 | BV32: 6240923 | BX32: 27.49 | BY32: 27.49 | BZ32: =BY32-BX32 -> 0 | CA32: -2.4 | CC32: =VLOOKUP(A32,'[1]RPT 1280 - Edmonton'!$1:$1048576,4,0) -> #N/A | CE32: AA | CF32: 21.98 | CG32: 0 | CH32: 0 | CI32: 4 | CJ32: =CF32-J32 -> 0 | CK32: =CG32-K32 -> 0 | CL32: =CH32-L32 -> 0 | CM32: =CI32-M32 -> 0 | CO32: 20.99 | CP32: 20.99 | CQ32: =CP32-CO32 -> 0
A33: 6518336 | B33: FRISKIES GRLRS TNDR CRNCY 1 X 7.5 KG | C33: 010132130390 | D33: L M S | E33: D | F33: F | G33: F | I33: C | J33: 21.98 | M33: 4 | O33: 21.98 | P33: 21.98 | Q33: 4 | T33: 1 / $20.99 | U33: 1 | V33: $20.99 | W33: 1/26.99 | X33: 32.99 | Z33: 27.99 | AA33: 0.096822296 | AC33: 25.19 | AD33: 30.19 | AE33: 26.59 | AF33: 28.79 | AH33: =IF(W33<>"",(RIGHT(W33,LEN(W33)-SEARCH("/",W33,1)))/U33,"") -> 26.99 | AI33: =IF(X33<>"",X33,"") -> 32.99 | AJ33: =IF(Y33<>"",Y33,"") | AK33: =IF(Z33<>"",Z33,"") -> 27.99 | AM33: 22.6 | AN33: 16.86 | AO33: 1 | AP33: =(AM33 * 1.05) - L33 - Q33 - K33 -> 19.73 | AQ33: N | AR33: =(((AH33)-((AP33/AO33) + ((AN33 * 0.03)/AO33)))/AH33)*100 -> 25.024824 | AS33: =(((AI33)-((AP33/AO33) + ((AN33 * 0.3)/AO33)))/AI33)*100 -> 24.862079 | AT33: =(((AJ33)-((AP33/AO33) + ((AN33 * 0.03)/AO33)))/AJ33)*100 -> #VALUE! | AU33: =(((AK33)-((AP33/AO33) + ((AN33 * 0.07)/AO33)))/AK33)*100 -> 25.294034 | BB33: =(((AH33)-(((AP33/AO33) + ((AN33 * 0.03)/AO33))-AW33))/AH33)*100 -> 25.024824 | BC33: =(((AI33)-(((AP33/AO33) + ((AN33 * 0.3)/AO33))-AX33))/AI33)*100 -> 24.862079 | BD33: =(((AJ33)-(((AP33/AO33) + ((AN33 * 0.03)/AO33))-AY33))/AJ33)*100 -> #VALUE! | BE33: =(((AK33)-(((AP33/AO33) + ((AN33 * 0.15)/AO33))-AZ33))/AK33)*100 -> 20.47517 | BG33: 0005580019716 | BH33: 0055800197160 | BJ33: Friskies Cat Food 7.26 - 7.5 kg | BM33: FRISKIES GRLRS TNDR CRNCY | BN33: 7.5 | BO33: KG | BQ33: #N/A | BR33: #N/A | BS33: 54 | BT33: 85.98 | BV33: 6518336 | BX33: 27.49 | BY33: 27.49 | BZ33: =BY33-BX33 -> 0 | CC33: =VLOOKUP(A33,'[1]RPT 1280 - Edmonton'!$1:$1048576,4,0) -> #N/A | CE33: AA | CF33: 21.98 | CG33: 0 | CH33: 0 | CI33: 4 | CJ33: =CF33-J33 -> 0 | CK33: =CG33-K33 -> 0 | CL33: =CH33-L33 -> 0 | CM33: =CI33-M33 -> 0 | CO33: 20.99 | CP33: 20.99 | CQ33: =CP33-CO33 -> 0
A34: 6270805 | B34: TIDY CATS GLADE CLR SPR 1 X 5.44 KG | C34: 010134120270 | D34: L M S | E34: D | F34: F | G34: F | I34: ALL | J34: 20.68 | M34: 3 | O34: 20.68 | P34: 20.68 | Q34: 3 | T34: 1 / $20.99 | U34: 1 | V34: $20.99 | W34: 1/26.49 | X34: 30.99 | Z34: 27.49 | AA34: 0.11407337 | AC34: 25.19 | AD34: 30.19 | AE34: 26.59 | AF34: 28.79 | AH34: =IF(W34<>"",(RIGHT(W34,LEN(W34)-SEARCH("/",W34,1)))/U34,"") -> 26.49 | AI34: =IF(X34<>"",X34,"") -> 30.99 | AJ34: =IF(Y34<>"",Y34,"") | AK34: =IF(Z34<>"",Z34,"") -> 27.49 | AM34: 21.19 | AN34: 12 | AO34: 1 | AP34: =(AM34 * 1.05) - L34 - Q34 - K34 -> 19.2495 | AQ34: N | AR34: =(((AH34)-((AP34/AO34) + ((AN34 * 0.03)/AO34)))/AH34)*100 -> 25.973952 | AS34: =(((AI34)-((AP34/AO34) + ((AN34 * 0.3)/AO34)))/AI34)*100 -> 26.268151 | AT34: =(((AJ34)-((AP34/AO34) + ((AN34 * 0.03)/AO34)))/AJ34)*100 -> #VALUE! | AU34: =(((AK34)-((AP34/AO34) + ((AN34 * 0.07)/AO34)))/AK34)*100 -> 26.920698 | BB34: =(((AH34)-(((AP34/AO34) + ((AN34 * 0.03)/AO34))-AW34))/AH34)*100 -> 25.973952 | BC34: =(((AI34)-(((AP34/AO34) + ((AN34 * 0.3)/AO34))-AX34))/AI34)*100 -> 26.268151 | BD34: =(((AJ34)-(((AP34/AO34) + ((AN34 * 0.03)/AO34))-AY34))/AJ34)*100 -> #VALUE! | BE34: =(((AK34)-(((AP34/AO34) + ((AN34 * 0.15)/AO34))-AZ34))/AK34)*100 -> 23.428519 | BG34: 0005580038962 | BH34: 0055800389626 | BJ34: Purina Tidy Cats 5.44 kg | BM34: TIDY CATS GLADE CLR SPR | BN34: 5.44 | BO34: KG | BQ34: #N/A | BR34: #N/A | BS34: 49 | BT34: 2686.59 | BV34: 6270805 | BX34: 28.49 | BY34: 28.49 | BZ34: =BY34-BX34 -> 0 | CC34: =VLOOKUP(A34,'[1]RPT 1280 - Edmonton'!$1:$1048576,4,0) -> #N/A | CE34: AA | CF34: 20.68 | CG34: 0 | CH34: 0 | CI34: 3 | CJ34: =CF34-J34 -> 0 | CK34: =CG34-K34 -> 0 | CL34: =CH34-L34 -> 0 | CM34: =CI34-M34 -> 0 | CO34: 20.99 | CP34: 20.99 | CQ34: =CP34-CO34 -> 0
A35: 6270797 | B35: TIDY CATS 4IN1 LIGHT WT 1 X 5.44 KG | C35: 010134120270 | D35: L M S | E35: D | F35: F | G35: F | J35: =J34 -> 20.68 | M35: 3 | O35: =O34 -> 20.68 | P35: =P34 -> 20.68 | Q35: 3 | W35: 1/26.49 | X35: 30.99 | Z35: 27.49 | AH35: =IF(W35<>"",(RIGHT(W35,LEN(W35)-SEARCH("/",W35,1)))/U35,"") -> #VALUE! | AI35: =IF(X35<>"",X35,"") -> 30.99 | AJ35: =IF(Y35<>"",Y35,"") | AK35: =IF(Z35<>"",Z35,"") -> 27.49 | BG35: 0005580039181 | BH35: 0055800391810 | BJ35: Purina Tidy Cats 5.44 kg | BM35: TIDY CATS 4IN1 LIGHT WT | BN35: 5.44 | BO35: KG | BQ35: #N/A | BR35: #N/A | BS35: 41 | BT35: 11115.49 | BV35: 6270797 | BX35: 28.49 | BY35: 28.49 | BZ35: =BY35-BX35 -> 0 | CC35: =VLOOKUP(A35,'[1]RPT 1280 - Edmonton'!$1:$1048576,4,0) -> #N/A | CE35: AA | CF35: 20.68 | CG35: 0 | CH35: 0 | CI35: 3 | CJ35: =CF35-J35 -> 0 | CK35: =CG35-K35 -> 0 | CL35: =CH35-L35 -> 0 | CM35: =CI35-M35 -> 0
A36: 6270789 | B36: TIDYCATS 24/7 LIGHTWGHT 1 X 5.44 KG | C36: 010134120270 | D36: L M S | E36: D | F36: F | G36: F | J36: =J35 -> 20.68 | M36: 3 | O36: =O35 -> 20.68 | P36: =P35 -> 20.68 | Q36: 3 | W36: 1/26.49 | X36: 30.99 | Z36: 27.49 | AH36: =IF(W36<>"",(RIGHT(W36,LEN(W36)-SEARCH("/",W36,1)))/U36,"") -> #VALUE! | AI36: =IF(X36<>"",X36,"") -> 30.99 | AJ36: =IF(Y36<>"",Y36,"") | AK36: =IF(Z36<>"",Z36,"") -> 27.49 | BG36: 0005580039204 | BH36: 0055800392046 | BJ36: Purina Tidy Cats 5.44 kg | BM36: TIDYCATS 24/7 LIGHTWGHT | BN36: 5.44 | BO36: KG | BQ36: #N/A | BR36: #N/A | BS36: 36 | BT36: 13072.18 | BV36: 6270789 | BX36: 28.49 | BY36: 28.49 | BZ36: =BY36-BX36 -> 0 | CC36: =VLOOKUP(A36,'[1]RPT 1280 - Edmonton'!$1:$1048576,4,0) -> #N/A | CE36: AA | CF36: 20.68 | CG36: 0 | CH36: 0 | CI36: 3 | CJ36: =CF36-J36 -> 0 | CK36: =CG36-K36 -> 0 | CL36: =CH36-L36 -> 0 | CM36: =CI36-M36 -> 0
A37: 786350 | B37: LARABAR APPLE 5PK GF 8 X 225 GR | C37: 010203710120 | D37: L M S | E37: D | F37: F | G37: F | I37: ALL | J37: 56.08 | M37: 6.86 | O37: 56.08 | P37: 7.01 | Q37: 6.86 | T37: 1 / $6.99 | U37: 1 | V37: $6.99 | W37: 1/8.99 | X37: 9.49 | Z37: 8.99 | AA37: 0.060421137 | AC37: 8.49 | AD37: 10.19 | AE37: 8.79 | AF37: 9.59 | AH37: =IF(W37<>"",(RIGHT(W37,LEN(W37)-SEARCH("/",W37,1)))/U37,"") -> 8.99 | AI37: =IF(X37<>"",X37,"") -> 9.49 | AJ37: =IF(Y37<>"",Y37,"") | AK37: =IF(Z37<>"",Z37,"") -> 8.99 | AM37: 56.08 | AN37: 5.11 | AO37: 8 | AP37: =(AM37 * 1.05) - L37 - Q37 - K37 -> 52.024 | AQ37: N | AR37: =(((AH37)-((AP37/AO37) + ((AN37 * 0.03)/AO37)))/AH37)*100 -> 27.450918 | AS37: =(((AI37)-((AP37/AO37) + ((AN37 * 0.3)/AO37)))/AI37)*100 -> 29.456006 | AT37: =(((AJ37)-((AP37/AO37) + ((AN37 * 0.03)/AO37)))/AJ37)*100 -> #VALUE! | AU37: =(((AK37)-((AP37/AO37) + ((AN37 * 0.07)/AO37)))/AK37)*100 -> 27.166713 | BB37: =(((AH37)-(((AP37/AO37) + ((AN37 * 0.03)/AO37))-AW37))/AH37)*100 -> 27.450918 | BC37: =(((AI37)-(((AP37/AO37) + ((AN37 * 0.3)/AO37))-AX37))/AI37)*100 -> 29.456006 | BD37: =(((AJ37)-(((AP37/AO37) + ((AN37 * 0.03)/AO37))-AY37))/AJ37)*100 -> #VALUE! | BE37: =(((AK37)-(((AP37/AO37) + ((AN37 * 0.15)/AO37))-AZ37))/AK37)*100 -> 26.598304 | BG37: 0002190842316 | BH37: 0021908416946 | BM37: LARABAR APPLE 5PK GF | BN37: 225 | BO37: GR | BQ37: #N/A | BR37: D | BS37: 48 | BT37: 3967.49 | BX37: 10.99 | BY37: 10.99 | BZ37: =BY37-BX37 -> 0 | CC37: =VLOOKUP(A37,'[1]RPT 1280 - Edmonton'!$1:$1048576,4,0) -> #N/A | CE37: AA | CF37: 56.08 | CG37: 0 | CH37: 0 | CI37: 6.86 | CJ37: =CF37-J37 -> 0 | CK37: =CG37-K37 -> 0 | CL37: =CH37-L37 -> 0 | CM37: =CI37-M37 -> 0 | CO37: 6.99 | CP37: 6.99 | CQ37: =CP37-CO37 -> 0
A38: 786400 | B38: LARABAR PEA BUT 5PK GF 8 X 240 GR | C38: 010203710120 | D38: L M S | E38: D | F38: F | G38: F | J38: =J37 -> 56.08 | M38: 6.86 | O38: =O37 -> 56.08 | P38: =P37 -> 7.01 | Q38: 6.86 | W38: 1/8.99 | X38: 9.49 | Z38: 8.99 | AH38: =IF(W38<>"",(RIGHT(W38,LEN(W38)-SEARCH("/",W38,1)))/U38,"") -> #VALUE! | AI38: =IF(X38<>"",X38,"") -> 9.49 | AJ38: =IF(Y38<>"",Y38,"") | AK38: =IF(Z38<>"",Z38,"") -> 8.99 | BG38: 0002190842317 | BH38: 0021908416953 | BM38: LARABAR PEA BUT 5PK GF | BN38: 240 | BO38: GR | BQ38: #N/A | BR38: D | BS38: 47 | BT38: 2987.87 | BX38: 10.99 | BY38: 10.99 | BZ38: =BY38-BX38 -> 0 | CC38: =VLOOKUP(A38,'[1]RPT 1280 - Edmonton'!$1:$1048576,4,0) -> #N/A | CE38: AA | CF38: 56.08 | CG38: 0 | CH38: 0 | CI38: 6.86 | CJ38: =CF38-J38 -> 0 | CK38: =CG38-K38 -> 0 | CL38: =CH38-L38 -> 0 | CM38: =CI38-M38 -> 0
A39: 371807 | B39: LARABAR PEA BUT CH CHIP 5PK GF 8 X 225 GR | C39: 010203710120 | D39: L M S | E39: D | F39: F | G39: F | J39: =J38 -> 56.08 | M39: 6.86 | O39: =O38 -> 56.08 | P39: =P38 -> 7.01 | Q39: 6.86 | W39: 1/8.99 | X39: 9.49 | Z39: 8.99 | AH39: =IF(W39<>"",(RIGHT(W39,LEN(W39)-SEARCH("/",W39,1)))/U39,"") -> #VALUE! | AI39: =IF(X39<>"",X39,"") -> 9.49 | AJ39: =IF(Y39<>"",Y39,"") | AK39: =IF(Z39<>"",Z39,"") -> 8.99 | BG39: 0002190846259 | BH39: 0021908462599 | BM39: LARABAR PEA BUT CH CHIP 5PK GF | BN39: 225 | BO39: GR | BQ39: #N/A | BR39: D | BS39: 46 | BT39: 6188.02 | BX39: 10.99 | BY39: 10.99 | BZ39: =BY39-BX39 -> 0 | CC39: =VLOOKUP(A39,'[1]RPT 1280 - Edmonton'!$1:$1048576,4,0) -> #N/A | CE39: AA | CF39: 56.08 | CG39: 0 | CH39: 0 | CI39: 6.86 | CJ39: =CF39-J39 -> 0 | CK39: =CG39-K39 -> 0 | CL39: =CH39-L39 -> 0 | CM39: =CI39-M39 -> 0
A40: 2418051 | B40: LARABAR COCONUT CREAM 5PK GF 8 X 240 GR | C40: 010203710120 | D40: L M S | E40: D | F40: F | G40: F | J40: =J39 -> 56.08 | M40: 6.86 | O40: =O39 -> 56.08 | P40: =P39 -> 7.01 | Q40: 6.86 | W40: 1/8.99 | X40: 9.49 | Z40: 8.99 | AH40: =IF(W40<>"",(RIGHT(W40,LEN(W40)-SEARCH("/",W40,1)))/U40,"") -> #VALUE! | AI40: =IF(X40<>"",X40,"") -> 9.49 | AJ40: =IF(Y40<>"",Y40,"") | AK40: =IF(Z40<>"",Z40,"") -> 8.99 | BG40: 0002190846258 | BH40: 0021908462582 | BM40: LARABAR COCONUT CREAM 5PK GF | BN40: 240 | BO40: GR | BQ40: #N/A | BR40: D | BS40: 48 | BT40: 3171.23 | BX40: 10.99 | BY40: 10.99 | BZ40: =BY40-BX40 -> 0 | CC40: =VLOOKUP(A40,'[1]RPT 1280 - Edmonton'!$1:$1048576,4,0) -> #N/A | CE40: AA | CF40: 56.08 | CG40: 0 | CH40: 0 | CI40: 6.86 | CJ40: =CF40-J40 -> 0 | CK40: =CG40-K40 -> 0 | CL40: =CH40-L40 -> 0 | CM40: =CI40-M40 -> 0
A41: 6281190 | B41: NV S&S FAM PEANUT 15PK 8 X 525 GR | C41: 010201120228 | D41: L M S | E41: D | F41: F | G41: F | I41: E | J41: 58.89 | M41: 9.68 | O41: 58.89 | P41: 7.36125 | Q41: 9.68 | T41: 1 / $6.99 | U41: 1 | V41: $6.99 | W41: 1/8.99 | X41: 9.49 | Z41: 8.99 | AA41: 0.060043813 | AC41: 8.49 | AD41: 10.19 | AE41: 8.79 | AF41: 9.59 | AH41: =IF(W41<>"",(RIGHT(W41,LEN(W41)-SEARCH("/",W41,1)))/U41,"") -> 8.99 | AI41: =IF(X41<>"",X41,"") -> 9.49 | AJ41: =IF(Y41<>"",Y41,"") | AK41: =IF(Z41<>"",Z41,"") -> 8.99 | AM41: 58.89 | AN41: 11.38 | AO41: 8 | AP41: =(AM41 * 1.05) - L41 - Q41 - K41 -> 52.1545 | AQ41: N | AR41: =(((AH41)-((AP41/AO41) + ((AN41 * 0.03)/AO41)))/AH41)*100 -> 27.007925 | AS41: =(((AI41)-((AP41/AO41) + ((AN41 * 0.3)/AO41)))/AI41)*100 -> 26.806507 | AT41: =(((AJ41)-((AP41/AO41) + ((AN41 * 0.03)/AO41)))/AJ41)*100 -> #VALUE! | AU41: =(((AK41)-((AP41/AO41) + ((AN41 * 0.07)/AO41)))/AK41)*100 -> 26.375 | BB41: =(((AH41)-(((AP41/AO41) + ((AN41 * 0.03)/AO41))-AW41))/AH41)*100 -> 27.007925 | BC41: =(((AI41)-(((AP41/AO41) + ((AN41 * 0.3)/AO41))-AX41))/AI41)*100 -> 26.806507 | BD41: =(((AJ41)-(((AP41/AO41) + ((AN41 * 0.03)/AO41))-AY41))/AJ41)*100 -> #VALUE! | BE41: =(((AK41)-(((AP41/AO41) + ((AN41 * 0.15)/AO41))-AZ41))/AK41)*100 -> 25.109149 | BG41: 0006563316335 | BH41: 0065633163352 | BM41: NV S&S FAM PEANUT 15PK | BN41: 525 | BO41: GR | BQ41: #N/A | BR41: D | BS41: 46 | BT41: 3080.43 | BX41: 10.79 | BY41: 10.79 | BZ41: =BY41-BX41 -> 0 | CC41: =VLOOKUP(A41,'[1]RPT 1280 - Edmonton'!$1:$1048576,4,0) -> #N/A | CE41: AA | CF41: 58.89 | CG41: 0 | CH41: 0 | CI41: 9.68 | CJ41: =CF41-J41 -> 0 | CK41: =CG41-K41 -> 0 | CL41: =CH41-L41 -> 0 | CM41: =CI41-M41 -> 0 | CO41: 6.99 | CP41: 6.99 | CQ41: =CP41-CO41 -> 0
A42: 6281208 | B42: NV S&S DARK CHOC 15PK 8 X 525 GR | C42: 010201120228 | D42: L M S | E42: D | F42: F | G42: F | I42: S | J42: 58.89 | M42: 9.68 | O42: 58.89 | P42: 7.36125 | Q42: 9.68 | T42: 1 / $6.99 | U42: 1 | V42: $6.99 | W42: 1/8.99 | X42: 9.49 | Z42: 8.99 | AA42: 0.060043813 | AC42: 8.49 | AD42: 10.19 | AE42: 8.79 | AF42: 9.59 | AH42: =IF(W42<>"",(RIGHT(W42,LEN(W42)-SEARCH("/",W42,1)))/U42,"") -> 8.99 | AI42: =IF(X42<>"",X42,"") -> 9.49 | AJ42: =IF(Y42<>"",Y42,"") | AK42: =IF(Z42<>"",Z42,"") -> 8.99 | AM42: 58.89 | AN42: 11.38 | AO42: 8 | AP42: =(AM42 * 1.05) - L42 - Q42 - K42 -> 52.1545 | AQ42: N | AR42: =(((AH42)-((AP42/AO42) + ((AN42 * 0.03)/AO42)))/AH42)*100 -> 27.007925 | AS42: =(((AI42)-((AP42/AO42) + ((AN42 * 0.3)/AO42)))/AI42)*100 -> 26.806507 | AT42: =(((AJ42)-((AP42/AO42) + ((AN42 * 0.03)/AO42)))/AJ42)*100 -> #VALUE! | AU42: =(((AK42)-((AP42/AO42) + ((AN42 * 0.07)/AO42)))/AK42)*100 -> 26.375 | BB42: =(((AH42)-(((AP42/AO42) + ((AN42 * 0.03)/AO42))-AW42))/AH42)*100 -> 27.007925 | BC42: =(((AI42)-(((AP42/AO42) + ((AN42 * 0.3)/AO42))-AX42))/AI42)*100 -> 26.806507 | BD42: =(((AJ42)-(((AP42/AO42) + ((AN42 * 0.03)/AO42))-AY42))/AJ42)*100 -> #VALUE! | BE42: =(((AK42)-(((AP42/AO42) + ((AN42 * 0.15)/AO42))-AZ42))/AK42)*100 -> 25.109149 | BG42: 0006563316334 | BH42: 0065633163345 | BM42: NV S&S DARK CHOC 15PK | BN42: 525 | BO42: GR | BQ42: #N/A | BR42: D | BS42: 45 | BT42: 4987.34 | BX42: 10.79 | BY42: 10.79 | BZ42: =BY42-BX42 -> 0 | CC42: =VLOOKUP(A42,'[1]RPT 1280 - Edmonton'!$1:$1048576,4,0) -> #N/A | CE42: AA | CF42: 58.89 | CG42: 0 | CH42: 0 | CI42: 9.68 | CJ42: =CF42-J42 -> 0 | CK42: =CG42-K42 -> 0 | CL42: =CH42-L42 -> 0 | CM42: =CI42-M42 -> 0 | CO42: 6.99 | CP42: 6.99 | CQ42: =CP42-CO42 -> 0
A43: 6438576 | B43: NV TRL MIX FRUIT/NUT 15CT 8 X 525 GR | C43: 010201120236 | D43: L M S | E43: D | F43: F | G43: F | I43: W | J43: 58.89 | M43: 9.68 | O43: 58.89 | P43: 7.36125 | Q43: 9.68 | T43: 1 / $6.99 | U43: 1 | V43: $6.99 | W43: 1/8.99 | X43: 9.49 | Z43: 8.99 | AA43: 0.060043813 | AC43: 8.49 | AD43: 10.19 | AE43: 8.79 | AF43: 9.59 | AH43: =IF(W43<>"",(RIGHT(W43,LEN(W43)-SEARCH("/",W43,1)))/U43,"") -> 8.99 | AI43: =IF(X43<>"",X43,"") -> 9.49 | AJ43: =IF(Y43<>"",Y43,"") | AK43: =IF(Z43<>"",Z43,"") -> 8.99 | AM43: 58.89 | AN43: 17.36 | AO43: 8 | AP43: =(AM43 * 1.05) - L43 - Q43 - K43 -> 52.1545 | AQ43: N | AR43: =(((AH43)-((AP43/AO43) + ((AN43 * 0.03)/AO43)))/AH43)*100 -> 26.758482 | AS43: =(((AI43)-((AP43/AO43) + ((AN43 * 0.3)/AO43)))/AI43)*100 -> 24.443493 | AT43: =(((AJ43)-((AP43/AO43) + ((AN43 * 0.03)/AO43)))/AJ43)*100 -> #VALUE! | AU43: =(((AK43)-((AP43/AO43) + ((AN43 * 0.07)/AO43)))/AK43)*100 -> 25.792964 | BB43: =(((AH43)-(((AP43/AO43) + ((AN43 * 0.03)/AO43))-AW43))/AH43)*100 -> 26.758482 | BC43: =(((AI43)-(((AP43/AO43) + ((AN43 * 0.3)/AO43))-AX43))/AI43)*100 -> 24.443493 | BD43: =(((AJ43)-(((AP43/AO43) + ((AN43 * 0.03)/AO43))-AY43))/AJ43)*100 -> #VALUE! | BE43: =(((AK43)-(((AP43/AO43) + ((AN43 * 0.15)/AO43))-AZ43))/AK43)*100 -> 23.86193 | BG43: 0006563321861 | BH43: 0065633218618 | BM43: NV TRL MIX FRUIT/NUT 15CT | BN43: 525 | BO43: GR | BQ43: #N/A | BR43: D | BS43: 53 | BT43: 272.77 | BX43: 9.99 | BY43: 10.79 | BZ43: =BY43-BX43 -> 0.8 | CC43: =VLOOKUP(A43,'[1]RPT 1280 - Edmonton'!$1:$1048576,4,0) -> #N/A | CE43: AA | CF43: 58.89 | CG43: 0 | CH43: 0 | CI43: 9.68 | CJ43: =CF43-J43 -> 0 | CK43: =CG43-K43 -> 0 | CL43: =CH43-L43 -> 0 | CM43: =CI43-M43 -> 0 | CO43: 6.99 | CP43: 6.99 | CQ43: =CP43-CO43 -> 0
A44: 6307748 | B44: GM REESE PUFF CRL BAR 4 X 385 GR | C44: 010201120298 | D44: L M S | E44: D | F44: F | G44: F | I44: E | J44: 29.4 | M44: 4.8 | O44: 29.4 | P44: 7.35 | Q44: 4.8 | T44: 1 / $6.99 | U44: 1 | V44: $6.99 | W44: 1/8.99 | X44: 9.49 | Z44: 8.99 | AA44: 0.060143062 | AC44: 8.49 | AD44: 10.19 | AE44: 8.79 | AF44: 9.59 | AH44: =IF(W44<>"",(RIGHT(W44,LEN(W44)-SEARCH("/",W44,1)))/U44,"") -> 8.99 | AI44: =IF(X44<>"",X44,"") -> 9.49 | AJ44: =IF(Y44<>"",Y44,"") | AK44: =IF(Z44<>"",Z44,"") -> 8.99 | AM44: 29.4 | AN44: 4.89 | AO44: 4 | AP44: =(AM44 * 1.05) - L44 - Q44 - K44 -> 26.07 | AQ44: N | AR44: =(((AH44)-((AP44/AO44) + ((AN44 * 0.03)/AO44)))/AH44)*100 -> 27.094828 | AS44: =(((AI44)-((AP44/AO44) + ((AN44 * 0.3)/AO44)))/AI44)*100 -> 27.45785 | AT44: =(((AJ44)-((AP44/AO44) + ((AN44 * 0.03)/AO44)))/AJ44)*100 -> #VALUE! | AU44: =(((AK44)-((AP44/AO44) + ((AN44 * 0.07)/AO44)))/AK44)*100 -> 26.55089 | BB44: =(((AH44)-(((AP44/AO44) + ((AN44 * 0.03)/AO44))-AW44))/AH44)*100 -> 27.094828 | BC44: =(((AI44)-(((AP44/AO44) + ((AN44 * 0.3)/AO44))-AX44))/AI44)*100 -> 27.45785 | BD44: =(((AJ44)-(((AP44/AO44) + ((AN44 * 0.03)/AO44))-AY44))/AJ44)*100 -> #VALUE! | BE44: =(((AK44)-(((AP44/AO44) + ((AN44 * 0.15)/AO44))-AZ44))/AK44)*100 -> 25.463014 | BG44: 0006563317478 | BH44: 0065633174785 | BM44: GM REESE PUFF CRL BAR | BN44: 385 | BO44: GR | BQ44: #N/A | BR44: D | BS44: 48 | BT44: 2710.88 | BX44: 11.79 | BY44: 11.79 | BZ44: =BY44-BX44 -> 0 | CC44: =VLOOKUP(A44,'[1]RPT 1280 - Edmonton'!$1:$1048576,4,0) -> #N/A | CE44: AA | CF44: 29.4 | CG44: 0 | CH44: 0 | CI44: 4.8 | CJ44: =CF44-J44 -> 0 | CK44: =CG44-K44 -> 0 | CL44: =CH44-L44 -> 0 | CM44: =CI44-M44 -> 0 | CO44: 6.99 | CP44: 6.99 | CQ44: =CP44-CO44 -> 0
A45: 6333587 | B45: FRT GUSHERS FAM PACK GF 6 X 368 GR | C45: 010202110190 | D45: L M S | E45: D | F45: F | G45: F | I45: E | J45: 39.54 | M45: 2.62 | O45: 39.54 | P45: 6.59 | Q45: 2.62 | T45: 1 / $6.99 | U45: 1 | V45: $6.99 | W45: 1/8.99 | X45: 9.49 | Z45: 8.99 | AA45: 0.060665236 | AC45: 8.49 | AD45: 10.19 | AE45: 8.79 | AF45: 9.59 | AH45: =IF(W45<>"",(RIGHT(W45,LEN(W45)-SEARCH("/",W45,1)))/U45,"") -> 8.99 | AI45: =IF(X45<>"",X45,"") -> 9.49 | AJ45: =IF(Y45<>"",Y45,"") | AK45: =IF(Z45<>"",Z45,"") -> 8.99 | AM45: 39.54 | AN45: 6.19 | AO45: 6 | AP45: =(AM45 * 1.05) - L45 - Q45 - K45 -> 38.897 | AQ45: N | AR45: =(((AH45)-((AP45/AO45) + ((AN45 * 0.03)/AO45)))/AH45)*100 -> 27.544123 | AS45: =(((AI45)-((AP45/AO45) + ((AN45 * 0.3)/AO45)))/AI45)*100 -> 28.426414 | AT45: =(((AJ45)-((AP45/AO45) + ((AN45 * 0.03)/AO45)))/AJ45)*100 -> #VALUE! | AU45: =(((AK45)-((AP45/AO45) + ((AN45 * 0.07)/AO45)))/AK45)*100 -> 27.085095 | BB45: =(((AH45)-(((AP45/AO45) + ((AN45 * 0.03)/AO45))-AW45))/AH45)*100 -> 27.544123 | BC45: =(((AI45)-(((AP45/AO45) + ((AN45 * 0.3)/AO45))-AX45))/AI45)*100 -> 28.426414 | BD45: =(((AJ45)-(((AP45/AO45) + ((AN45 * 0.03)/AO45))-AY45))/AJ45)*100 -> #VALUE! | BE45: =(((AK45)-(((AP45/AO45) + ((AN45 * 0.15)/AO45))-AZ45))/AK45)*100 -> 26.167037 | BG45: 0006563318168 | BH45: 0065633181684 | BM45: FRT GUSHERS FAM PACK GF | BN45: 368 | BO45: GR | BQ45: #N/A | BR45: D | BS45: 39 | BT45: 10352.49 | BX45: 10.79 | BY45: 10.79 | BZ45: =BY45-BX45 -> 0 | CC45: =VLOOKUP(A45,'[1]RPT 1280 - Edmonton'!$1:$1048576,4,0) -> #N/A | CE45: AA | CF45: 39.54 | CG45: 0 | CH45: 0 | CI45: 2.62 | CJ45: =CF45-J45 -> 0 | CK45: =CG45-K45 -> 0 | CL45: =CH45-L45 -> 0 | CM45: =CI45-M45 -> 0 | CO45: 6.99 | CP45: 6.99 | CQ45: =CP45-CO45 -> 0
A46: 6518260 | B46: MOTTS FRTSATIONS ASST FRT 6 X 498 GR | C46: 010202120290 | D46: L M S | E46: D | F46: F | G46: F | I46: S | J46: 39.54 | M46: 2.62 | O46: 39.54 | P46: 6.59 | Q46: 2.62 | T46: 1 / $6.99 | U46: 1 | V46: $6.99 | W46: 1/8.99 | X46: 9.49 | Z46: 8.99 | AA46: 0.060665236 | AC46: 8.49 | AD46: 10.19 | AE46: 8.79 | AF46: 9.59 | AH46: =IF(W46<>"",(RIGHT(W46,LEN(W46)-SEARCH("/",W46,1)))/U46,"") -> 8.99 | AI46: =IF(X46<>"",X46,"") -> 9.49 | AJ46: =IF(Y46<>"",Y46,"") | AK46: =IF(Z46<>"",Z46,"") -> 8.99 | AM46: 39.54 | AN46: 6.6 | AO46: 6 | AP46: =(AM46 * 1.05) - L46 - Q46 - K46 -> 38.897 | AQ46: N | AR46: =(((AH46)-((AP46/AO46) + ((AN46 * 0.03)/AO46)))/AH46)*100 -> 27.52132 | AS46: =(((AI46)-((AP46/AO46) + ((AN46 * 0.3)/AO46)))/AI46)*100 -> 28.210397 | AT46: =(((AJ46)-((AP46/AO46) + ((AN46 * 0.03)/AO46)))/AJ46)*100 -> #VALUE! | AU46: =(((AK46)-((AP46/AO46) + ((AN46 * 0.07)/AO46)))/AK46)*100 -> 27.031887 | BB46: =(((AH46)-(((AP46/AO46) + ((AN46 * 0.03)/AO46))-AW46))/AH46)*100 -> 27.52132 | BC46: =(((AI46)-(((AP46/AO46) + ((AN46 * 0.3)/AO46))-AX46))/AI46)*100 -> 28.210397 | BD46: =(((AJ46)-(((AP46/AO46) + ((AN46 * 0.03)/AO46))-AY46))/AJ46)*100 -> #VALUE! | BE46: =(((AK46)-(((AP46/AO46) + ((AN46 * 0.15)/AO46))-AZ46))/AK46)*100 -> 26.053022 | BG46: 0006563323096 | BH46: 0065633230962 | BM46: MOTTS FRTSATIONS ASST FRT | BN46: 498 | BO46: GR | BQ46: #N/A | BR46: D | BS46: 54 | BT46: 148.66 | BX46: 9.99 | BY46: 9.99 | BZ46: =BY46-BX46 -> 0 | CC46: =VLOOKUP(A46,'[1]RPT 1280 - Edmonton'!$1:$1048576,4,0) -> #N/A | CE46: AA | CF46: 39.54 | CG46: 0 | CH46: 0 | CI46: 2.62 | CJ46: =CF46-J46 -> 0 | CK46: =CG46-K46 -> 0 | CL46: =CH46-L46 -> 0 | CM46: =CI46-M46 -> 0 | CO46: 6.99 | CP46: 6.99 | CQ46: =CP46-CO46 -> 0
A47: 6498364 | B47: LARABAR SPECIAL EDITION 5CT 8 X 225 GR | C47: 010203710120 | D47: L M S | E47: D | F47: F | G47: F | I47: E | J47: 56.08 | M47: 6.86 | O47: 56.08 | P47: 7.01 | Q47: 6.86 | T47: 1 / $6.99 | U47: 1 | V47: $6.99 | W47: 1/8.99 | X47: 9.49 | Z47: 8.99 | AA47: 0.060421137 | AC47: 8.49 | AD47: 10.19 | AE47: 8.79 | AF47: 9.59 | AH47: =IF(W47<>"",(RIGHT(W47,LEN(W47)-SEARCH("/",W47,1)))/U47,"") -> 8.99 | AI47: =IF(X47<>"",X47,"") -> 9.49 | AJ47: =IF(Y47<>"",Y47,"") | AK47: =IF(Z47<>"",Z47,"") -> 8.99 | AM47: 56.08 | AN47: 5.09 | AO47: 8 | AP47: =(AM47 * 1.05) - L47 - Q47 - K47 -> 52.024 | AQ47: N | AR47: =(((AH47)-((AP47/AO47) + ((AN47 * 0.03)/AO47)))/AH47)*100 -> 27.451752 | AS47: =(((AI47)-((AP47/AO47) + ((AN47 * 0.3)/AO47)))/AI47)*100 -> 29.463909 | AT47: =(((AJ47)-((AP47/AO47) + ((AN47 * 0.03)/AO47)))/AJ47)*100 -> #VALUE! | AU47: =(((AK47)-((AP47/AO47) + ((AN47 * 0.07)/AO47)))/AK47)*100 -> 27.16866 | BB47: =(((AH47)-(((AP47/AO47) + ((AN47 * 0.03)/AO47))-AW47))/AH47)*100 -> 27.451752 | BC47: =(((AI47)-(((AP47/AO47) + ((AN47 * 0.3)/AO47))-AX47))/AI47)*100 -> 29.463909 | BD47: =(((AJ47)-(((AP47/AO47) + ((AN47 * 0.03)/AO47))-AY47))/AJ47)*100 -> #VALUE! | BE47: =(((AK47)-(((AP47/AO47) + ((AN47 * 0.15)/AO47))-AZ47))/AK47)*100 -> 26.602475 | BG47: 0006563322661 | BH47: 0065633226613 | BM47: LARABAR SPECIAL EDITION 5CT | BN47: 225 | BO47: GR | BQ47: #N/A | BR47: D | BS47: 54 | BT47: 263.76 | BX47: 10.99 | BY47: 10.99 | BZ47: =BY47-BX47 -> 0 | CC47: =VLOOKUP(A47,'[1]RPT 1280 - Edmonton'!$1:$1048576,4,0) -> #N/A | CE47: AA | CF47: 56.08 | CG47: 0 | CH47: 0 | CI47: 6.86 | CJ47: =CF47-J47 -> 0 | CK47: =CG47-K47 -> 0 | CL47: =CH47-L47 -> 0 | CM47: =CI47-M47 -> 0 | CO47: 6.99 | CP47: 6.99 | CQ47: =CP47-CO47 -> 0
A48: 6517973 | B48: NV CRNCH GRNL BAR OAT HNY 6 X 630 GR | C48: 010201120228 | D48: L M S | E48: D | F48: F | G48: F | I48: E | J48: 44.17 | M48: 7.26 | O48: 44.17 | P48: 7.3616667 | Q48: 7.26 | T48: 1 / $6.99 | U48: 1 | V48: $6.99 | W48: 1/8.99 | X48: 9.49 | Z48: 8.99 | AA48: 0.060653314 | AC48: 8.49 | AD48: 10.19 | AE48: 8.79 | AF48: 9.59 | AH48: =IF(W48<>"",(RIGHT(W48,LEN(W48)-SEARCH("/",W48,1)))/U48,"") -> 8.99 | AI48: =IF(X48<>"",X48,"") -> 9.49 | AJ48: =IF(Y48<>"",Y48,"") | AK48: =IF(Z48<>"",Z48,"") -> 8.99 | AM48: 44.17 | AN48: 8.33 | AO48: 6 | AP48: =(AM48 * 1.05) - L48 - Q48 - K48 -> 39.1185 | AQ48: N | AR48: =(((AH48)-((AP48/AO48) + ((AN48 * 0.03)/AO48)))/AH48)*100 -> 27.014461 | AS48: =(((AI48)-((AP48/AO48) + ((AN48 * 0.3)/AO48)))/AI48)*100 -> 26.909905 | AT48: =(((AJ48)-((AP48/AO48) + ((AN48 * 0.03)/AO48)))/AJ48)*100 -> #VALUE! | AU48: =(((AK48)-((AP48/AO48) + ((AN48 * 0.07)/AO48)))/AK48)*100 -> 26.396737 | BB48: =(((AH48)-(((AP48/AO48) + ((AN48 * 0.03)/AO48))-AW48))/AH48)*100 -> 27.014461 | BC48: =(((AI48)-(((AP48/AO48) + ((AN48 * 0.3)/AO48))-AX48))/AI48)*100 -> 26.909905 | BD48: =(((AJ48)-(((AP48/AO48) + ((AN48 * 0.03)/AO48))-AY48))/AJ48)*100 -> #VALUE! | BE48: =(((AK48)-(((AP48/AO48) + ((AN48 * 0.15)/AO48))-AZ48))/AK48)*100 -> 25.16129 | BG48: 0006563322691 | BH48: 0065633226910 | BM48: NV CRNCH GRNL BAR OAT HNY | BN48: 630 | BO48: GR | BQ48: #N/A | BR48: D | BS48: 51 | BT48: 156.45 | BX48: 10.79 | BY48: 10.79 | BZ48: =BY48-BX48 -> 0 | CC48: =VLOOKUP(A48,'[1]RPT 1280 - Edmonton'!$1:$1048576,4,0) -> #N/A | CE48: AA | CF48: 44.17 | CG48: 0 | CH48: 0 | CI48: 7.26 | CJ48: =CF48-J48 -> 0 | CK48: =CG48-K48 -> 0 | CL48: =CH48-L48 -> 0 | CM48: =CI48-M48 -> 0 | CO48: 6.99 | CP48: 6.99 | CQ48: =CP48-CO48 -> 0
A49: 696179 | B49: KR CHZ WHIZ 1/2 PAL- 900G (318PC)-P 318 X 1 EA | C49: 010319090900 | D49: L M S | E49: DNK | F49: F | G49: F | I49: ALL | J49: 2936.59 | M49: 575.58 | O49: 2936.59 | P49: 9.2345597 | Q49: 575.58 | R49: 318 | S49: $1.000 | T49: 1 / $6.99 | U49: 1 | V49: $6.99 | W49: 1 /6.99 | X49: 8.49 | Z49: 7.99 | AA49: 0.045075017 | AC49: 8.49 | AD49: 10.19 | AE49: 8.79 | AF49: 9.59 | AH49: =IF(W49<>"",(RIGHT(W49,LEN(W49)-SEARCH("/",W49,1)))/U49,"") -> 6.99 | AI49: =IF(X49<>"",X49,"") -> 8.49 | AJ49: =IF(Y49<>"",Y49,"") | AK49: =IF(Z49<>"",Z49,"") -> 7.99 | AM49: 2990.08 | AN49: 915.17 | AO49: 318 | AP49: =(AM49 * 1.05) - L49 - Q49 - K49 -> 2564.004 | AQ49: N | AR49: =(((AH49)-((AP49/AO49) + ((AN49 * 0.03)/AO49)))/AH49)*100 -> -16.584298 | AS49: =(((AI49)-((AP49/AO49) + ((AN49 * 0.3)/AO49)))/AI49)*100 -> -5.1386759 | AT49: =(((AJ49)-((AP49/AO49) + ((AN49 * 0.03)/AO49)))/AJ49)*100 -> #VALUE! | AU49: =(((AK49)-((AP49/AO49) + ((AN49 * 0.07)/AO49)))/AK49)*100 -> -3.4337694 | BB49: =(((AH49)-(((AP49/AO49) + ((AN49 * 0.03)/AO49))-AW49))/AH49)*100 -> -16.584298 | BC49: =(((AI49)-(((AP49/AO49) + ((AN49 * 0.3)/AO49))-AX49))/AI49)*100 -> -5.1386759 | BD49: =(((AJ49)-(((AP49/AO49) + ((AN49 * 0.03)/AO49))-AY49))/AJ49)*100 -> #VALUE! | BE49: =(((AK49)-(((AP49/AO49) + ((AN49 * 0.15)/AO49))-AZ49))/AK49)*100 -> -6.3152644 | BG49: 0000000000000 | BH49: 0000000000000 | BM49: KR CHZ WHIZ 1/2 PAL- 900G (318PC)-P | BN49: 1 | BO49: EA | BP49: 696179 | BQ49: #N/A | BR49: #N/A | BU49: 696179 | BY49: #N/A | BZ49: =BY49-BX49 -> #N/A | CC49: =VLOOKUP(A49,'[1]RPT 1280 - Edmonton'!$1:$1048576,4,0) -> #N/A | CE49: Q | CF49: 2936.59 | CG49: 0 | CH49: 0 | CI49: 575.58 | CJ49: =CF49-J49 -> 0 | CK49: =CG49-K49 -> 0 | CL49: =CH49-L49 -> 0 | CM49: =CI49-M49 -> 0 | CO49: 6.99 | CP49: 6.99 | CQ49: =CP49-CO49 -> 0
A50: 603605 | B50: KR CHEEZ WHIZ REGULAR 6 X 900 GR | C50: 010315530315 | D50: L M S | E50: A | F50: F | G50: F | I50: ALL | J50: 56.35 | M50: 10.86 | O50: 56.35 | P50: 9.3916667 | Q50: 13.98 | R50: 6 | S50: $1.000 | T50: 1 / $6.99 | U50: 1 | V50: $6.99 | W50: 1 /6.99 | X50: 8.99 | Z50: 7.99 | AA50: 0.030933476 | AC50: 8.49 | AD50: 10.19 | AE50: 8.79 | AF50: 9.59 | AH50: =IF(W50<>"",(RIGHT(W50,LEN(W50)-SEARCH("/",W50,1)))/U50,"") -> 6.99 | AI50: =IF(X50<>"",X50,"") -> 8.99 | AJ50: =IF(Y50<>"",Y50,"") | AK50: =IF(Z50<>"",Z50,"") -> 7.99 | AM50: 57.36 | AN50: 17.15 | AO50: 6 | AP50: =(AM50 * 1.05) - L50 - Q50 - K50 -> 46.248 | AQ50: N | AR50: =(((AH50)-((AP50/AO50) + ((AN50 * 0.03)/AO50)))/AH50)*100 -> -11.498569 | AS50: =(((AI50)-((AP50/AO50) + ((AN50 * 0.3)/AO50)))/AI50)*100 -> 4.7219132 | AT50: =(((AJ50)-((AP50/AO50) + ((AN50 * 0.03)/AO50)))/AJ50)*100 -> #VALUE! | AU50: =(((AK50)-((AP50/AO50) + ((AN50 * 0.07)/AO50)))/AK50)*100 -> 1.0252399 | BB50: =(((AH50)-(((AP50/AO50) + ((AN50 * 0.03)/AO50))-AW50))/AH50)*100 -> -11.498569 | BC50: =(((AI50)-(((AP50/AO50) + ((AN50 * 0.3)/AO50))-AX50))/AI50)*100 -> 4.7219132 | BD50: =(((AJ50)-(((AP50/AO50) + ((AN50 * 0.03)/AO50))-AY50))/AJ50)*100 -> #VALUE! | BE50: =(((AK50)-(((AP50/AO50) + ((AN50 * 0.15)/AO50))-AZ50))/AK50)*100 -> -1.8366708 | BG50: 0006810089235 | BH50: 0068100892359 | BI50: remove EDLC | BJ50: Kraft Singles 825 g or Cheez Whiz 900 g | BM50: KR CHEEZ WHIZ REGULAR | BN50: 900 | BO50: GR | BP50: 603605 | BQ50: B | BR50: #N/A | BS50: 1 | BT50: 138072.02 | BU50: 603605 | BX50: 15.29 | BY50: 15.29 | BZ50: =BY50-BX50 -> 0 | CC50: =VLOOKUP(A50,'[1]RPT 1280 - Edmonton'!$1:$1048576,4,0) -> #N/A | CE50: AA | CF50: 56.35 | CG50: 0 | CH50: 0 | CI50: 10.86 | CJ50: =CF50-J50 -> 0 | CK50: =CG50-K50 -> 0 | CL50: =CH50-L50 -> 0 | CM50: =CI50-M50 -> 0 | CO50: 6.99 | CP50: 6.99 | CQ50: =CP50-CO50 -> 0
A51: 603613 | B51: KR CHEEZ WHIZ LIGHT 6 X 900 GR | C51: 010315530315 | D51: L M S | E51: A | F51: F | G51: F | J51: =J50 -> 56.35 | M51: 10.86 | O51: =O50 -> 56.35 | P51: =P50 -> 9.3916667 | Q51: 13.98 | W51: 1 /6.99 | X51: 8.99 | Z51: 7.99 | AH51: =IF(W51<>"",(RIGHT(W51,LEN(W51)-SEARCH("/",W51,1)))/U51,"") -> #VALUE! | AI51: =IF(X51<>"",X51,"") -> 8.99 | AJ51: =IF(Y51<>"",Y51,"") | AK51: =IF(Z51<>"",Z51,"") -> 7.99 | BG51: 0006810089236 | BH51: 0068100892366 | BI51: remove EDLC | BJ51: Kraft Singles 825 g or Cheez Whiz 900 g | BM51: KR CHEEZ WHIZ LIGHT | BN51: 900 | BO51: GR | BP51: 603613 | BQ51: B | BR51: #N/A | BS51: 25 | BT51: 7577.64 | BU51: 603613 | BX51: 15.29 | BY51: 15.29 | BZ51: =BY51-BX51 -> 0 | CC51: =VLOOKUP(A51,'[1]RPT 1280 - Edmonton'!$1:$1048576,4,0) -> #N/A | CE51: AA | CF51: 56.35 | CG51: 0 | CH51: 0 | CI51: 10.86 | CJ51: =CF51-J51 -> 0 | CK51: =CG51-K51 -> 0 | CL51: =CH51-L51 -> 0 | CM51: =CI51-M51 -> 0
A52: 6225957 | B52: KR SINGLES SLICES 44'S 8 X 825 GR | C52: 010314130325 | D52: L M S | E52: A | F52: F | G52: F | I52: ALL | J52: 76.97 | M52: 15.24 | O52: 76.97 | P52: 9.62125 | Q52: 20 | R52: 8 | S52: $1.000 | T52: 1 / $6.99 | U52: 1 | V52: $6.99 | W52: 1 /6.99 | X52: 8.99 | Z52: 7.99 | AA52: 0.030843169 | AC52: 8.49 | AD52: 10.19 | AE52: 8.79 | AF52: 9.59 | AH52: =IF(W52<>"",(RIGHT(W52,LEN(W52)-SEARCH("/",W52,1)))/U52,"") -> 6.99 | AI52: =IF(X52<>"",X52,"") -> 8.99 | AJ52: =IF(Y52<>"",Y52,"") | AK52: =IF(Z52<>"",Z52,"") -> 7.99 | AM52: 78.34 | AN52: 15.48 | AO52: 8 | AP52: =(AM52 * 1.05) - L52 - Q52 - K52 -> 62.257 | AQ52: N | AR52: =(((AH52)-((AP52/AO52) + ((AN52 * 0.03)/AO52)))/AH52)*100 -> -12.162732 | AS52: =(((AI52)-((AP52/AO52) + ((AN52 * 0.3)/AO52)))/AI52)*100 -> 6.9785873 | AT52: =(((AJ52)-((AP52/AO52) + ((AN52 * 0.03)/AO52)))/AJ52)*100 -> #VALUE! | AU52: =(((AK52)-((AP52/AO52) + ((AN52 * 0.07)/AO52)))/AK52)*100 -> 0.90644556 | BB52: =(((AH52)-(((AP52/AO52) + ((AN52 * 0.03)/AO52))-AW52))/AH52)*100 -> -12.162732 | BC52: =(((AI52)-(((AP52/AO52) + ((AN52 * 0.3)/AO52))-AX52))/AI52)*100 -> 6.9785873 | BD52: =(((AJ52)-(((AP52/AO52) + ((AN52 * 0.03)/AO52))-AY52))/AJ52)*100 -> #VALUE! | BE52: =(((AK52)-(((AP52/AO52) + ((AN52 * 0.15)/AO52))-AZ52))/AK52)*100 -> -1.0309762 | BG52: 0006810000359 | BH52: 0068100003595 | BI52: remove EDLC | BJ52: Kraft Singles 825 g or Cheez Whiz 900 g | BM52: KR SINGLES SLICES 44 S | BN52: 825 | BO52: GR | BP52: 6225957 | BQ52: B | BR52: #N/A | BS52: 1 | BT52: 160599.75 | BU52: 6225957 | BX52: 14.29 | BY52: 14.29 | BZ52: =BY52-BX52 -> 0 | CC52: =VLOOKUP(A52,'[1]RPT 1280 - Edmonton'!$1:$1048576,4,0) -> #N/A | CE52: AA | CF52: 76.97 | CG52: 0 | CH52: 0 | CI52: 15.24 | CJ52: =CF52-J52 -> 0 | CK52: =CG52-K52 -> 0 | CL52: =CH52-L52 -> 0 | CM52: =CI52-M52 -> 0 | CO52: 6.99 | CP52: 6.99 | CQ52: =CP52-CO52 -> 0
A53: 6225940 | B53: KR SINGLES THICK 28S 8 X 825 GR | C53: 010314130325 | D53: L M S | E53: A | F53: F | G53: F | J53: =J52 -> 76.97 | M53: 15.24 | O53: =O52 -> 76.97 | P53: =P52 -> 9.62125 | Q53: 20 | W53: 1 /6.99 | X53: 8.99 | Z53: 7.99 | AH53: =IF(W53<>"",(RIGHT(W53,LEN(W53)-SEARCH("/",W53,1)))/U53,"") -> #VALUE! | AI53: =IF(X53<>"",X53,"") -> 8.99 | AJ53: =IF(Y53<>"",Y53,"") | AK53: =IF(Z53<>"",Z53,"") -> 7.99 | BG53: 0006810000357 | BH53: 0068100003571 | BI53: remove EDLC | BJ53: Kraft Singles 825 g or Cheez Whiz 900 g | BM53: KR SINGLES THICK 28S | BN53: 825 | BO53: GR | BP53: 6225940 | BQ53: B | BR53: #N/A | BS53: 7 | BT53: 110965.88 | BU53: 6225940 | BX53: 14.29 | BY53: 14.29 | BZ53: =BY53-BX53 -> 0 | CC53: =VLOOKUP(A53,'[1]RPT 1280 - Edmonton'!$1:$1048576,4,0) -> #N/A | CE53: AA | CF53: 76.97 | CG53: 0 | CH53: 0 | CI53: 15.24 | CJ53: =CF53-J53 -> 0 | CK53: =CG53-K53 -> 0 | CL53: =CH53-L53 -> 0 | CM53: =CI53-M53 -> 0
A54: 856351 | B54: LCKY DRGN AAA SCNTD JSMIN RICE 1 X 18.1 KG | C54: 010171160644 | D54: L M S | E54: A | F54: F | G54: F | I54: ALL | J54: 36.84 | O54: 36.84 | P54: 36.84 | Q54: 6 | T54: 1 / $27.99 | U54: 1 | V54: $27.99 | W54: 1 /27.99 | X54: 59.99 | Z54: 51.99 | AA54: 0.029974991 | AC54: 33.59 | AD54: 40.19 | AE54: 35.49 | AF54: 37.19 | AH54: =IF(W54<>"",(RIGHT(W54,LEN(W54)-SEARCH("/",W54,1)))/U54,"") -> 27.99 | AI54: =IF(X54<>"",X54,"") -> 59.99 | AJ54: =IF(Y54<>"",Y54,"") | AK54: =IF(Z54<>"",Z54,"") -> 51.99 | AM54: 37.44 | AN54: 39.9 | AO54: 1 | AP54: =(AM54 * 1.05) - L54 - Q54 - K54 -> 33.312 | AQ54: N | AR54: =(((AH54)-((AP54/AO54) + ((AN54 * 0.03)/AO54)))/AH54)*100 -> -23.290461 | AS54: =(((AI54)-((AP54/AO54) + ((AN54 * 0.3)/AO54)))/AI54)*100 -> 24.51742 | AT54: =(((AJ54)-((AP54/AO54) + ((AN54 * 0.03)/AO54)))/AJ54)*100 -> #VALUE! | AU54: =(((AK54)-((AP54/AO54) + ((AN54 * 0.07)/AO54)))/AK54)*100 -> 30.553953 | BB54: =(((AH54)-(((AP54/AO54) + ((AN54 * 0.03)/AO54))-AW54))/AH54)*100 -> -23.290461 | BC54: =(((AI54)-(((AP54/AO54) + ((AN54 * 0.3)/AO54))-AX54))/AI54)*100 -> 24.51742 | BD54: =(((AJ54)-(((AP54/AO54) + ((AN54 * 0.03)/AO54))-AY54))/AJ54)*100 -> #VALUE! | BE54: =(((AK54)-(((AP54/AO54) + ((AN54 * 0.15)/AO54))-AZ54))/AK54)*100 -> 24.41431 | BG54: 0005731616335 | BH54: 0057316163353 | BJ54: Lucky Dragon AAA Scented Jasmine Rice 18.1 kg | BM54: LCKY DRGN AAA SCNTD JSMIN RICE | BN54: 18.1 | BO54: KG | BQ54: #N/A | BR54: #N/A | BS54: 21 | BT54: 84592.87 | BX54: 52.99 | BY54: 52.99 | BZ54: =BY54-BX54 -> 0 | CC54: =VLOOKUP(A54,'[1]RPT 1280 - Edmonton'!$1:$1048576,4,0) -> #N/A | CE54: AA | CF54: 36.84 | CG54: 0 | CH54: 0 | CI54: 0 | CJ54: =CF54-J54 -> 0 | CK54: =CG54-K54 -> 0 | CL54: =CH54-L54 -> 0 | CM54: =CI54-M54 -> 0 | CO54: 27.99 | CP54: 27.99 | CQ54: =CP54-CO54 -> 0
A55: 741306 | B55: SIMILAC POWDER REGULAR 6 X 850 GR | C55: 507131110150 | D55: L M S | E55: DNK | F55: F | G55: F | I55: E | J55: 217.62 | M55: 15 | O55: 217.62 | P55: 36.27 | Q55: 15 | T55: 1/32.99 | U55: 1 | V55: $34.99 | W55: 1 /34.99 | X55: 41.99 | Z55: 38.49 | AA55: 0.047985615 | AC55: 41.99 | AD55: 50.49 | AE55: 44.19 | AF55: 46.19 | AH55: =IF(W55<>"",(RIGHT(W55,LEN(W55)-SEARCH("/",W55,1)))/U55,"") -> 34.99 | AI55: =IF(X55<>"",X55,"") -> 41.99 | AJ55: =IF(Y55<>"",Y55,"") | AK55: =IF(Z55<>"",Z55,"") -> 38.49 | AM55: 217.62 | AN55: 14.55 | AO55: 6 | AP55: =(AM55 * 1.05) - L55 - Q55 - K55 -> 213.501 | AQ55: N | AR55: =(((AH55)-((AP55/AO55) + ((AN55 * 0.03)/AO55)))/AH55)*100 -> -1.9041155 | AS55: =(((AI55)-((AP55/AO55) + ((AN55 * 0.3)/AO55)))/AI55)*100 -> 13.524649 | AT55: =(((AJ55)-((AP55/AO55) + ((AN55 * 0.03)/AO55)))/AJ55)*100 -> #VALUE! | AU55: =(((AK55)-((AP55/AO55) + ((AN55 * 0.07)/AO55)))/AK55)*100 -> 7.1102884 | BB55: =(((AH55)-(((AP55/AO55) + ((AN55 * 0.03)/AO55))-AW55))/AH55)*100 -> -1.9041155 | BC55: =(((AI55)-(((AP55/AO55) + ((AN55 * 0.3)/AO55))-AX55))/AI55)*100 -> 13.524649 | BD55: =(((AJ55)-(((AP55/AO55) + ((AN55 * 0.03)/AO55))-AY55))/AJ55)*100 -> #VALUE! | BE55: =(((AK55)-(((AP55/AO55) + ((AN55 * 0.15)/AO55))-AZ55))/AK55)*100 -> 6.6062614 | BG55: 0005532502251 | BH55: 0055325022524 | BM55: SIMILAC POWDER REGULAR | BN55: 850 | BO55: GR | BQ55: #N/A | BR55: #N/A | BS55: 47 | BT55: 8233.98 | BX55: 42.99 | BY55: 42.99 | BZ55: =BY55-BX55 -> 0 | CA55: -10.5 | CC55: =VLOOKUP(A55,'[1]RPT 1280 - Edmonton'!$1:$1048576,4,0) -> RC | CE55: IA | CF55: 217.62 | CG55: 0 | CH55: 0 | CI55: 15 | CJ55: =CF55-J55 -> 0 | CK55: =CG55-K55 -> 0 | CL55: =CH55-L55 -> 0 | CM55: =CI55-M55 -> 0 | CO55: 32.99 | CP55: 34.99 | CQ55: =CP55-CO55 -> 2
A56: 741348 | B56: SIMILAC POWDER IRON FORT 6 X 850 GR | C56: 507131110150 | D56: L M S | E56: DNK | F56: F | G56: F | I56: S | J56: 217.62 | M56: 15 | O56: 217.62 | P56: 36.27 | Q56: 15 | T56: 1/32.99 | U56: 1 | V56: $34.99 | W56: 1 /34.99 | X56: 41.99 | Z56: 38.49 | AA56: 0.047985615 | AC56: 41.99 | AD56: 50.49 | AE56: 44.19 | AF56: 46.19 | AH56: =IF(W56<>"",(RIGHT(W56,LEN(W56)-SEARCH("/",W56,1)))/U56,"") -> 34.99 | AI56: =IF(X56<>"",X56,"") -> 41.99 | AJ56: =IF(Y56<>"",Y56,"") | AK56: =IF(Z56<>"",Z56,"") -> 38.49 | AM56: 217.62 | AN56: 14.55 | AO56: 6 | AP56: =(AM56 * 1.05) - L56 - Q56 - K56 -> 213.501 | AQ56: N | AR56: =(((AH56)-((AP56/AO56) + ((AN56 * 0.03)/AO56)))/AH56)*100 -> -1.9041155 | AS56: =(((AI56)-((AP56/AO56) + ((AN56 * 0.3)/AO56)))/AI56)*100 -> 13.524649 | AT56: =(((AJ56)-((AP56/AO56) + ((AN56 * 0.03)/AO56)))/AJ56)*100 -> #VALUE! | AU56: =(((AK56)-((AP56/AO56) + ((AN56 * 0.07)/AO56)))/AK56)*100 -> 7.1102884 | BB56: =(((AH56)-(((AP56/AO56) + ((AN56 * 0.03)/AO56))-AW56))/AH56)*100 -> -1.9041155 | BC56: =(((AI56)-(((AP56/AO56) + ((AN56 * 0.3)/AO56))-AX56))/AI56)*100 -> 13.524649 | BD56: =(((AJ56)-(((AP56/AO56) + ((AN56 * 0.03)/AO56))-AY56))/AJ56)*100 -> #VALUE! | BE56: =(((AK56)-(((AP56/AO56) + ((AN56 * 0.15)/AO56))-AZ56))/AK56)*100 -> 6.6062614 | BG56: 0005532502502 | BH56: 0055325025037 | BM56: SIMILAC POWDER IRON FORT | BN56: 850 | BO56: GR | BQ56: #N/A | BR56: #N/A | BS56: 48 | BT56: 8217.61 | BX56: 42.99 | BY56: 42.99 | BZ56: =BY56-BX56 -> 0 | CA56: -10.5 | CC56: =VLOOKUP(A56,'[1]RPT 1280 - Edmonton'!$1:$1048576,4,0) -> RC | CE56: IA | CF56: 217.62 | CG56: 0 | CH56: 0 | CI56: 15 | CJ56: =CF56-J56 -> 0 | CK56: =CG56-K56 -> 0 | CL56: =CH56-L56 -> 0 | CM56: =CI56-M56 -> 0 | CO56: 32.99 | CP56: 34.99 | CQ56: =CP56-CO56 -> 2
A57: 741405 | B57: SIMILAC POWDER GO & GROW 6 X 850 GR | C57: 507131110150 | D57: L M S | E57: DNK | F57: F | G57: F | I57: C | J57: 217.62 | M57: 15 | O57: 217.62 | P57: 36.27 | Q57: 15 | T57: 1/32.99 | U57: 1 | V57: $34.99 | W57: 1 /34.99 | X57: 41.99 | Z57: 38.49 | AA57: 0.047985615 | AC57: 41.99 | AD57: 50.49 | AE57: 44.19 | AF57: 46.19 | AH57: =IF(W57<>"",(RIGHT(W57,LEN(W57)-SEARCH("/",W57,1)))/U57,"") -> 34.99 | AI57: =IF(X57<>"",X57,"") -> 41.99 | AJ57: =IF(Y57<>"",Y57,"") | AK57: =IF(Z57<>"",Z57,"") -> 38.49 | AM57: 217.62 | AN57: 14.55 | AO57: 6 | AP57: =(AM57 * 1.05) - L57 - Q57 - K57 -> 213.501 | AQ57: N | AR57: =(((AH57)-((AP57/AO57) + ((AN57 * 0.03)/AO57)))/AH57)*100 -> -1.9041155 | AS57: =(((AI57)-((AP57/AO57) + ((AN57 * 0.3)/AO57)))/AI57)*100 -> 13.524649 | AT57: =(((AJ57)-((AP57/AO57) + ((AN57 * 0.03)/AO57)))/AJ57)*100 -> #VALUE! | AU57: =(((AK57)-((AP57/AO57) + ((AN57 * 0.07)/AO57)))/AK57)*100 -> 7.1102884 | BB57: =(((AH57)-(((AP57/AO57) + ((AN57 * 0.03)/AO57))-AW57))/AH57)*100 -> -1.9041155 | BC57: =(((AI57)-(((AP57/AO57) + ((AN57 * 0.3)/AO57))-AX57))/AI57)*100 -> 13.524649 | BD57: =(((AJ57)-(((AP57/AO57) + ((AN57 * 0.03)/AO57))-AY57))/AJ57)*100 -> #VALUE! | BE57: =(((AK57)-(((AP57/AO57) + ((AN57 * 0.15)/AO57))-AZ57))/AK57)*100 -> 6.6062614 | BG57: 0005532502521 | BH57: 0055325025228 | BM57: SIMILAC POWDER GO & GROW | BN57: 850 | BO57: GR | BQ57: #N/A | BR57: #N/A | BS57: 47 | BT57: 9496.98 | BX57: 42.99 | BY57: 42.99 | BZ57: =BY57-BX57 -> 0 | CA57: -10.5 | CC57: =VLOOKUP(A57,'[1]RPT 1280 - Edmonton'!$1:$1048576,4,0) -> RC | CE57: IA | CF57: 217.62 | CG57: 0 | CH57: 0 | CI57: 15 | CJ57: =CF57-J57 -> 0 | CK57: =CG57-K57 -> 0 | CL57: =CH57-L57 -> 0 | CM57: =CI57-M57 -> 0 | CO57: 32.99 | CP57: 34.99 | CQ57: =CP57-CO57 -> 2
A58: 6449532 | B58: PAMP SWAD NBRN HUGE 136 1 X 136 EA | C58: 507111130322 | D58: L M S | E58: DNK | F58: F | G58: F | I58: ALL | J58: 40.47 | O58: 40.47 | P58: 40.47 | Q58: 4.6 | T58: 1/32.99 | U58: 1 | V58: $34.99 | W58: 1 /34.99 | X58: 41.99 | Z58: 38.49 | AA58: 0.058506716 | AC58: 41.99 | AD58: 50.49 | AE58: 44.19 | AF58: 46.19 | AH58: =IF(W58<>"",(RIGHT(W58,LEN(W58)-SEARCH("/",W58,1)))/U58,"") -> 34.99 | AI58: =IF(X58<>"",X58,"") -> 41.99 | AJ58: =IF(Y58<>"",Y58,"") | AK58: =IF(Z58<>"",Z58,"") -> 38.49 | AM58: 40.47 | AN58: 5.67 | AO58: 1 | AP58: =(AM58 * 1.05) - L58 - Q58 - K58 -> 37.8935 | AQ58: N | AR58: =(((AH58)-((AP58/AO58) + ((AN58 * 0.03)/AO58)))/AH58)*100 -> -8.7842241 | AS58: =(((AI58)-((AP58/AO58) + ((AN58 * 0.3)/AO58)))/AI58)*100 -> 5.7049297 | AT58: =(((AJ58)-((AP58/AO58) + ((AN58 * 0.03)/AO58)))/AJ58)*100 -> #VALUE! | AU58: =(((AK58)-((AP58/AO58) + ((AN58 * 0.07)/AO58)))/AK58)*100 -> 0.51857625 | BB58: =(((AH58)-(((AP58/AO58) + ((AN58 * 0.03)/AO58))-AW58))/AH58)*100 -> -8.7842241 | BC58: =(((AI58)-(((AP58/AO58) + ((AN58 * 0.3)/AO58))-AX58))/AI58)*100 -> 5.7049297 | BD58: =(((AJ58)-(((AP58/AO58) + ((AN58 * 0.03)/AO58))-AY58))/AJ58)*100 -> #VALUE! | BE58: =(((AK58)-(((AP58/AO58) + ((AN58 * 0.15)/AO58))-AZ58))/AK58)*100 -> -0.65991167 | BG58: 0003077203549 | BH58: 0030772035495 | BM58: PAMP SWAD NBRN HUGE 136 | BN58: 136 | BO58: EA | BQ58: DNK | BR58: #N/A | BS58: 52 | BT58: 537.76 | BX58: 43.99 | BY58: 43.99 | BZ58: =BY58-BX58 -> 0 | CA58: -4.37 | CC58: =VLOOKUP(A58,'[1]RPT 1280 - Edmonton'!$1:$1048576,4,0) -> RC | CE58: IA | CF58: 40.47 | CG58: 0 | CH58: 0 | CI58: 0 | CJ58: =CF58-J58 -> 0 | CK58: =CG58-K58 -> 0 | CL58: =CH58-L58 -> 0 | CM58: =CI58-M58 -> 0 | CO58: 32.99 | CP58: 34.99 | CQ58: =CP58-CO58 -> 2
A59: 6449540 | B59: PAMP SWAD SZ 1 HUGE 160 1 X 160 EA | C59: 507111130322 | D59: L M S | E59: DNK | F59: F | G59: F | J59: =J58 -> 40.47 | O59: =O58 -> 40.47 | P59: =P58 -> 40.47 | Q59: 4.6 | AH59: =IF(W59<>"",(RIGHT(W59,LEN(W59)-SEARCH("/",W59,1)))/U59,"") | AI59: =IF(X59<>"",X59,"") | AJ59: =IF(Y59<>"",Y59,"") | AK59: =IF(Z59<>"",Z59,"") | BG59: 0003077203550 | BH59: 0030772035501 | BM59: PAMP SWAD SZ 1 HUGE 160 | BN59: 160 | BO59: EA | BQ59: DNK | BR59: #N/A | BS59: 51 | BT59: 178.93 | BX59: 43.99 | BY59: 43.99 | BZ59: =BY59-BX59 -> 0 | CA59: -4.37 | CC59: =VLOOKUP(A59,'[1]RPT 1280 - Edmonton'!$1:$1048576,4,0) -> RC | CE59: IA | CF59: 40.47 | CG59: 0 | CH59: 0 | CI59: 0 | CJ59: =CF59-J59 -> 0 | CK59: =CG59-K59 -> 0 | CL59: =CH59-L59 -> 0 | CM59: =CI59-M59 -> 0
A60: 6449714 | B60: PAMP SWAD SZ 6 HUGE 80CT 1 X 80 EA | C60: 507111130322 | D60: L M S | E60: DNK | F60: F | G60: F | J60: =J59 -> 40.47 | O60: =O59 -> 40.47 | P60: =P59 -> 40.47 | Q60: 5.15 | AH60: =IF(W60<>"",(RIGHT(W60,LEN(W60)-SEARCH("/",W60,1)))/U60,"") | AI60: =IF(X60<>"",X60,"") | AJ60: =IF(Y60<>"",Y60,"") | AK60: =IF(Z60<>"",Z60,"") | BG60: 0003077204282 | BH60: 0030772042820 | BM60: PAMP SWAD SZ 6 HUGE 80CT | BN60: 80 | BO60: EA | BQ60: DNK | BR60: #N/A | BS60: 53 | BT60: 662.71 | BX60: 43.99 | BY60: 43.99 | BZ60: =BY60-BX60 -> 0 | CA60: -4.9 | CC60: =VLOOKUP(A60,'[1]RPT 1280 - Edmonton'!$1:$1048576,4,0) -> RC | CE60: IA | CF60: 40.47 | CG60: 0 | CH60: 0 | CI60: 0 | CJ60: =CF60-J60 -> 0 | CK60: =CG60-K60 -> 0 | CL60: =CH60-L60 -> 0 | CM60: =CI60-M60 -> 0
A61: 6449672 | B61: PAMP SWAD SZ 2 HUGE 144 1 X 144 EA | C61: 507111130322 | D61: L M S | E61: DNK | F61: F | G61: F | J61: =J60 -> 40.47 | O61: =O60 -> 40.47 | P61: =P60 -> 40.47 | Q61: 4.6 | AH61: =IF(W61<>"",(RIGHT(W61,LEN(W61)-SEARCH("/",W61,1)))/U61,"") | AI61: =IF(X61<>"",X61,"") | AJ61: =IF(Y61<>"",Y61,"") | AK61: =IF(Z61<>"",Z61,"") | BG61: 0003077203551 | BH61: 0030772035518 | BM61: PAMP SWAD SZ 2 HUGE 144 | BN61: 144 | BO61: EA | BQ61: DNK | BR61: #N/A | BS61: 50 | BT61: 1872.44 | BX61: 43.99 | BY61: 43.99 | BZ61: =BY61-BX61 -> 0 | CA61: -4.36 | CC61: =VLOOKUP(A61,'[1]RPT 1280 - Edmonton'!$1:$1048576,4,0) -> RC | CE61: IA | CF61: 40.47 | CG61: 0 | CH61: 0 | CI61: 0 | CJ61: =CF61-J61 -> 0 | CK61: =CG61-K61 -> 0 | CL61: =CH61-L61 -> 0 | CM61: =CI61-M61 -> 0
A62: 6449698 | B62: PAMP SWADDLERS SZ4 HUGE 116 1 X 116 EA | C62: 507111130332 | D62: L M S | E62: DNK | F62: F | G62: F | J62: =J61 -> 40.47 | O62: =O61 -> 40.47 | P62: =P61 -> 40.47 | Q62: 4.6 | AH62: =IF(W62<>"",(RIGHT(W62,LEN(W62)-SEARCH("/",W62,1)))/U62,"") | AI62: =IF(X62<>"",X62,"") | AJ62: =IF(Y62<>"",Y62,"") | AK62: =IF(Z62<>"",Z62,"") | BG62: 0003077204280 | BH62: 0030772042806 | BM62: PAMP SWADDLERS SZ4 HUGE 116 | BN62: 116 | BO62: EA | BQ62: DNK | BR62: #N/A | BS62: 52 | BT62: 1663.33 | BX62: 43.99 | BY62: 43.99 | BZ62: =BY62-BX62 -> 0 | CA62: -4.37 | CC62: =VLOOKUP(A62,'[1]RPT 1280 - Edmonton'!$1:$1048576,4,0) -> RC | CE62: IA | CF62: 40.47 | CG62: 0 | CH62: 0 | CI62: 0 | CJ62: =CF62-J62 -> 0 | CK62: =CG62-K62 -> 0 | CL62: =CH62-L62 -> 0 | CM62: =CI62-M62 -> 0
A63: 6449706 | B63: PAMP SWADDLERS SZ5 HUGE 100CT 1 X 100 EA | C63: 507111130332 | D63: L M S | E63: DNK | F63: F | G63: F | J63: =J62 -> 40.47 | O63: =O62 -> 40.47 | P63: =P62 -> 40.47 | Q63: 4.6 | AH63: =IF(W63<>"",(RIGHT(W63,LEN(W63)-SEARCH("/",W63,1)))/U63,"") | AI63: =IF(X63<>"",X63,"") | AJ63: =IF(Y63<>"",Y63,"") | AK63: =IF(Z63<>"",Z63,"") | BG63: 0003077203554 | BH63: 0030772035549 | BM63: PAMP SWADDLERS SZ5 HUGE 100CT | BN63: 100 | BO63: EA | BQ63: DNK | BR63: #N/A | BS63: 54 | BT63: 575.88 | BX63: 43.99 | BY63: 43.99 | BZ63: =BY63-BX63 -> 0 | CA63: -4.37 | CC63: =VLOOKUP(A63,'[1]RPT 1280 - Edmonton'!$1:$1048576,4,0) -> RC | CE63: IA | CF63: 40.47 | CG63: 0 | CH63: 0 | CI63: 0 | CJ63: =CF63-J63 -> 0 | CK63: =CG63-K63 -> 0 | CL63: =CH63-L63 -> 0 | CM63: =CI63-M63 -> 0
A64: 6449680 | B64: PAMP SWADDLERS SZ3 HUGE 132CT 1 X 132 EA | C64: 507111130332 | D64: L M S | E64: DNK | F64: F | G64: F | J64: =J63 -> 40.47 | O64: =O63 -> 40.47 | P64: =P63 -> 40.47 | Q64: 4.6 | AH64: =IF(W64<>"",(RIGHT(W64,LEN(W64)-SEARCH("/",W64,1)))/U64,"") | AI64: =IF(X64<>"",X64,"") | AJ64: =IF(Y64<>"",Y64,"") | AK64: =IF(Z64<>"",Z64,"") | BG64: 0003077203552 | BH64: 0030772035525 | BM64: PAMP SWADDLERS SZ3 HUGE 132CT | BN64: 132 | BO64: EA | BQ64: DNK | BR64: #N/A | BS64: 52 | BT64: 640.87 | BX64: 43.99 | BY64: 43.99 | BZ64: =BY64-BX64 -> 0 | CA64: -4.37 | CC64: =VLOOKUP(A64,'[1]RPT 1280 - Edmonton'!$1:$1048576,4,0) -> RC | CE64: IA | CF64: 40.47 | CG64: 0 | CH64: 0 | CI64: 0 | CJ64: =CF64-J64 -> 0 | CK64: =CG64-K64 -> 0 | CL64: =CH64-L64 -> 0 | CM64: =CI64-M64 -> 0
A65: 6522999 | B65: PAMP BDRY SZ6 MEGA 124CT 1 X 124 EA | C65: 507111130355 | D65: L M S | E65: DNK | F65: F | G65: F | I65: ALL | J65: 38.66 | O65: 38.66 | P65: 38.66 | T65: 1/32.99 | U65: 1 | V65: $34.99 | W65: 1 /34.99 | X65: 41.99 | Z65: 38.49 | AA65: 0.050491569 | AC65: 41.99 | AD65: 50.49 | AE65: 44.19 | AF65: 46.19 | AH65: =IF(W65<>"",(RIGHT(W65,LEN(W65)-SEARCH("/",W65,1)))/U65,"") -> 34.99 | AI65: =IF(X65<>"",X65,"") -> 41.99 | AJ65: =IF(Y65<>"",Y65,"") | AK65: =IF(Z65<>"",Z65,"") -> 38.49 | AM65: 38.66 | AN65: 13.86 | AO65: 1 | AP65: =(AM65 * 1.05) - L65 - Q65 - K65 -> 40.593 | AQ65: N | AR65: =(((AH65)-((AP65/AO65) + ((AN65 * 0.03)/AO65)))/AH65)*100 -> -17.201486 | AS65: =(((AI65)-((AP65/AO65) + ((AN65 * 0.3)/AO65)))/AI65)*100 -> -6.5753751 | AT65: =(((AJ65)-((AP65/AO65) + ((AN65 * 0.03)/AO65)))/AJ65)*100 -> #VALUE! | AU65: =(((AK65)-((AP65/AO65) + ((AN65 * 0.07)/AO65)))/AK65)*100 -> -7.9844115 | BB65: =(((AH65)-(((AP65/AO65) + ((AN65 * 0.03)/AO65))-AW65))/AH65)*100 -> -17.201486 | BC65: =(((AI65)-(((AP65/AO65) + ((AN65 * 0.3)/AO65))-AX65))/AI65)*100 -> -6.5753751 | BD65: =(((AJ65)-(((AP65/AO65) + ((AN65 * 0.03)/AO65))-AY65))/AJ65)*100 -> #VALUE! | BE65: =(((AK65)-(((AP65/AO65) + ((AN65 * 0.15)/AO65))-AZ65))/AK65)*100 -> -10.86516 | BG65: 0003077219795 | BH65: 0030772197957 | BM65: PAMP BDRY SZ6 MEGA 124CT | BN65: 124 | BO65: EA | BQ65: DNK | BR65: #N/A | BX65: 43.99 | BY65: 43.99 | BZ65: =BY65-BX65 -> 0 | CC65: =VLOOKUP(A65,'[1]RPT 1280 - Edmonton'!$1:$1048576,4,0) -> RC | CE65: IA | CF65: 38.66 | CG65: 0 | CH65: 0 | CI65: 0 | CJ65: =CF65-J65 -> 0 | CK65: =CG65-K65 -> 0 | CL65: =CH65-L65 -> 0 | CM65: =CI65-M65 -> 0 | CO65: 32.99 | CP65: 34.99 | CQ65: =CP65-CO65 -> 2
A66: 6522924 | B66: PAMP BDRY SZ5 MEGA 138CT 1 X 138 EA | C66: 507111130355 | D66: L M S | E66: DNK | F66: F | G66: F | J66: =J65 -> 38.66 | O66: =O65 -> 38.66 | P66: =P65 -> 38.66 | AH66: =IF(W66<>"",(RIGHT(W66,LEN(W66)-SEARCH("/",W66,1)))/U66,"") | AI66: =IF(X66<>"",X66,"") | AJ66: =IF(Y66<>"",Y66,"") | AK66: =IF(Z66<>"",Z66,"") | BG66: 0003077219788 | BH66: 0030772197889 | BM66: PAMP BDRY SZ5 MEGA 138CT | BN66: 138 | BO66: EA | BQ66: DNK | BR66: #N/A | BX66: 43.99 | BY66: 43.99 | BZ66: =BY66-BX66 -> 0 | CC66: =VLOOKUP(A66,'[1]RPT 1280 - Edmonton'!$1:$1048576,4,0) -> RC | CE66: IA | CF66: 38.66 | CG66: 0 | CH66: 0 | CI66: 0 | CJ66: =CF66-J66 -> 0 | CK66: =CG66-K66 -> 0 | CL66: =CH66-L66 -> 0 | CM66: =CI66-M66 -> 0
A67: 6522981 | B67: PAMP BDRY SZ4 MEGA 156CT 1 X 156 EA | C67: 507111130355 | D67: L M S | E67: DNK | F67: F | G67: F | J67: =J66 -> 38.66 | O67: =O66 -> 38.66 | P67: =P66 -> 38.66 | AH67: =IF(W67<>"",(RIGHT(W67,LEN(W67)-SEARCH("/",W67,1)))/U67,"") | AI67: =IF(X67<>"",X67,"") | AJ67: =IF(Y67<>"",Y67,"") | AK67: =IF(Z67<>"",Z67,"") | BG67: 0003077219791 | BH67: 0030772197919 | BM67: PAMP BDRY SZ4 MEGA 156CT | BN67: 156 | BO67: EA | BQ67: DNK | BR67: #N/A | BX67: 43.99 | BY67: 43.99 | BZ67: =BY67-BX67 -> 0 | CC67: =VLOOKUP(A67,'[1]RPT 1280 - Edmonton'!$1:$1048576,4,0) -> RC | CE67: IA | CF67: 38.66 | CG67: 0 | CH67: 0 | CI67: 0 | CJ67: =CF67-J67 -> 0 | CK67: =CG67-K67 -> 0 | CL67: =CH67-L67 -> 0 | CM67: =CI67-M67 -> 0
A68: 2456952 | B68: AVE DLY MOIST LOTION 3 X 532 ML | C68: 507215050510 | D68: L M | E68: DNK | F68: B | G68: B | I68: C | J68: 140.28 | L68: 18.36 | M68: 7.83 | N68: 7.83 | O68: 121.92 | P68: 10.16 | Q68: 31.32 | T68: 1 / $8.99 | U68: 1 | V68: $8.99 | W68: 1 /8.99 | X68: 10.79 | Z68: 9.99 | AA68: 0.10521598 | AC68: 10.79 | AD68: 12.99 | AE68: 11.49 | AF68: 11.99 | AH68: =IF(W68<>"",(RIGHT(W68,LEN(W68)-SEARCH("/",W68,1)))/U68,"") -> 8.99 | AI68: =IF(X68<>"",X68,"") -> 10.79 | AJ68: =IF(Y68<>"",Y68,"") | AK68: =IF(Z68<>"",Z68,"") -> 9.99 | AM68: 30.48 | AN68: 4.25 | AO68: 3 | AP68: =(AM68 * 1.05) - L68 - Q68 - K68 -> -17.676 | AQ68: N | AR68: =(((AH68)-((AP68/AO68) + ((AN68 * 0.03)/AO68)))/AH68)*100 -> 165.06674 | AS68: =(((AI68)-((AP68/AO68) + ((AN68 * 0.3)/AO68)))/AI68)*100 -> 150.66728 | AT68: =(((AJ68)-((AP68/AO68) + ((AN68 * 0.03)/AO68)))/AJ68)*100 -> #VALUE! | AU68: =(((AK68)-((AP68/AO68) + ((AN68 * 0.07)/AO68)))/AK68)*100 -> 157.98632 | BB68: =(((AH68)-(((AP68/AO68) + ((AN68 * 0.03)/AO68))-AW68))/AH68)*100 -> 165.06674 | BC68: =(((AI68)-(((AP68/AO68) + ((AN68 * 0.3)/AO68))-AX68))/AI68)*100 -> 150.66728 | BD68: =(((AJ68)-(((AP68/AO68) + ((AN68 * 0.03)/AO68))-AY68))/AJ68)*100 -> #VALUE! | BE68: =(((AK68)-(((AP68/AO68) + ((AN68 * 0.15)/AO68))-AZ68))/AK68)*100 -> 156.85185 | BG68: 0006260006025 | BH68: 0038137006025 | BM68: AVE DLY MOIST LOTION | BN68: 532 | BO68: ML | BQ68: #N/A | BR68: #N/A | BS68: 50 | BT68: 847.19 | BX68: 20.99 | BY68: 20.99 | BZ68: =BY68-BX68 -> 0 | CC68: =VLOOKUP(A68,'[1]RPT 1280 - Edmonton'!$1:$1048576,4,0) -> #N/A | CE68: JB | CF68: 140.28 | CG68: 0 | CH68: 18.36 | CI68: 31.32 | CJ68: =CF68-J68 -> 0 | CK68: =CG68-K68 -> 0 | CL68: =CH68-L68 -> 0 | CM68: =CI68-M68 -> 23.49 | CO68: 8.99 | CP68: 8.99 | CQ68: =CP68-CO68 -> 0
A69: 2456960 | B69: AVE SKN RELIEF MOIST LTN FF 3 X 532 ML | C69: 507215050510 | D69: L M | E69: DNK | F69: B | G69: B | J69: =J68 -> 140.28 | L69: =L68 -> 18.36 | M69: 7.83 | N69: 7.83 | O69: =O68 -> 121.92 | P69: =P68 -> 10.16 | Q69: 31.32 | AH69: =IF(W69<>"",(RIGHT(W69,LEN(W69)-SEARCH("/",W69,1)))/U69,"") | AI69: =IF(X69<>"",X69,"") | AJ69: =IF(Y69<>"",Y69,"") | AK69: =IF(Z69<>"",Z69,"") | BG69: 0006260006298 | BH69: 0038137006298 | BM69: AVE SKN RELIEF MOIST LTN FF | BN69: 532 | BO69: ML | BQ69: #N/A | BR69: #N/A | BS69: 53 | BT69: 266.87 | BX69: 20.99 | BY69: 20.99 | BZ69: =BY69-BX69 -> 0 | CC69: =VLOOKUP(A69,'[1]RPT 1280 - Edmonton'!$1:$1048576,4,0) -> #N/A | CE69: JB | CF69: 140.28 | CG69: 0 | CH69: 18.36 | CI69: 31.32 | CJ69: =CF69-J69 -> 0 | CK69: =CG69-K69 -> 0 | CL69: =CH69-L69 -> 0 | CM69: =CI69-M69 -> 23.49
A70: 2456986 | B70: AVEENO DAILY SHEER HYD 3 X 532 ML | C70: 507215050510 | D70: L M | E70: DNK | F70: B | G70: B | J70: =J69 -> 140.28 | L70: =L69 -> 18.36 | M70: 7.83 | N70: 7.83 | O70: =O69 -> 121.92 | P70: =P69 -> 10.16 | Q70: 31.32 | AH70: =IF(W70<>"",(RIGHT(W70,LEN(W70)-SEARCH("/",W70,1)))/U70,"") | AI70: =IF(X70<>"",X70,"") | AJ70: =IF(Y70<>"",Y70,"") | AK70: =IF(Z70<>"",Z70,"") | BG70: 0006260096305 | BH70: 0006260096305 | BM70: AVEENO DAILY SHEER HYD | BN70: 532 | BO70: ML | BQ70: #N/A | BR70: #N/A | BS70: 54 | BT70: 131.82 | BX70: 20.99 | BY70: 20.99 | BZ70: =BY70-BX70 -> 0 | CC70: =VLOOKUP(A70,'[1]RPT 1280 - Edmonton'!$1:$1048576,4,0) -> #N/A | CE70: JB | CF70: 140.28 | CG70: 0 | CH70: 18.36 | CI70: 31.32 | CJ70: =CF70-J70 -> 0 | CK70: =CG70-K70 -> 0 | CL70: =CH70-L70 -> 0 | CM70: =CI70-M70 -> 23.49
A71: 979740 | B71: AVEENO STRSS RLEF MOIST LOTION 3 X 532 ML | C71: 507215050510 | D71: L M | E71: DNK | F71: B | G71: B | J71: =J70 -> 140.28 | L71: =L70 -> 18.36 | M71: 7.83 | N71: 7.83 | O71: =O70 -> 121.92 | P71: =P70 -> 10.16 | Q71: 31.32 | AH71: =IF(W71<>"",(RIGHT(W71,LEN(W71)-SEARCH("/",W71,1)))/U71,"") | AI71: =IF(X71<>"",X71,"") | AJ71: =IF(Y71<>"",Y71,"") | AK71: =IF(Z71<>"",Z71,"") | BG71: 0006260095903 | BH71: 0006260095903 | BM71: AVEENO STRSS RLEF MOIST LOTION | BN71: 532 | BO71: ML | BQ71: #N/A | BR71: #N/A | BS71: 53 | BT71: 267.34 | BX71: 20.99 | BY71: 20.99 | BZ71: =BY71-BX71 -> 0 | CC71: =VLOOKUP(A71,'[1]RPT 1280 - Edmonton'!$1:$1048576,4,0) -> #N/A | CE71: JB | CF71: 140.28 | CG71: 0 | CH71: 18.36 | CI71: 31.32 | CJ71: =CF71-J71 -> 0 | CK71: =CG71-K71 -> 0 | CL71: =CH71-L71 -> 0 | CM71: =CI71-M71 -> 23.49
A72: 6314785 | B72: AVEENO BDYWASH MOISTRIZNG 532 ML 3 X 532 ML | C72: 507236010147 | D72: L M | E72: DNK | F72: B | G72: B | I72: C | J72: 102.12 | M72: 2.88 | N72: 2.88 | O72: 102.12 | P72: 8.51 | Q72: 11.52 | T72: 1 / $8.99 | U72: 1 | V72: $8.99 | W72: 1 /8.99 | X72: 10.79 | Z72: 9.99 | AA72: 0.10519559 | AC72: 10.79 | AD72: 12.99 | AE72: 11.49 | AF72: 11.99 | AH72: =IF(W72<>"",(RIGHT(W72,LEN(W72)-SEARCH("/",W72,1)))/U72,"") -> 8.99 | AI72: =IF(X72<>"",X72,"") -> 10.79 | AJ72: =IF(Y72<>"",Y72,"") | AK72: =IF(Z72<>"",Z72,"") -> 9.99 | AM72: 25.53 | AN72: 4.25 | AO72: 3 | AP72: =(AM72 * 1.05) - L72 - Q72 - K72 -> 15.2865 | AQ72: N | AR72: =(((AH72)-((AP72/AO72) + ((AN72 * 0.03)/AO72)))/AH72)*100 -> 42.847608 | AS72: =(((AI72)-((AP72/AO72) + ((AN72 * 0.3)/AO72)))/AI72)*100 -> 48.836886 | AT72: =(((AJ72)-((AP72/AO72) + ((AN72 * 0.03)/AO72)))/AJ72)*100 -> #VALUE! | AU72: =(((AK72)-((AP72/AO72) + ((AN72 * 0.07)/AO72)))/AK72)*100 -> 48.001335 | BB72: =(((AH72)-(((AP72/AO72) + ((AN72 * 0.03)/AO72))-AW72))/AH72)*100 -> 42.847608 | BC72: =(((AI72)-(((AP72/AO72) + ((AN72 * 0.3)/AO72))-AX72))/AI72)*100 -> 48.836886 | BD72: =(((AJ72)-(((AP72/AO72) + ((AN72 * 0.03)/AO72))-AY72))/AJ72)*100 -> #VALUE! | BE72: =(((AK72)-(((AP72/AO72) + ((AN72 * 0.15)/AO72))-AZ72))/AK72)*100 -> 46.866867 | BG72: 0006260006384 | BH72: 0038137006384 | BM72: AVEENO BDYWASH MOISTRIZNG 532 ML | BN72: 532 | BO72: ML | BQ72: #N/A | BR72: #N/A | BS72: 52 | BT72: 254.88 | BX72: 12.29 | BY72: 12.29 | BZ72: =BY72-BX72 -> 0 | CC72: =VLOOKUP(A72,'[1]RPT 1280 - Edmonton'!$1:$1048576,4,0) -> #N/A | CE72: JB | CF72: 102.12 | CG72: 0 | CH72: 0 | CI72: 11.52 | CJ72: =CF72-J72 -> 0 | CK72: =CG72-K72 -> 0 | CL72: =CH72-L72 -> 0 | CM72: =CI72-M72 -> 8.64 | CN72: inner | CO72: 8.99 | CP72: 8.99 | CQ72: =CP72-CO72 -> 0
A73: 6314793 | B73: AVEENO BDYWASH FRAG FREE 532 ML 3 X 532 ML | C73: 507236010147 | D73: L M | E73: DNK | F73: B | G73: B | J73: =J72 -> 102.12 | M73: 2.88 | N73: 2.88 | O73: =O72 -> 102.12 | P73: =P72 -> 8.51 | Q73: 11.52 | AH73: =IF(W73<>"",(RIGHT(W73,LEN(W73)-SEARCH("/",W73,1)))/U73,"") | AI73: =IF(X73<>"",X73,"") | AJ73: =IF(Y73<>"",Y73,"") | AK73: =IF(Z73<>"",Z73,"") | BG73: 0006260006292 | BH73: 0038137006292 | BM73: AVEENO BDYWASH FRAG FREE 532 ML | BN73: 532 | BO73: ML | BQ73: #N/A | BR73: #N/A | BS73: 48 | BT73: 476.5 | BX73: 12.29 | BY73: 12.29 | BZ73: =BY73-BX73 -> 0 | CC73: =VLOOKUP(A73,'[1]RPT 1280 - Edmonton'!$1:$1048576,4,0) -> #N/A | CE73: JB | CF73: 102.12 | CG73: 0 | CH73: 0 | CI73: 11.52 | CJ73: =CF73-J73 -> 0 | CK73: =CG73-K73 -> 0 | CL73: =CH73-L73 -> 0 | CM73: =CI73-M73 -> 8.64 | CN73: inner
A74: 625988 | B74: GATORADE ORANGE 591ML 4 X 6 EA | C74: 010126020200 | D74: L M | E74: DNK-Direct | F74: B | G74: B | I74: E | J74: 33.01 | K74: 6.03 | O74: 26.98 | P74: 6.745 | T74: 1 / $5.99 | U74: 1 | V74: $5.99 | W74: 1 /5.99 | X74: 7.19 | Z74: 6.99 | AA74: 0.014190317 | AC74: 7.19 | AD74: 8.59 | AE74: 7.59 | AF74: 8.49 | AH74: =IF(W74<>"",(RIGHT(W74,LEN(W74)-SEARCH("/",W74,1)))/U74,"") -> 5.99 | AI74: =IF(X74<>"",X74,"") -> 7.19 | AJ74: =IF(Y74<>"",Y74,"") | AK74: =IF(Z74<>"",Z74,"") -> 6.99 | AM74: 29.65 | AN74: 34.4 | AO74: 4 | AP74: =(AM74 * 1.05) - L74 - Q74 - K74 -> 25.1025 | AQ74: N | AR74: =(((AH74)-((AP74/AO74) + ((AN74 * 0.03)/AO74)))/AH74)*100 -> -9.0755426 | AS74: =(((AI74)-((AP74/AO74) + ((AN74 * 0.3)/AO74)))/AI74)*100 -> -23.165855 | AT74: =(((AJ74)-((AP74/AO74) + ((AN74 * 0.03)/AO74)))/AJ74)*100 -> #VALUE! | AU74: =(((AK74)-((AP74/AO74) + ((AN74 * 0.07)/AO74)))/AK74)*100 -> 1.6076538 | BB74: =(((AH74)-(((AP74/AO74) + ((AN74 * 0.03)/AO74))-AW74))/AH74)*100 -> -9.0755426 | BC74: =(((AI74)-(((AP74/AO74) + ((AN74 * 0.3)/AO74))-AX74))/AI74)*100 -> -23.165855 | BD74: =(((AJ74)-(((AP74/AO74) + ((AN74 * 0.03)/AO74))-AY74))/AJ74)*100 -> #VALUE! | BE74: =(((AK74)-(((AP74/AO74) + ((AN74 * 0.15)/AO74))-AZ74))/AK74)*100 -> -8.2349785 | BG74: 0005557742050 | BH74: 0055577920503 | BJ74: Gatorade Sport Beverage 6 x 591 mL or G2 PLUS DEPOSIT | BM74: GATORADE ORANGE 591ML | BN74: 6 | BO74: EA | BP74: 625988 | BQ74: #N/A | BR74: #N/A | BS74: 14 | BT74: 19369.48 | BX74: 9.29 | BY74: 9.29 | BZ74: =BY74-BX74 -> 0 | CC74: =VLOOKUP(A74,'[1]RPT 1280 - Edmonton'!$1:$1048576,4,0) -> PC | CE74: DB | CF74: 33.01 | CG74: 6.03 | CH74: 0 | CI74: 0 | CJ74: =CF74-J74 -> 0 | CK74: =CG74-K74 -> 0 | CL74: =CH74-L74 -> 0 | CM74: =CI74-M74 -> 0 | CO74: 5.99 | CP74: 5.99 | CQ74: =CP74-CO74 -> 0
A75: 625830 | B75: GATORADE COOL BLUE 591ML 4 X 6 EA | C75: 010126020200 | D75: L M | E75: DNK-Direct | F75: B | G75: B | I75: S | J75: 33.97 | K75: 6.03 | O75: 27.94 | P75: 6.985 | T75: 1 / $5.99 | U75: 1 | V75: $5.99 | W75: 1 /5.99 | X75: 7.19 | Z75: 6.99 | AA75: 0.014190317 | AC75: 7.19 | AD75: 8.59 | AE75: 7.59 | AF75: 8.49 | AH75: =IF(W75<>"",(RIGHT(W75,LEN(W75)-SEARCH("/",W75,1)))/U75,"") -> 5.99 | AI75: =IF(X75<>"",X75,"") -> 7.19 | AJ75: =IF(Y75<>"",Y75,"") | AK75: =IF(Z75<>"",Z75,"") -> 6.99 | AM75: 29.65 | AN75: 34.4 | AO75: 4 | AP75: =(AM75 * 1.05) - L75 - Q75 - K75 -> 25.1025 | AQ75: N | AR75: =(((AH75)-((AP75/AO75) + ((AN75 * 0.03)/AO75)))/AH75)*100 -> -9.0755426 | AS75: =(((AI75)-((AP75/AO75) + ((AN75 * 0.3)/AO75)))/AI75)*100 -> -23.165855 | AT75: =(((AJ75)-((AP75/AO75) + ((AN75 * 0.03)/AO75)))/AJ75)*100 -> #VALUE! | AU75: =(((AK75)-((AP75/AO75) + ((AN75 * 0.07)/AO75)))/AK75)*100 -> 1.6076538 | BB75: =(((AH75)-(((AP75/AO75) + ((AN75 * 0.03)/AO75))-AW75))/AH75)*100 -> -9.0755426 | BC75: =(((AI75)-(((AP75/AO75) + ((AN75 * 0.3)/AO75))-AX75))/AI75)*100 -> -23.165855 | BD75: =(((AJ75)-(((AP75/AO75) + ((AN75 * 0.03)/AO75))-AY75))/AJ75)*100 -> #VALUE! | BE75: =(((AK75)-(((AP75/AO75) + ((AN75 * 0.15)/AO75))-AZ75))/AK75)*100 -> -8.2349785 | BG75: 0005557742051 | BH75: 0055577920510 | BJ75: Gatorade Sport Beverage 6 x 591 mL or G2 PLUS DEPOSIT | BM75: GATORADE COOL BLUE 591ML | BN75: 6 | BO75: EA | BP75: 625830 | BQ75: #N/A | BR75: #N/A | BS75: 12 | BT75: 31687.37 | BX75: 9.29 | BY75: 9.29 | BZ75: =BY75-BX75 -> 0 | CC75: =VLOOKUP(A75,'[1]RPT 1280 - Edmonton'!$1:$1048576,4,0) -> PC | CE75: DB | CF75: 33.97 | CG75: 6.03 | CH75: 0 | CI75: 0 | CJ75: =CF75-J75 -> 0 | CK75: =CG75-K75 -> 0 | CL75: =CH75-L75 -> 0 | CM75: =CI75-M75 -> 0 | CO75: 5.99 | CP75: 5.99 | CQ75: =CP75-CO75 -> 0
A76: 484568 | B76: GATORADE FRT PUNCH 6X591ML 4 X 6 EA | C76: 010126020200 | D76: L M | E76: DNK-Direct | F76: B | G76: B | I76: C | J76: 33.01 | K76: 6.03 | O76: 26.98 | P76: 6.745 | T76: 1 / $5.99 | U76: 1 | V76: $5.99 | W76: 1 /5.99 | X76: 7.19 | Z76: 6.99 | AA76: 0.014190317 | AC76: 7.19 | AD76: 8.59 | AE76: 7.59 | AF76: 8.49 | AH76: =IF(W76<>"",(RIGHT(W76,LEN(W76)-SEARCH("/",W76,1)))/U76,"") -> 5.99 | AI76: =IF(X76<>"",X76,"") -> 7.19 | AJ76: =IF(Y76<>"",Y76,"") | AK76: =IF(Z76<>"",Z76,"") -> 6.99 | AM76: 29.65 | AN76: 34.4 | AO76: 4 | AP76: =(AM76 * 1.05) - L76 - Q76 - K76 -> 25.1025 | AQ76: N | AR76: =(((AH76)-((AP76/AO76) + ((AN76 * 0.03)/AO76)))/AH76)*100 -> -9.0755426 | AS76: =(((AI76)-((AP76/AO76) + ((AN76 * 0.3)/AO76)))/AI76)*100 -> -23.165855 | AT76: =(((AJ76)-((AP76/AO76) + ((AN76 * 0.03)/AO76)))/AJ76)*100 -> #VALUE! | AU76: =(((AK76)-((AP76/AO76) + ((AN76 * 0.07)/AO76)))/AK76)*100 -> 1.6076538 | BB76: =(((AH76)-(((AP76/AO76) + ((AN76 * 0.03)/AO76))-AW76))/AH76)*100 -> -9.0755426 | BC76: =(((AI76)-(((AP76/AO76) + ((AN76 * 0.3)/AO76))-AX76))/AI76)*100 -> -23.165855 | BD76: =(((AJ76)-(((AP76/AO76) + ((AN76 * 0.03)/AO76))-AY76))/AJ76)*100 -> #VALUE! | BE76: =(((AK76)-(((AP76/AO76) + ((AN76 * 0.15)/AO76))-AZ76))/AK76)*100 -> -8.2349785 | BG76: 0005557742075 | BH76: 0055577920756 | BJ76: Gatorade Sport Beverage 6 x 591 mL or G2 PLUS DEPOSIT | BM76: GATORADE FRT PUNCH 6X591ML | BN76: 6 | BO76: EA | BP76: 484568 | BQ76: #N/A | BR76: #N/A | BS76: 14 | BT76: 22197.3 | BX76: 9.29 | BY76: 9.29 | BZ76: =BY76-BX76 -> 0 | CC76: =VLOOKUP(A76,'[1]RPT 1280 - Edmonton'!$1:$1048576,4,0) -> PC | CE76: DB | CF76: 33.01 | CG76: 6.03 | CH76: 0 | CI76: 0 | CJ76: =CF76-J76 -> 0 | CK76: =CG76-K76 -> 0 | CL76: =CH76-L76 -> 0 | CM76: =CI76-M76 -> 0 | CO76: 5.99 | CP76: 5.99 | CQ76: =CP76-CO76 -> 0
A77: 221614 | B77: GATORADE G2 GRP 591ML 4 X 6 EA | C77: 010126020200 | D77: L M | E77: DNK-Direct | F77: B | G77: B | I77: W | J77: 30.13 | K77: 6.03 | O77: 24.1 | P77: 6.025 | T77: 1 / $5.99 | U77: 1 | V77: $5.99 | W77: 1 /5.99 | X77: 7.19 | Z77: 6.99 | AA77: 0.014190317 | AC77: 7.19 | AD77: 8.59 | AE77: 7.59 | AF77: 8.49 | AH77: =IF(W77<>"",(RIGHT(W77,LEN(W77)-SEARCH("/",W77,1)))/U77,"") -> 5.99 | AI77: =IF(X77<>"",X77,"") -> 7.19 | AJ77: =IF(Y77<>"",Y77,"") | AK77: =IF(Z77<>"",Z77,"") -> 6.99 | AM77: 29.65 | AN77: 34.4 | AO77: 4 | AP77: =(AM77 * 1.05) - L77 - Q77 - K77 -> 25.1025 | AQ77: N | AR77: =(((AH77)-((AP77/AO77) + ((AN77 * 0.03)/AO77)))/AH77)*100 -> -9.0755426 | AS77: =(((AI77)-((AP77/AO77) + ((AN77 * 0.3)/AO77)))/AI77)*100 -> -23.165855 | AT77: =(((AJ77)-((AP77/AO77) + ((AN77 * 0.03)/AO77)))/AJ77)*100 -> #VALUE! | AU77: =(((AK77)-((AP77/AO77) + ((AN77 * 0.07)/AO77)))/AK77)*100 -> 1.6076538 | BB77: =(((AH77)-(((AP77/AO77) + ((AN77 * 0.03)/AO77))-AW77))/AH77)*100 -> -9.0755426 | BC77: =(((AI77)-(((AP77/AO77) + ((AN77 * 0.3)/AO77))-AX77))/AI77)*100 -> -23.165855 | BD77: =(((AJ77)-(((AP77/AO77) + ((AN77 * 0.03)/AO77))-AY77))/AJ77)*100 -> #VALUE! | BE77: =(((AK77)-(((AP77/AO77) + ((AN77 * 0.15)/AO77))-AZ77))/AK77)*100 -> -8.2349785 | BG77: 0005557742388 | BH77: 0055577923887 | BJ77: Gatorade Sport Beverage 6 x 591 mL or G2 PLUS DEPOSIT | BM77: GATORADE G2 GRP 591ML | BN77: 6 | BO77: EA | BP77: 221614 | BQ77: #N/A | BR77: #N/A | BS77: 30 | BT77: 9249.48 | BX77: 9.29 | BY77: 9.29 | BZ77: =BY77-BX77 -> 0 | CC77: =VLOOKUP(A77,'[1]RPT 1280 - Edmonton'!$1:$1048576,4,0) -> PC | CE77: DB | CF77: 30.13 | CG77: 6.03 | CH77: 0 | CI77: 0 | CJ77: =CF77-J77 -> 0 | CK77: =CG77-K77 -> 0 | CL77: =CH77-L77 -> 0 | CM77: =CI77-M77 -> 0 | CO77: 5.99 | CP77: 5.99 | CQ77: =CP77-CO77 -> 0
A78: 917153 | B78: GATORADE G2 BLUE 591ML 4 X 6 EA | C78: 010126020200 | D78: L M | E78: DNK-Direct | F78: B | G78: B | J78: =J77 -> 30.13 | K78: =K77 -> 6.03 | O78: =O77 -> 24.1 | P78: =P77 -> 6.025 | AH78: =IF(W78<>"",(RIGHT(W78,LEN(W78)-SEARCH("/",W78,1)))/U78,"") | AI78: =IF(X78<>"",X78,"") | AJ78: =IF(Y78<>"",Y78,"") | AK78: =IF(Z78<>"",Z78,"") | BG78: 0005727155544 | BH78: 0057271555456 | BM78: GATORADE G2 BLUE 591ML | BN78: 6 | BO78: EA | BQ78: #N/A | BR78: #N/A | BX78: 9.29 | BY78: 9.29 | BZ78: =BY78-BX78 -> 0 | CC78: =VLOOKUP(A78,'[1]RPT 1280 - Edmonton'!$1:$1048576,4,0) -> PC | CE78: DB | CF78: 30.13 | CG78: 6.03 | CH78: 0 | CI78: 0 | CJ78: =CF78-J78 -> 0 | CK78: =CG78-K78 -> 0 | CL78: =CH78-L78 -> 0 | CM78: =CI78-M78 -> 0
A79: 6208151 | B79: GATORADE ZERO ORNGE 6X591 4 X 6 EA | C79: 010126020200 | D79: L M | E79: DNK-Direct | F79: B | G79: B | J79: =J78 -> 30.13 | K79: =K78 -> 6.03 | O79: =O78 -> 24.1 | P79: =P78 -> 6.025 | AH79: =IF(W79<>"",(RIGHT(W79,LEN(W79)-SEARCH("/",W79,1)))/U79,"") | AI79: =IF(X79<>"",X79,"") | AJ79: =IF(Y79<>"",Y79,"") | AK79: =IF(Z79<>"",Z79,"") | BG79: 0005727116268 | BH79: 0005727116268 | BM79: GATORADE ZERO ORNGE 6X591 | BN79: 6 | BO79: EA | BP79: 6208151 | BQ79: #N/A | BR79: #N/A | BS79: 37 | BT79: 3954.67 | BX79: 9.29 | BY79: 9.29 | BZ79: =BY79-BX79 -> 0 | CC79: =VLOOKUP(A79,'[1]RPT 1280 - Edmonton'!$1:$1048576,4,0) -> PC | CE79: DB | CF79: 30.13 | CG79: 6.03 | CH79: 0 | CI79: 0 | CJ79: =CF79-J79 -> 0 | CK79: =CG79-K79 -> 0 | CL79: =CH79-L79 -> 0 | CM79: =CI79-M79 -> 0
A80: 6208144 | B80: GATORADE ZERO BERRY 6X591 4 X 6 EA | C80: 010126020200 | D80: L M | E80: DNK-Direct | F80: B | G80: B | J80: =J79 -> 30.13 | K80: =K79 -> 6.03 | O80: =O79 -> 24.1 | P80: =P79 -> 6.025 | AH80: =IF(W80<>"",(RIGHT(W80,LEN(W80)-SEARCH("/",W80,1)))/U80,"") | AI80: =IF(X80<>"",X80,"") | AJ80: =IF(Y80<>"",Y80,"") | AK80: =IF(Z80<>"",Z80,"") | BG80: 0005727116264 | BH80: 0005727116264 | BM80: GATORADE ZERO BERRY 6X591 | BN80: 6 | BO80: EA | BP80: 6208144 | BQ80: #N/A | BR80: #N/A | BS80: 21 | BT80: 14752.37 | BX80: 9.29 | BY80: 9.29 | BZ80: =BY80-BX80 -> 0 | CC80: =VLOOKUP(A80,'[1]RPT 1280 - Edmonton'!$1:$1048576,4,0) -> PC | CE80: DB | CF80: 30.13 | CG80: 6.03 | CH80: 0 | CI80: 0 | CJ80: =CF80-J80 -> 0 | CK80: =CG80-K80 -> 0 | CL80: =CH80-L80 -> 0 | CM80: =CI80-M80 -> 0
A81: 6256887 | B81: GATRDE ZERO GLACIER 6X591 4 X 6 EA | C81: 010126020200 | D81: L M | E81: DNK-Direct | F81: B | G81: B | J81: =J80 -> 30.13 | K81: =K80 -> 6.03 | O81: =O80 -> 24.1 | P81: =P80 -> 6.025 | AH81: =IF(W81<>"",(RIGHT(W81,LEN(W81)-SEARCH("/",W81,1)))/U81,"") | AI81: =IF(X81<>"",X81,"") | AJ81: =IF(Y81<>"",Y81,"") | AK81: =IF(Z81<>"",Z81,"") | BG81: 0005727116412 | BH81: 0005727116412 | BM81: GATRDE ZERO GLACIER 6X591 | BN81: 6 | BO81: EA | BP81: 6256887 | BQ81: #N/A | BR81: #N/A | BS81: 21 | BT81: 14983.88 | BX81: 9.29 | BY81: 9.29 | BZ81: =BY81-BX81 -> 0 | CC81: =VLOOKUP(A81,'[1]RPT 1280 - Edmonton'!$1:$1048576,4,0) -> PC | CE81: DB | CF81: 30.13 | CG81: 6.03 | CH81: 0 | CI81: 0 | CJ81: =CF81-J81 -> 0 | CK81: =CG81-K81 -> 0 | CL81: =CH81-L81 -> 0 | CM81: =CI81-M81 -> 0
A82: 6467500 | B82: GATRDE ZERO GLAC CHERRY 6X591 4 X 6 EA | C82: 010126020200 | D82: L M | E82: DNK-Direct | F82: B | G82: B | J82: =J81 -> 30.13 | K82: =K81 -> 6.03 | O82: =O81 -> 24.1 | P82: =P81 -> 6.025 | AH82: =IF(W82<>"",(RIGHT(W82,LEN(W82)-SEARCH("/",W82,1)))/U82,"") | AI82: =IF(X82<>"",X82,"") | AJ82: =IF(Y82<>"",Y82,"") | AK82: =IF(Z82<>"",Z82,"") | BG82: 0005727116467 | BH82: 0005727116467 | BM82: GATRDE ZERO GLAC CHERRY 6X591 | BN82: 6 | BO82: EA | BQ82: #N/A | BR82: #N/A | BS82: 51 | BT82: 101.64 | BX82: 9.29 | BY82: 9.29 | BZ82: =BY82-BX82 -> 0 | CC82: =VLOOKUP(A82,'[1]RPT 1280 - Edmonton'!$1:$1048576,4,0) -> PC | CE82: DB | CF82: 30.13 | CG82: 6.03 | CH82: 0 | CI82: 0 | CJ82: =CF82-J82 -> 0 | CK82: =CG82-K82 -> 0 | CL82: =CH82-L82 -> 0 | CM82: =CI82-M82 -> 0
A83: 204727 | B83: C.GOLD BLUBRY SUR -Z 12 X 600 GR | C83: 010561110120 | D83: L M | E83: A | F83: B | G83: B | I83: ALL | J83: 63.22 | O83: 63.22 | P83: 5.2683333 | Q83: 3.66 | T83: 1 / $5.49 | U83: 1 | V83: $5.49 | W83: 1 /5.49 | X83: 6.49 | Z83: 5.99 | AA83: 0.05025258 | AC83: 6.59 | AD83: 7.79 | AE83: 6.99 | AF83: 8.49 | AH83: =IF(W83<>"",(RIGHT(W83,LEN(W83)-SEARCH("/",W83,1)))/U83,"") -> 5.49 | AI83: =IF(X83<>"",X83,"") -> 6.49 | AJ83: =IF(Y83<>"",Y83,"") | AK83: =IF(Z83<>"",Z83,"") -> 5.99 | AM83: 64.86 | AN83: 16.69 | AO83: 12 | AP83: =(AM83 * 1.05) - L83 - Q83 - K83 -> 64.443 | AQ83: N | AR83: =(((AH83)-((AP83/AO83) + ((AN83 * 0.03)/AO83)))/AH83)*100 -> 1.4212204 | AS83: =(((AI83)-((AP83/AO83) + ((AN83 * 0.3)/AO83)))/AI83)*100 -> 10.824345 | AT83: =(((AJ83)-((AP83/AO83) + ((AN83 * 0.03)/AO83)))/AJ83)*100 -> #VALUE! | AU83: =(((AK83)-((AP83/AO83) + ((AN83 * 0.07)/AO83)))/AK83)*100 -> 8.7210629 | BB83: =(((AH83)-(((AP83/AO83) + ((AN83 * 0.03)/AO83))-AW83))/AH83)*100 -> 1.4212204 | BC83: =(((AI83)-(((AP83/AO83) + ((AN83 * 0.3)/AO83))-AX83))/AI83)*100 -> 10.824345 | BD83: =(((AJ83)-(((AP83/AO83) + ((AN83 * 0.03)/AO83))-AY83))/AJ83)*100 -> #VALUE! | BE83: =(((AK83)-(((AP83/AO83) + ((AN83 * 0.15)/AO83))-AZ83))/AK83)*100 -> 6.8635225 | BG83: 0005731602880 | BH83: 0057316028802 | BJ83: Co-op Gold Frozen Fruit 300 - 600 g Select Varieties | BM83: C.GOLD BLUBRY SUR -Z | BN83: 600 | BO83: GR | BQ83: #N/A | BR83: #N/A | BS83: 0 | BT83: 94851.08 | BX83: 7.49 | BY83: 7.49 | BZ83: =BY83-BX83 -> 0 | CC83: =VLOOKUP(A83,'[1]RPT 1280 - Edmonton'!$1:$1048576,4,0) -> #N/A | CE83: EA | CF83: 63.22 | CG83: 0 | CH83: 0 | CI83: 0 | CJ83: =CF83-J83 -> 0 | CK83: =CG83-K83 -> 0 | CL83: =CH83-L83 -> 0 | CM83: =CI83-M83 -> 0 | CO83: 5.49 | CP83: 5.49 | CQ83: =CP83-CO83 -> 0
A84: 980276 | B84: C.GOLD STN BERRIES-Z 12 X 300 GR | C84: 010561110130 | D84: L M | E84: A | F84: B | G84: B | I84: ALL | J84: 57.77 | O84: 57.77 | P84: 4.8141667 | Q84: 1.2 | T84: 1 / $5.49 | U84: 1 | V84: $5.49 | W84: 1 /5.49 | X84: 6.49 | Z84: 5.99 | AA84: 0.048887219 | AC84: 6.59 | AD84: 7.79 | AE84: 6.99 | AF84: 8.49 | AH84: =IF(W84<>"",(RIGHT(W84,LEN(W84)-SEARCH("/",W84,1)))/U84,"") -> 5.49 | AI84: =IF(X84<>"",X84,"") -> 6.49 | AJ84: =IF(Y84<>"",Y84,"") | AK84: =IF(Z84<>"",Z84,"") -> 5.99 | AM84: 59.27 | AN84: 9.44 | AO84: 12 | AP84: =(AM84 * 1.05) - L84 - Q84 - K84 -> 61.0335 | AQ84: N | AR84: =(((AH84)-((AP84/AO84) + ((AN84 * 0.03)/AO84)))/AH84)*100 -> 6.9266849 | AS84: =(((AI84)-((AP84/AO84) + ((AN84 * 0.3)/AO84)))/AI84)*100 -> 17.994992 | AT84: =(((AJ84)-((AP84/AO84) + ((AN84 * 0.03)/AO84)))/AJ84)*100 -> #VALUE! | AU84: =(((AK84)-((AP84/AO84) + ((AN84 * 0.07)/AO84)))/AK84)*100 -> 14.170423 | BB84: =(((AH84)-(((AP84/AO84) + ((AN84 * 0.03)/AO84))-AW84))/AH84)*100 -> 6.9266849 | BC84: =(((AI84)-(((AP84/AO84) + ((AN84 * 0.3)/AO84))-AX84))/AI84)*100 -> 17.994992 | BD84: =(((AJ84)-(((AP84/AO84) + ((AN84 * 0.03)/AO84))-AY84))/AJ84)*100 -> #VALUE! | BE84: =(((AK84)-(((AP84/AO84) + ((AN84 * 0.15)/AO84))-AZ84))/AK84)*100 -> 13.119783 | BG84: 0005731611865 | BH84: 0057316118650 | BJ84: Co-op Gold Frozen Fruit 300 - 600 g Select Varieties | BM84: C.GOLD STN BERRIES-Z | BN84: 300 | BO84: GR | BQ84: #N/A | BR84: #N/A | BS84: 28 | BT84: 9166.65 | BX84: 7.49 | BY84: 7.49 | BZ84: =BY84-BX84 -> 0 | CC84: =VLOOKUP(A84,'[1]RPT 1280 - Edmonton'!$1:$1048576,4,0) -> #N/A | CE84: EA | CF84: 57.77 | CG84: 0 | CH84: 0 | CI84: 0 | CJ84: =CF84-J84 -> 0 | CK84: =CG84-K84 -> 0 | CL84: =CH84-L84 -> 0 | CM84: =CI84-M84 -> 0 | CO84: 5.49 | CP84: 5.49 | CQ84: =CP84-CO84 -> 0
A85: 343673 | B85: C.GOLD BERRY BLEND SUR -Z 12 X 600 GR | C85: 010561110120 | D85: L M | E85: A | F85: B | G85: B | I85: ALL | J85: 65.02 | O85: 65.02 | P85: 5.4183333 | Q85: 6 | T85: 1 / $5.49 | U85: 1 | V85: $5.49 | W85: 1 /5.49 | X85: 6.49 | Z85: 5.99 | AA85: 0.05025258 | AC85: 6.59 | AD85: 7.79 | AE85: 6.99 | AF85: 8.49 | AH85: =IF(W85<>"",(RIGHT(W85,LEN(W85)-SEARCH("/",W85,1)))/U85,"") -> 5.49 | AI85: =IF(X85<>"",X85,"") -> 6.49 | AJ85: =IF(Y85<>"",Y85,"") | AK85: =IF(Z85<>"",Z85,"") -> 5.99 | AM85: 66.71 | AN85: 16.69 | AO85: 12 | AP85: =(AM85 * 1.05) - L85 - Q85 - K85 -> 64.0455 | AQ85: N | AR85: =(((AH85)-((AP85/AO85) + ((AN85 * 0.03)/AO85)))/AH85)*100 -> 2.0245902 | AS85: =(((AI85)-((AP85/AO85) + ((AN85 * 0.3)/AO85)))/AI85)*100 -> 11.334746 | AT85: =(((AJ85)-((AP85/AO85) + ((AN85 * 0.03)/AO85)))/AJ85)*100 -> #VALUE! | AU85: =(((AK85)-((AP85/AO85) + ((AN85 * 0.07)/AO85)))/AK85)*100 -> 9.2740679 | BB85: =(((AH85)-(((AP85/AO85) + ((AN85 * 0.03)/AO85))-AW85))/AH85)*100 -> 2.0245902 | BC85: =(((AI85)-(((AP85/AO85) + ((AN85 * 0.3)/AO85))-AX85))/AI85)*100 -> 11.334746 | BD85: =(((AJ85)-(((AP85/AO85) + ((AN85 * 0.03)/AO85))-AY85))/AJ85)*100 -> #VALUE! | BE85: =(((AK85)-(((AP85/AO85) + ((AN85 * 0.15)/AO85))-AZ85))/AK85)*100 -> 7.4165275 | BG85: 0005731612164 | BH85: 0057316121643 | BJ85: Co-op Gold Frozen Fruit 300 - 600 g Select Varieties | BM85: C.GOLD BERRY BLEND SUR -Z | BN85: 600 | BO85: GR | BQ85: #N/A | BR85: #N/A | BS85: 8 | BT85: 74167.69 | BX85: 7.49 | BY85: 7.49 | BZ85: =BY85-BX85 -> 0 | CC85: =VLOOKUP(A85,'[1]RPT 1280 - Edmonton'!$1:$1048576,4,0) -> #N/A | CE85: EA | CF85: 65.02 | CG85: 0 | CH85: 0 | CI85: 0 | CJ85: =CF85-J85 -> 0 | CK85: =CG85-K85 -> 0 | CL85: =CH85-L85 -> 0 | CM85: =CI85-M85 -> 0 | CO85: 5.49 | CP85: 5.49 | CQ85: =CP85-CO85 -> 0
A86: 151597 | B86: C.GOLD WHL STRWBRY SUR -Z 12 X 600 GR | C86: 010561110120 | D86: L M | E86: A | F86: B | G86: B | I86: ALL | J86: 58.58 | O86: 58.58 | P86: 4.8816667 | Q86: 1.2 | T86: 1 / $5.49 | U86: 1 | V86: $5.49 | W86: 1 /5.49 | X86: 6.49 | Z86: 5.99 | AA86: 0.05091014 | AC86: 6.59 | AD86: 7.79 | AE86: 6.99 | AF86: 8.49 | AH86: =IF(W86<>"",(RIGHT(W86,LEN(W86)-SEARCH("/",W86,1)))/U86,"") -> 5.49 | AI86: =IF(X86<>"",X86,"") -> 6.49 | AJ86: =IF(Y86<>"",Y86,"") | AK86: =IF(Z86<>"",Z86,"") -> 5.99 | AM86: 60.1 | AN86: 16.69 | AO86: 12 | AP86: =(AM86 * 1.05) - L86 - Q86 - K86 -> 61.905 | AQ86: N | AR86: =(((AH86)-((AP86/AO86) + ((AN86 * 0.03)/AO86)))/AH86)*100 -> 5.2736794 | AS86: =(((AI86)-((AP86/AO86) + ((AN86 * 0.3)/AO86)))/AI86)*100 -> 14.083205 | AT86: =(((AJ86)-((AP86/AO86) + ((AN86 * 0.03)/AO86)))/AJ86)*100 -> #VALUE! | AU86: =(((AK86)-((AP86/AO86) + ((AN86 * 0.07)/AO86)))/AK86)*100 -> 12.251948 | BB86: =(((AH86)-(((AP86/AO86) + ((AN86 * 0.03)/AO86))-AW86))/AH86)*100 -> 5.2736794 | BC86: =(((AI86)-(((AP86/AO86) + ((AN86 * 0.3)/AO86))-AX86))/AI86)*100 -> 14.083205 | BD86: =(((AJ86)-(((AP86/AO86) + ((AN86 * 0.03)/AO86))-AY86))/AJ86)*100 -> #VALUE! | BE86: =(((AK86)-(((AP86/AO86) + ((AN86 * 0.15)/AO86))-AZ86))/AK86)*100 -> 10.394407 | BG86: 0005731613312 | BH86: 0057316133124 | BJ86: Co-op Gold Frozen Fruit 300 - 600 g Select Varieties | BM86: C.GOLD WHL STRWBRY SUR -Z | BN86: 600 | BO86: GR | BQ86: #N/A | BR86: #N/A | BS86: 0 | BT86: 68205.5 | BX86: 7.49 | BY86: 7.49 | BZ86: =BY86-BX86 -> 0 | CC86: =VLOOKUP(A86,'[1]RPT 1280 - Edmonton'!$1:$1048576,4,0) -> #N/A | CE86: EA | CF86: 58.58 | CG86: 0 | CH86: 0 | CI86: 0 | CJ86: =CF86-J86 -> 0 | CK86: =CG86-K86 -> 0 | CL86: =CH86-L86 -> 0 | CM86: =CI86-M86 -> 0 | CO86: 5.49 | CP86: 5.49 | CQ86: =CP86-CO86 -> 0
A87: 811463 | B87: C.GOLD FRT MEDLEY SUR -Z 12 X 600 GR | C87: 010561110120 | D87: L M | E87: A | F87: B | G87: B | I87: ALL | J87: 59.24 | O87: 59.24 | P87: 4.9366667 | Q87: 1.2 | T87: 1 / $5.49 | U87: 1 | V87: $5.49 | W87: 1 /5.49 | X87: 6.49 | Z87: 5.99 | AA87: 0.051567699 | AC87: 6.59 | AD87: 7.79 | AE87: 6.99 | AF87: 8.49 | AH87: =IF(W87<>"",(RIGHT(W87,LEN(W87)-SEARCH("/",W87,1)))/U87,"") -> 5.49 | AI87: =IF(X87<>"",X87,"") -> 6.49 | AJ87: =IF(Y87<>"",Y87,"") | AK87: =IF(Z87<>"",Z87,"") -> 5.99 | AM87: 60.78 | AN87: 16.69 | AO87: 12 | AP87: =(AM87 * 1.05) - L87 - Q87 - K87 -> 62.619 | AQ87: N | AR87: =(((AH87)-((AP87/AO87) + ((AN87 * 0.03)/AO87)))/AH87)*100 -> 4.1898907 | AS87: =(((AI87)-((AP87/AO87) + ((AN87 * 0.3)/AO87)))/AI87)*100 -> 13.16641 | AT87: =(((AJ87)-((AP87/AO87) + ((AN87 * 0.03)/AO87)))/AJ87)*100 -> #VALUE! | AU87: =(((AK87)-((AP87/AO87) + ((AN87 * 0.07)/AO87)))/AK87)*100 -> 11.258625 | BB87: =(((AH87)-(((AP87/AO87) + ((AN87 * 0.03)/AO87))-AW87))/AH87)*100 -> 4.1898907 | BC87: =(((AI87)-(((AP87/AO87) + ((AN87 * 0.3)/AO87))-AX87))/AI87)*100 -> 13.16641 | BD87: =(((AJ87)-(((AP87/AO87) + ((AN87 * 0.03)/AO87))-AY87))/AJ87)*100 -> #VALUE! | BE87: =(((AK87)-(((AP87/AO87) + ((AN87 * 0.15)/AO87))-AZ87))/AK87)*100 -> 9.4010851 | BG87: 0005731613313 | BH87: 0057316133134 | BJ87: Co-op Gold Frozen Fruit 300 - 600 g Select Varieties | BM87: C.GOLD FRT MEDLEY SUR -Z | BN87: 600 | BO87: GR | BQ87: #N/A | BR87: #N/A | BS87: 8 | BT87: 33319.33 | BX87: 7.49 | BY87: 7.49 | BZ87: =BY87-BX87 -> 0 | CC87: =VLOOKUP(A87,'[1]RPT 1280 - Edmonton'!$1:$1048576,4,0) -> #N/A | CE87: EA | CF87: 59.24 | CG87: 0 | CH87: 0 | CI87: 0 | CJ87: =CF87-J87 -> 0 | CK87: =CG87-K87 -> 0 | CL87: =CH87-L87 -> 0 | CM87: =CI87-M87 -> 0 | CO87: 5.49 | CP87: 5.49 | CQ87: =CP87-CO87 -> 0
A88: 667279 | B88: C.GOLD MANGO CHUNKS -Z 12 X 600 GR | C88: 010561110120 | D88: L M | E88: A | F88: B | G88: B | I88: ALL | J88: 56.47 | O88: 56.47 | P88: 4.7058333 | Q88: 1.2 | T88: 1 / $5.49 | U88: 1 | V88: $5.49 | W88: 1 /5.49 | X88: 6.49 | Z88: 5.99 | AA88: 0.069281876 | AC88: 6.59 | AD88: 7.79 | AE88: 6.99 | AF88: 8.49 | AH88: =IF(W88<>"",(RIGHT(W88,LEN(W88)-SEARCH("/",W88,1)))/U88,"") -> 5.49 | AI88: =IF(X88<>"",X88,"") -> 6.49 | AJ88: =IF(Y88<>"",Y88,"") | AK88: =IF(Z88<>"",Z88,"") -> 5.99 | AM88: 57.94 | AN88: 16.69 | AO88: 12 | AP88: =(AM88 * 1.05) - L88 - Q88 - K88 -> 59.637 | AQ88: N | AR88: =(((AH88)-((AP88/AO88) + ((AN88 * 0.03)/AO88)))/AH88)*100 -> 8.7163024 | AS88: =(((AI88)-((AP88/AO88) + ((AN88 * 0.3)/AO88)))/AI88)*100 -> 16.995378 | AT88: =(((AJ88)-((AP88/AO88) + ((AN88 * 0.03)/AO88)))/AJ88)*100 -> #VALUE! | AU88: =(((AK88)-((AP88/AO88) + ((AN88 * 0.07)/AO88)))/AK88)*100 -> 15.407206 | BB88: =(((AH88)-(((AP88/AO88) + ((AN88 * 0.03)/AO88))-AW88))/AH88)*100 -> 8.7163024 | BC88: =(((AI88)-(((AP88/AO88) + ((AN88 * 0.3)/AO88))-AX88))/AI88)*100 -> 16.995378 | BD88: =(((AJ88)-(((AP88/AO88) + ((AN88 * 0.03)/AO88))-AY88))/AJ88)*100 -> #VALUE! | BE88: =(((AK88)-(((AP88/AO88) + ((AN88 * 0.15)/AO88))-AZ88))/AK88)*100 -> 13.549666 | BG88: 0005731615080 | BH88: 0057316150803 | BJ88: Co-op Gold Frozen Fruit 300 - 600 g Select Varieties | BM88: C.GOLD MANGO CHUNKS -Z | BN88: 600 | BO88: GR | BQ88: #N/A | BR88: #N/A | BS88: 11 | BT88: 47873.88 | BX88: 7.49 | BY88: 7.49 | BZ88: =BY88-BX88 -> 0 | CC88: =VLOOKUP(A88,'[1]RPT 1280 - Edmonton'!$1:$1048576,4,0) -> #N/A | CE88: EA | CF88: 56.47 | CG88: 0 | CH88: 0 | CI88: 0 | CJ88: =CF88-J88 -> 0 | CK88: =CG88-K88 -> 0 | CL88: =CH88-L88 -> 0 | CM88: =CI88-M88 -> 0 | CO88: 5.49 | CP88: 5.49 | CQ88: =CP88-CO88 -> 0
A89: 6237499 | B89: C.GOLD EXOTIC DRAGONFRUIT BLND-Z 12 X 600 GR | C89: 010561110120 | D89: L M | E89: A | F89: B | G89: B | J89: =J88 -> 56.47 | O89: =O88 -> 56.47 | P89: =P88 -> 4.7058333 | Q89: 1.2 | W89: 1 /5.49 | X89: 6.49 | Z89: 5.99 | AH89: =IF(W89<>"",(RIGHT(W89,LEN(W89)-SEARCH("/",W89,1)))/U89,"") -> #VALUE! | AI89: =IF(X89<>"",X89,"") -> 6.49 | AJ89: =IF(Y89<>"",Y89,"") | AK89: =IF(Z89<>"",Z89,"") -> 5.99 | BG89: 0005731618898 | BH89: 0057316188981 | BJ89: Co-op Gold Frozen Fruit 300 - 600 g Select Varieties | BM89: C.GOLD EXOTIC DRAGONFRUIT BLND-Z | BN89: 600 | BO89: GR | BQ89: #N/A | BR89: #N/A | BS89: 29 | BT89: 9452.24 | BX89: 7.49 | BY89: 7.49 | BZ89: =BY89-BX89 -> 0 | CC89: =VLOOKUP(A89,'[1]RPT 1280 - Edmonton'!$1:$1048576,4,0) -> #N/A | CE89: EA | CF89: 56.47 | CG89: 0 | CH89: 0 | CI89: 0 | CJ89: =CF89-J89 -> 0 | CK89: =CG89-K89 -> 0 | CL89: =CH89-L89 -> 0 | CM89: =CI89-M89 -> 0
A90: 6327241 | B90: C.GOLD BITE SIZED BLEND-Z 12 X 500 GR | C90: 010561110120 | D90: L M | E90: A | F90: B | G90: B | J90: =J89 -> 56.47 | O90: =O89 -> 56.47 | P90: =P89 -> 4.7058333 | Q90: 1.2 | W90: 1 /5.49 | X90: 6.49 | Z90: 5.99 | AH90: =IF(W90<>"",(RIGHT(W90,LEN(W90)-SEARCH("/",W90,1)))/U90,"") -> #VALUE! | AI90: =IF(X90<>"",X90,"") -> 6.49 | AJ90: =IF(Y90<>"",Y90,"") | AK90: =IF(Z90<>"",Z90,"") -> 5.99 | BG90: 0005731620276 | BH90: 0057316202762 | BJ90: Co-op Gold Frozen Fruit 300 - 600 g Select Varieties | BM90: C.GOLD BITE SIZED BLEND-Z | BN90: 500 | BO90: GR | BQ90: #N/A | BR90: #N/A | BS90: 42 | BT90: 8486.83 | BX90: 7.49 | BY90: 7.49 | BZ90: =BY90-BX90 -> 0 | CC90: =VLOOKUP(A90,'[1]RPT 1280 - Edmonton'!$1:$1048576,4,0) -> #N/A | CE90: EA | CF90: 56.47 | CG90: 0 | CH90: 0 | CI90: 0 | CJ90: =CF90-J90 -> 0 | CK90: =CG90-K90 -> 0 | CL90: =CH90-L90 -> 0 | CM90: =CI90-M90 -> 0
A91: 6464606 | B91: CG BERRY BANANA SPINACH BLEND-Z 12 X 600 GR | C91: 010561110120 | D91: L M | E91: A | F91: B | G91: B | J91: =J90 -> 56.47 | O91: =O90 -> 56.47 | P91: =P90 -> 4.7058333 | Q91: 1.2 | W91: 1 /5.49 | X91: 6.49 | Z91: 5.99 | AH91: =IF(W91<>"",(RIGHT(W91,LEN(W91)-SEARCH("/",W91,1)))/U91,"") -> #VALUE! | AI91: =IF(X91<>"",X91,"") -> 6.49 | AJ91: =IF(Y91<>"",Y91,"") | AK91: =IF(Z91<>"",Z91,"") -> 5.99 | BG91: 0005731621429 | BH91: 0057316214291 | BJ91: Co-op Gold Frozen Fruit 300 - 600 g Select Varieties | BM91: CG BERRY BANANA SPINACH BLEND-Z | BN91: 600 | BO91: GR | BQ91: #N/A | BR91: #N/A | BS91: 32 | BT91: 12847.69 | BX91: 7.49 | BY91: 7.49 | BZ91: =BY91-BX91 -> 0 | CC91: =VLOOKUP(A91,'[1]RPT 1280 - Edmonton'!$1:$1048576,4,0) -> #N/A | CE91: EA | CF91: 56.47 | CG91: 0 | CH91: 0 | CI91: 0 | CJ91: =CF91-J91 -> 0 | CK91: =CG91-K91 -> 0 | CL91: =CH91-L91 -> 0 | CM91: =CI91-M91 -> 0
A92: 6464614 | B92: CG TROPICAL KALE BLEND -Z 12 X 600 GR | C92: 010561110120 | D92: L M | E92: A | F92: B | G92: B | J92: =J91 -> 56.47 | O92: =O91 -> 56.47 | P92: =P91 -> 4.7058333 | Q92: 1.2 | W92: 1 /5.49 | X92: 6.49 | Z92: 5.99 | AH92: =IF(W92<>"",(RIGHT(W92,LEN(W92)-SEARCH("/",W92,1)))/U92,"") -> #VALUE! | AI92: =IF(X92<>"",X92,"") -> 6.49 | AJ92: =IF(Y92<>"",Y92,"") | AK92: =IF(Z92<>"",Z92,"") -> 5.99 | BG92: 0005731621430 | BH92: 0057316214307 | BJ92: Co-op Gold Frozen Fruit 300 - 600 g Select Varieties | BM92: CG TROPICAL KALE BLEND -Z | BN92: 600 | BO92: GR | BQ92: #N/A | BR92: #N/A | BS92: 43 | BT92: 4601.22 | BX92: 7.49 | BY92: 7.49 | BZ92: =BY92-BX92 -> 0 | CC92: =VLOOKUP(A92,'[1]RPT 1280 - Edmonton'!$1:$1048576,4,0) -> #N/A | CE92: EA | CF92: 56.47 | CG92: 0 | CH92: 0 | CI92: 0 | CJ92: =CF92-J92 -> 0 | CK92: =CG92-K92 -> 0 | CL92: =CH92-L92 -> 0 | CM92: =CI92-M92 -> 0
A93: 667329 | B93: C.GOLD TROPICAL BLEND -Z 12 X 600 GR | C93: 010561110120 | D93: L M | E93: A | F93: B | G93: B | I93: ALL | J93: 58.9 | O93: 58.9 | P93: 4.9083333 | Q93: 1.2 | T93: 1 / $5.49 | U93: 1 | V93: $5.49 | W93: 1 /5.49 | X93: 6.49 | Z93: 5.99 | AA93: 0.05058136 | AC93: 6.59 | AD93: 7.79 | AE93: 6.99 | AF93: 8.49 | AH93: =IF(W93<>"",(RIGHT(W93,LEN(W93)-SEARCH("/",W93,1)))/U93,"") -> 5.49 | AI93: =IF(X93<>"",X93,"") -> 6.49 | AJ93: =IF(Y93<>"",Y93,"") | AK93: =IF(Z93<>"",Z93,"") -> 5.99 | AM93: 60.43 | AN93: 16.69 | AO93: 12 | AP93: =(AM93 * 1.05) - L93 - Q93 - K93 -> 62.2515 | AQ93: N | AR93: =(((AH93)-((AP93/AO93) + ((AN93 * 0.03)/AO93)))/AH93)*100 -> 4.7477231 | AS93: =(((AI93)-((AP93/AO93) + ((AN93 * 0.3)/AO93)))/AI93)*100 -> 13.63829 | AT93: =(((AJ93)-((AP93/AO93) + ((AN93 * 0.03)/AO93)))/AJ93)*100 -> #VALUE! | AU93: =(((AK93)-((AP93/AO93) + ((AN93 * 0.07)/AO93)))/AK93)*100 -> 11.769894 | BB93: =(((AH93)-(((AP93/AO93) + ((AN93 * 0.03)/AO93))-AW93))/AH93)*100 -> 4.7477231 | BC93: =(((AI93)-(((AP93/AO93) + ((AN93 * 0.3)/AO93))-AX93))/AI93)*100 -> 13.63829 | BD93: =(((AJ93)-(((AP93/AO93) + ((AN93 * 0.03)/AO93))-AY93))/AJ93)*100 -> #VALUE! | BE93: =(((AK93)-(((AP93/AO93) + ((AN93 * 0.15)/AO93))-AZ93))/AK93)*100 -> 9.9123539 | BG93: 0005731615471 | BH93: 0057316154719 | BJ93: Co-op Gold Frozen Fruit 300 - 600 g Select Varieties | BM93: C.GOLD TROPICAL BLEND -Z | BN93: 600 | BO93: GR | BQ93: #N/A | BR93: #N/A | BS93: 9 | BT93: 33025.93 | BX93: 7.49 | BY93: 7.49 | BZ93: =BY93-BX93 -> 0 | CC93: =VLOOKUP(A93,'[1]RPT 1280 - Edmonton'!$1:$1048576,4,0) -> #N/A | CE93: EA | CF93: 58.9 | CG93: 0 | CH93: 0 | CI93: 0 | CJ93: =CF93-J93 -> 0 | CK93: =CG93-K93 -> 0 | CL93: =CH93-L93 -> 0 | CM93: =CI93-M93 -> 0 | CO93: 5.49 | CP93: 5.49 | CQ93: =CP93-CO93 -> 0
A94: 381442 | B94: C.GOLD CHERRY BRY BLND-Z 12 X 600 GR | C94: 010561110120 | D94: L M | E94: A | F94: B | G94: B | I94: ALL | J94: 62.67 | O94: 62.67 | P94: 5.2225 | Q94: 3.6 | T94: 1 / $5.49 | U94: 1 | V94: $5.49 | W94: 1 /5.49 | X94: 6.49 | Z94: 5.99 | AA94: 0.051074529 | AC94: 6.59 | AD94: 7.79 | AE94: 6.99 | AF94: 8.49 | AH94: =IF(W94<>"",(RIGHT(W94,LEN(W94)-SEARCH("/",W94,1)))/U94,"") -> 5.49 | AI94: =IF(X94<>"",X94,"") -> 6.49 | AJ94: =IF(Y94<>"",Y94,"") | AK94: =IF(Z94<>"",Z94,"") -> 5.99 | AM94: 64.3 | AN94: 16.69 | AO94: 12 | AP94: =(AM94 * 1.05) - L94 - Q94 - K94 -> 63.915 | AQ94: N | AR94: =(((AH94)-((AP94/AO94) + ((AN94 * 0.03)/AO94)))/AH94)*100 -> 2.2226776 | AS94: =(((AI94)-((AP94/AO94) + ((AN94 * 0.3)/AO94)))/AI94)*100 -> 11.502311 | AT94: =(((AJ94)-((AP94/AO94) + ((AN94 * 0.03)/AO94)))/AJ94)*100 -> #VALUE! | AU94: =(((AK94)-((AP94/AO94) + ((AN94 * 0.07)/AO94)))/AK94)*100 -> 9.4556205 | BB94: =(((AH94)-(((AP94/AO94) + ((AN94 * 0.03)/AO94))-AW94))/AH94)*100 -> 2.2226776 | BC94: =(((AI94)-(((AP94/AO94) + ((AN94 * 0.3)/AO94))-AX94))/AI94)*100 -> 11.502311 | BD94: =(((AJ94)-(((AP94/AO94) + ((AN94 * 0.03)/AO94))-AY94))/AJ94)*100 -> #VALUE! | BE94: =(((AK94)-(((AP94/AO94) + ((AN94 * 0.15)/AO94))-AZ94))/AK94)*100 -> 7.5980801 | BG94: 0005731617154 | BH94: 0057316171549 | BJ94: Co-op Gold Frozen Fruit 300 - 600 g Select Varieties | BM94: C.GOLD CHERRY BRY BLND-Z | BN94: 600 | BO94: GR | BQ94: #N/A | BR94: #N/A | BS94: 25 | BT94: 25961.87 | BX94: 7.49 | BY94: 7.49 | BZ94: =BY94-BX94 -> 0 | CC94: =VLOOKUP(A94,'[1]RPT 1280 - Edmonton'!$1:$1048576,4,0) -> #N/A | CE94: EA | CF94: 62.67 | CG94: 0 | CH94: 0 | CI94: 0 | CJ94: =CF94-J94 -> 0 | CK94: =CG94-K94 -> 0 | CL94: =CH94-L94 -> 0 | CM94: =CI94-M94 -> 0 | CO94: 5.49 | CP94: 5.49 | CQ94: =CP94-CO94 -> 0
A95: 382887 | B95: C.GOLD DARK SWT CHERRY-Z 12 X 400 GR | C95: 010561110130 | D95: L M | E95: A | F95: B | G95: B | I95: ALL | J95: 54.5 | O95: 54.5 | P95: 4.5416667 | Q95: 1.2 | T95: 1 / $5.49 | U95: 1 | V95: $5.49 | W95: 1 /5.49 | X95: 6.49 | Z95: 5.99 | AA95: 0.10236491 | AC95: 6.59 | AD95: 7.79 | AE95: 6.99 | AF95: 8.49 | AH95: =IF(W95<>"",(RIGHT(W95,LEN(W95)-SEARCH("/",W95,1)))/U95,"") -> 5.49 | AI95: =IF(X95<>"",X95,"") -> 6.49 | AJ95: =IF(Y95<>"",Y95,"") | AK95: =IF(Z95<>"",Z95,"") -> 5.99 | AM95: 55.92 | AN95: 11.27 | AO95: 12 | AP95: =(AM95 * 1.05) - L95 - Q95 - K95 -> 57.516 | AQ95: N | AR95: =(((AH95)-((AP95/AO95) + ((AN95 * 0.03)/AO95)))/AH95)*100 -> 12.182605 | AS95: =(((AI95)-((AP95/AO95) + ((AN95 * 0.3)/AO95)))/AI95)*100 -> 21.806626 | AT95: =(((AJ95)-((AP95/AO95) + ((AN95 * 0.03)/AO95)))/AJ95)*100 -> #VALUE! | AU95: =(((AK95)-((AP95/AO95) + ((AN95 * 0.07)/AO95)))/AK95)*100 -> 18.885782 | BB95: =(((AH95)-(((AP95/AO95) + ((AN95 * 0.03)/AO95))-AW95))/AH95)*100 -> 12.182605 | BC95: =(((AI95)-(((AP95/AO95) + ((AN95 * 0.3)/AO95))-AX95))/AI95)*100 -> 21.806626 | BD95: =(((AJ95)-(((AP95/AO95) + ((AN95 * 0.03)/AO95))-AY95))/AJ95)*100 -> #VALUE! | BE95: =(((AK95)-(((AP95/AO95) + ((AN95 * 0.15)/AO95))-AZ95))/AK95)*100 -> 17.631469 | BG95: 0005731617392 | BH95: 0057316173925 | BJ95: Co-op Gold Frozen Fruit 400 - 600 g Select Varieties | BM95: C.GOLD DARK SWT CHERRY-Z | BN95: 400 | BO95: GR | BQ95: #N/A | BR95: #N/A | BS95: 31 | BT95: 9417.58 | BX95: 7.49 | BY95: 7.49 | BZ95: =BY95-BX95 -> 0 | CC95: =VLOOKUP(A95,'[1]RPT 1280 - Edmonton'!$1:$1048576,4,0) -> #N/A | CE95: EA | CF95: 54.5 | CG95: 0 | CH95: 0 | CI95: 0 | CJ95: =CF95-J95 -> 0 | CK95: =CG95-K95 -> 0 | CL95: =CH95-L95 -> 0 | CM95: =CI95-M95 -> 0 | CO95: 5.49 | CP95: 5.49 | CQ95: =CP95-CO95 -> 0
A96: 380923 | B96: C.GLD PINEAPPLE CHUNKS-Z 12 X 600 GR | C96: 010561110120 | D96: L M | E96: A | F96: B | G96: B | I96: ALL | J96: 60.46 | O96: 60.46 | P96: 5.0383333 | Q96: 1.2 | T96: 1 / $5.49 | U96: 1 | V96: $5.49 | W96: 1 /5.49 | X96: 6.49 | Z96: 5.99 | AA96: 0.051238919 | AC96: 6.59 | AD96: 7.79 | AE96: 6.99 | AF96: 8.49 | AH96: =IF(W96<>"",(RIGHT(W96,LEN(W96)-SEARCH("/",W96,1)))/U96,"") -> 5.49 | AI96: =IF(X96<>"",X96,"") -> 6.49 | AJ96: =IF(Y96<>"",Y96,"") | AK96: =IF(Z96<>"",Z96,"") -> 5.99 | AM96: 62.03 | AN96: 16.69 | AO96: 12 | AP96: =(AM96 * 1.05) - L96 - Q96 - K96 -> 63.9315 | AQ96: N | AR96: =(((AH96)-((AP96/AO96) + ((AN96 * 0.03)/AO96)))/AH96)*100 -> 2.1976321 | AS96: =(((AI96)-((AP96/AO96) + ((AN96 * 0.3)/AO96)))/AI96)*100 -> 11.481125 | AT96: =(((AJ96)-((AP96/AO96) + ((AN96 * 0.03)/AO96)))/AJ96)*100 -> #VALUE! | AU96: =(((AK96)-((AP96/AO96) + ((AN96 * 0.07)/AO96)))/AK96)*100 -> 9.4326656 | BB96: =(((AH96)-(((AP96/AO96) + ((AN96 * 0.03)/AO96))-AW96))/AH96)*100 -> 2.1976321 | BC96: =(((AI96)-(((AP96/AO96) + ((AN96 * 0.3)/AO96))-AX96))/AI96)*100 -> 11.481125 | BD96: =(((AJ96)-(((AP96/AO96) + ((AN96 * 0.03)/AO96))-AY96))/AJ96)*100 -> #VALUE! | BE96: =(((AK96)-(((AP96/AO96) + ((AN96 * 0.15)/AO96))-AZ96))/AK96)*100 -> 7.5751252 | BG96: 0005731617152 | BH96: 0057316171525 | BJ96: Co-op Gold Frozen Fruit 300 - 600 g Select Varieties | BM96: C.GLD PINEAPPLE CHUNKS-Z | BN96: 600 | BO96: GR | BQ96: #N/A | BR96: #N/A | BS96: 20 | BT96: 18813.52 | BX96: 7.49 | BY96: 7.49 | BZ96: =BY96-BX96 -> 0 | CC96: =VLOOKUP(A96,'[1]RPT 1280 - Edmonton'!$1:$1048576,4,0) -> #N/A | CE96: EA | CF96: 60.46 | CG96: 0 | CH96: 0 | CI96: 0 | CJ96: =CF96-J96 -> 0 | CK96: =CG96-K96 -> 0 | CL96: =CH96-L96 -> 0 | CM96: =CI96-M96 -> 0 | CO96: 5.49 | CP96: 5.49 | CQ96: =CP96-CO96 -> 0
A97: 472696 | B97: C.GOLD WHOLE RASPBRY-Z 12 X 400 GR | C97: 010561110131 | D97: L M | E97: A | F97: B | G97: B | I97: ALL | J97: 65.14 | O97: 65.14 | P97: 5.4283333 | Q97: 6 | T97: 1 / $5.49 | U97: 1 | V97: $5.49 | W97: 1 /5.49 | X97: 6.49 | Z97: 5.99 | AA97: 0.050746509 | AC97: 6.59 | AD97: 7.79 | AE97: 6.99 | AF97: 8.49 | AH97: =IF(W97<>"",(RIGHT(W97,LEN(W97)-SEARCH("/",W97,1)))/U97,"") -> 5.49 | AI97: =IF(X97<>"",X97,"") -> 6.49 | AJ97: =IF(Y97<>"",Y97,"") | AK97: =IF(Z97<>"",Z97,"") -> 5.99 | AM97: 66.83 | AN97: 11.27 | AO97: 12 | AP97: =(AM97 * 1.05) - L97 - Q97 - K97 -> 64.1715 | AQ97: N | AR97: =(((AH97)-((AP97/AO97) + ((AN97 * 0.03)/AO97)))/AH97)*100 -> 2.0801457 | AS97: =(((AI97)-((AP97/AO97) + ((AN97 * 0.3)/AO97)))/AI97)*100 -> 13.260786 | AT97: =(((AJ97)-((AP97/AO97) + ((AN97 * 0.03)/AO97)))/AJ97)*100 -> #VALUE! | AU97: =(((AK97)-((AP97/AO97) + ((AN97 * 0.07)/AO97)))/AK97)*100 -> 9.6265999 | BB97: =(((AH97)-(((AP97/AO97) + ((AN97 * 0.03)/AO97))-AW97))/AH97)*100 -> 2.0801457 | BC97: =(((AI97)-(((AP97/AO97) + ((AN97 * 0.3)/AO97))-AX97))/AI97)*100 -> 13.260786 | BD97: =(((AJ97)-(((AP97/AO97) + ((AN97 * 0.03)/AO97))-AY97))/AJ97)*100 -> #VALUE! | BE97: =(((AK97)-(((AP97/AO97) + ((AN97 * 0.15)/AO97))-AZ97))/AK97)*100 -> 8.3722871 | BG97: 0005731617146 | BH97: 0057316133127 | BJ97: Co-op Gold Frozen Fruit 300 - 600 g Select Varieties | BM97: C.GOLD WHOLE RASPBRY-Z | BN97: 400 | BO97: GR | BQ97: #N/A | BR97: #N/A | BS97: 15 | BT97: 48280.62 | BX97: 7.29 | BY97: 7.29 | BZ97: =BY97-BX97 -> 0 | CC97: =VLOOKUP(A97,'[1]RPT 1280 - Edmonton'!$1:$1048576,4,0) -> #N/A | CE97: EA | CF97: 65.14 | CG97: 0 | CH97: 0 | CI97: 0 | CJ97: =CF97-J97 -> 0 | CK97: =CG97-K97 -> 0 | CL97: =CH97-L97 -> 0 | CM97: =CI97-M97 -> 0 | CO97: 5.49 | CP97: 5.49 | CQ97: =CP97-CO97 -> 0
A98: 6236699 | B98: C.GOLD WATERMELON BLEND-Z 12 X 600 GR | C98: 010561110120 | D98: L M | E98: A | F98: B | G98: B | I98: ALL | J98: 53.61 | O98: 53.61 | P98: 4.4675 | Q98: 1.2 | T98: 1 / $5.49 | U98: 1 | V98: $5.49 | W98: 1 /5.49 | X98: 6.49 | Z98: 5.99 | AA98: 0.11617289 | AC98: 6.59 | AD98: 7.79 | AE98: 6.99 | AF98: 8.49 | AH98: =IF(W98<>"",(RIGHT(W98,LEN(W98)-SEARCH("/",W98,1)))/U98,"") -> 5.49 | AI98: =IF(X98<>"",X98,"") -> 6.49 | AJ98: =IF(Y98<>"",Y98,"") | AK98: =IF(Z98<>"",Z98,"") -> 5.99 | AM98: 55 | AN98: 16.69 | AO98: 12 | AP98: =(AM98 * 1.05) - L98 - Q98 - K98 -> 56.55 | AQ98: N | AR98: =(((AH98)-((AP98/AO98) + ((AN98 * 0.03)/AO98)))/AH98)*100 -> 13.402095 | AS98: =(((AI98)-((AP98/AO98) + ((AN98 * 0.3)/AO98)))/AI98)*100 -> 20.959168 | AT98: =(((AJ98)-((AP98/AO98) + ((AN98 * 0.03)/AO98)))/AJ98)*100 -> #VALUE! | AU98: =(((AK98)-((AP98/AO98) + ((AN98 * 0.07)/AO98)))/AK98)*100 -> 19.701864 | BB98: =(((AH98)-(((AP98/AO98) + ((AN98 * 0.03)/AO98))-AW98))/AH98)*100 -> 13.402095 | BC98: =(((AI98)-(((AP98/AO98) + ((AN98 * 0.3)/AO98))-AX98))/AI98)*100 -> 20.959168 | BD98: =(((AJ98)-(((AP98/AO98) + ((AN98 * 0.03)/AO98))-AY98))/AJ98)*100 -> #VALUE! | BE98: =(((AK98)-(((AP98/AO98) + ((AN98 * 0.15)/AO98))-AZ98))/AK98)*100 -> 17.844324 | BG98: 0005731618899 | BH98: 0057316188998 | BJ98: Co-op Gold Frozen Fruit 300 - 600 g Select Varieties | BM98: C.GOLD WATERMELON BLEND-Z | BN98: 600 | BO98: GR | BQ98: #N/A | BR98: #N/A | BS98: 36 | BT98: 6732.17 | BX98: 7.49 | BY98: 7.49 | BZ98: =BY98-BX98 -> 0 | CC98: =VLOOKUP(A98,'[1]RPT 1280 - Edmonton'!$1:$1048576,4,0) -> #N/A | CE98: EA | CF98: 53.61 | CG98: 0 | CH98: 0 | CI98: 0 | CJ98: =CF98-J98 -> 0 | CK98: =CG98-K98 -> 0 | CL98: =CH98-L98 -> 0 | CM98: =CI98-M98 -> 0 | CO98: 5.49 | CP98: 5.49 | CQ98: =CP98-CO98 -> 0
A99: 6236764 | B99: C.GOLD AVOCADO CHUNKS-Z 12 X 400 GR | C99: 010561110131 | D99: L M | E99: A | F99: B | G99: B | I99: ALL | J99: 56.07 | O99: 56.07 | P99: 4.6725 | Q99: 1.2 | T99: 1 / $5.49 | U99: 1 | V99: $5.49 | W99: 1 /5.49 | X99: 6.49 | Z99: 5.99 | AA99: 0.076555707 | AC99: 6.59 | AD99: 7.79 | AE99: 6.99 | AF99: 8.49 | AH99: =IF(W99<>"",(RIGHT(W99,LEN(W99)-SEARCH("/",W99,1)))/U99,"") -> 5.49 | AI99: =IF(X99<>"",X99,"") -> 6.49 | AJ99: =IF(Y99<>"",Y99,"") | AK99: =IF(Z99<>"",Z99,"") -> 5.99 | AM99: 57.53 | AN99: 11.27 | AO99: 12 | AP99: =(AM99 * 1.05) - L99 - Q99 - K99 -> 59.2065 | AQ99: Y | AR99: =(((AH99)-((AP99/AO99) + ((AN99 * 0.03)/AO99)))/AH99)*100 -> 9.6165756 | AS99: =(((AI99)-((AP99/AO99) + ((AN99 * 0.3)/AO99)))/AI99)*100 -> 19.635978 | AT99: =(((AJ99)-((AP99/AO99) + ((AN99 * 0.03)/AO99)))/AJ99)*100 -> #VALUE! | AU99: =(((AK99)-((AP99/AO99) + ((AN99 * 0.07)/AO99)))/AK99)*100 -> 16.533945 | BB99: =(((AH99)-(((AP99/AO99) + ((AN99 * 0.03)/AO99))-AW99))/AH99)*100 -> 9.6165756 | BC99: =(((AI99)-(((AP99/AO99) + ((AN99 * 0.3)/AO99))-AX99))/AI99)*100 -> 19.635978 | BD99: =(((AJ99)-(((AP99/AO99) + ((AN99 * 0.03)/AO99))-AY99))/AJ99)*100 -> #VALUE! | BE99: =(((AK99)-(((AP99/AO99) + ((AN99 * 0.15)/AO99))-AZ99))/AK99)*100 -> 15.279633 | BG99: 0005731618897 | BH99: 0057316188974 | BJ99: Co-op Gold Frozen Fruit 300 - 600 g Select Varieties | BM99: C.GOLD AVOCADO CHUNKS-Z | BN99: 400 | BO99: GR | BQ99: #N/A | BR99: #N/A | BS99: 37 | BT99: 5168.1 | BX99: 7.29 | BY99: 7.29 | BZ99: =BY99-BX99 -> 0 | CC99: =VLOOKUP(A99,'[1]RPT 1280 - Edmonton'!$1:$1048576,4,0) -> #N/A | CE99: EA | CF99: 56.07 | CG99: 0 | CH99: 0 | CI99: 0 | CJ99: =CF99-J99 -> 0 | CK99: =CG99-K99 -> 0 | CL99: =CH99-L99 -> 0 | CM99: =CI99-M99 -> 0 | CO99: 5.49 | CP99: 5.49 | CQ99: =CP99-CO99 -> 0
A100: 6294490 | B100: C.GOLD SLICED PEACHES-Z 12 X 600 GR | C100: 010561110120 | D100: L M | E100: A | F100: B | G100: B | I100: ALL | J100: 58.96 | O100: 58.96 | P100: 4.9133333 | Q100: 1.2 | T100: 1 / $5.49 | U100: 1 | V100: $5.49 | W100: 1 /5.49 | X100: 6.49 | Z100: 5.99 | AA100: 0.051238919 | AC100: 6.59 | AD100: 7.79 | AE100: 6.99 | AF100: 8.49 | AH100: =IF(W100<>"",(RIGHT(W100,LEN(W100)-SEARCH("/",W100,1)))/U100,"") -> 5.49 | AI100: =IF(X100<>"",X100,"") -> 6.49 | AJ100: =IF(Y100<>"",Y100,"") | AK100: =IF(Z100<>"",Z100,"") -> 5.99 | AM100: 60.49 | AN100: 16.69 | AO100: 12 | AP100: =(AM100 * 1.05) - L100 - Q100 - K100 -> 62.3145 | AQ100: N | AR100: =(((AH100)-((AP100/AO100) + ((AN100 * 0.03)/AO100)))/AH100)*100 -> 4.6520947 | AS100: =(((AI100)-((AP100/AO100) + ((AN100 * 0.3)/AO100)))/AI100)*100 -> 13.557396 | AT100: =(((AJ100)-((AP100/AO100) + ((AN100 * 0.03)/AO100)))/AJ100)*100 -> #VALUE! | AU100: =(((AK100)-((AP100/AO100) + ((AN100 * 0.07)/AO100)))/AK100)*100 -> 11.682248 | BB100: =(((AH100)-(((AP100/AO100) + ((AN100 * 0.03)/AO100))-AW100))/AH100)*100 -> 4.6520947 | BC100: =(((AI100)-(((AP100/AO100) + ((AN100 * 0.3)/AO100))-AX100))/AI100)*100 -> 13.557396 | BD100: =(((AJ100)-(((AP100/AO100) + ((AN100 * 0.03)/AO100))-AY100))/AJ100)*100 -> #VALUE! | BE100: =(((AK100)-(((AP100/AO100) + ((AN100 * 0.15)/AO100))-AZ100))/AK100)*100 -> 9.8247078 | BG100: 0005731619877 | BH100: 0057316198775 | BJ100: Co-op Gold Frozen Fruit 300 - 600 g Select Varieties | BM100: C.GOLD SLICED PEACHES-Z | BN100: 600 | BO100: GR | BQ100: #N/A | BR100: #N/A | BS100: 27 | BT100: 12804.42 | BX100: 7.49 | BY100: 7.49 | BZ100: =BY100-BX100 -> 0 | CC100: =VLOOKUP(A100,'[1]RPT 1280 - Edmonton'!$1:$1048576,4,0) -> #N/A | CE100: EA | CF100: 58.96 | CG100: 0 | CH100: 0 | CI100: 0 | CJ100: =CF100-J100 -> 0 | CK100: =CG100-K100 -> 0 | CL100: =CH100-L100 -> 0 | CM100: =CI100-M100 -> 0 | CO100: 5.49 | CP100: 5.49 | CQ100: =CP100-CO100 -> 0
...

Sheet FP - 1
D1: AD NO.: | F1: 15
D2: AD Theme: | F2: we love local
A5: **Remote Market
H6: FLYER START DATE: | L6: 46121 | Q6: FLYER STOP DATE: | T6: =L6+6 -> 46127
A8: 6250120 | B8: str 1.7/kg | N8: produce
A9: Whole Beef Brisket Cut from Canada AA Grade or Higher Random Cryovac Wrapped Raised in Western Canada | M9: =VLOOKUP(M8,Source!$1:$1048576,62,FALSE) -> #N/A
A14: =VLOOKUP(A8,[3]Meat!$1:$1048576,4,0) -> 4960 | M14: =VLOOKUP(M8,Source!$1:$1048576,59,FALSE) -> #N/A
A16: 5.99lb/13.21kg | E16: 6.49lb/14.31kg | I16: 5.99lb/13.21kg | M16: =VLOOKUP(M8,Source!$1:$1048576,23,FALSE) -> #N/A | Q16: =VLOOKUP(M8,Source!$1:$1048576,24,FALSE) -> #N/A | U16: =VLOOKUP(M8,Source!$1:$1048576,26,FALSE) -> #N/A
A18: =VLOOKUP(A8,[4]Source!$1:$1048576,54,FALSE) -> #N/A | E18: =VLOOKUP(A8,[4]Source!$1:$1048576,55,FALSE) -> #N/A | I18: =VLOOKUP(A8,[4]Source!$1:$1048576,57,FALSE) -> #N/A | M18: =VLOOKUP(M8,Source!1:1048576,54,FALSE) -> #N/A | Q18: =VLOOKUP(M8,Source!1:1048576,55,FALSE) -> #N/A | U18: =VLOOKUP(M8,Source!1:1048576,57,FALSE) -> #N/A
A19: 2468312 | B19: red hot april13-14-15-canada | M19: 603605 | N19: Canada-str
A20: Co-op Centsibles Enriched Flour 10 kg | M20: =VLOOKUP(M19,Source!$1:$1048576,62,FALSE) -> Kraft Singles 825 g or Cheez Whiz 900 g
A25: =VLOOKUP(A19,Source!$1:$1048576,59,FALSE) -> 0005731618245 | M25: 0006810089235/6810000359
A27: =VLOOKUP(A19,Source!$1:$1048576,23,FALSE) -> 1 /7.99 | E27: =VLOOKUP(A19,Source!$1:$1048576,24,FALSE) -> 4.99 | I27: =VLOOKUP(A19,Source!$1:$1048576,26,FALSE) -> 9.99 | M27: =VLOOKUP(M19,Source!$1:$1048576,23,FALSE) -> 1 /6.99 | Q27: =VLOOKUP(M19,Source!$1:$1048576,24,FALSE) -> 8.99 | U27: =VLOOKUP(M19,Source!$1:$1048576,26,FALSE) -> 7.99
A29: =VLOOKUP(A19,Source!$1:$1048576,54,FALSE) -> -15.613267 | C29: =VLOOKUP(#REF!,Source!$1:$1048576,54,FALSE) -> #REF! | E29: =VLOOKUP(A19,Source!$1:$1048576,55,FALSE) -> -204.15832 | G29: =VLOOKUP(#REF!,Source!$1:$1048576,54,FALSE) -> #REF! | I29: =VLOOKUP(A19,Source!$1:$1048576,57,FALSE) -> -18.893894 | K29: =VLOOKUP(#REF!,Source!$1:$1048576,54,FALSE) -> #REF! | M29: =VLOOKUP(M19,Source!$1:$1048576,54,FALSE) -> -11.498569 | O29: =VLOOKUP(#REF!,Source!$1:$1048576,54,FALSE) -> #REF! | Q29: =VLOOKUP(M19,Source!$1:$1048576,55,FALSE) -> 4.7219132 | S29: =VLOOKUP(#REF!,Source!$1:$1048576,54,FALSE) -> #REF! | U29: =VLOOKUP(M19,Source!$1:$1048576,57,FALSE) -> -1.8366708 | W29: =VLOOKUP(#REF!,Source!$1:$1048576,54,FALSE) -> #REF!
A30: 6499271 | B30: Canada-str | M30: 856351 | N30: no-str
A31: Co-op Gold Ice Cream or Frozen Yogurt 1.5 L or Novelties Package of 4 - 12 | M31: =VLOOKUP(M30,Source!$1:$1048576,62,FALSE) -> Lucky Dragon AAA Scented Jasmine Rice 18.1 kg
A36: 0005731621715/0005731613225 | M36: =VLOOKUP(M30,Source!$1:$1048576,59,FALSE) -> 0005731616335
A38: =VLOOKUP(A30,Source!$1:$1048576,23,FALSE) -> 1 /4.99 | E38: =VLOOKUP(A30,Source!$1:$1048576,24,FALSE) -> 5.99 | I38: =VLOOKUP(A30,Source!$1:$1048576,26,FALSE) -> 5.49 | M38: =VLOOKUP(M30,Source!$1:$1048576,23,FALSE) -> 1 /27.99 | Q38: =VLOOKUP(M30,Source!$1:$1048576,24,FALSE) -> 59.99 | U38: =VLOOKUP(M30,Source!$1:$1048576,26,FALSE) -> 51.99
A40: =VLOOKUP(A30,Source!$1:$1048576,54,FALSE) -> -4.3947896 | C40: =VLOOKUP(#REF!,Source!$1:$1048576,54,FALSE) -> #REF! | E40: =VLOOKUP(A30,Source!$1:$1048576,55,FALSE) -> 3.0717863 | G40: =VLOOKUP(#REF!,Source!$1:$1048576,54,FALSE) -> #REF! | I40: =VLOOKUP(A30,Source!$1:$1048576,57,FALSE) -> 0.28233151 | K40: =VLOOKUP(#REF!,Source!$1:$1048576,54,FALSE) -> #REF! | M40: =VLOOKUP(M30,Source!$1:$1048576,54,FALSE) -> -23.290461 | O40: =VLOOKUP(#REF!,Source!$1:$1048576,54,FALSE) -> #REF! | Q40: =VLOOKUP(M30,Source!$1:$1048576,55,FALSE) -> 24.51742 | S40: =VLOOKUP(#REF!,Source!$1:$1048576,54,FALSE) -> #REF! | U40: =VLOOKUP(M30,Source!$1:$1048576,57,FALSE) -> 24.41431 | W40: =VLOOKUP(#REF!,Source!$1:$1048576,54,FALSE) -> #REF!
A41: 551002 | M41: 536805 | N41: Canada
A42: Co-op Chicken Split Wings Grain Fed, Free Run, Air Chilled Value Pack Raised in Western Canada | M42: =VLOOKUP(M41,Source!$1:$1048576,62,FALSE) -> Dr. Oetker Pizza Ristorante or Casa Di Mama Frozen 320 - 410 g
A47: 5168 | M47: 0005833617000/0005833617303
A49: 4.99lb/11.00kg | E49: 5.49lb/12.10kg | I49: 5.19lb/11.44kg | M49: =VLOOKUP(M41,Source!$1:$1048576,23,FALSE) -> 1 /3.99 | Q49: =VLOOKUP(M41,Source!$1:$1048576,24,FALSE) -> 4.49 | U49: =VLOOKUP(M41,Source!$1:$1048576,26,FALSE) -> 4.19
A51: =VLOOKUP(A41,Source!$1:$1048576,54,FALSE) -> #N/A | C51: =VLOOKUP(#REF!,Source!$1:$1048576,54,FALSE) -> #REF! | E51: =VLOOKUP(A41,Source!$1:$1048576,55,FALSE) -> #N/A | G51: =VLOOKUP(#REF!,Source!$1:$1048576,54,FALSE) -> #REF! | I51: =VLOOKUP(A41,Source!$1:$1048576,57,FALSE) -> #N/A | K51: =VLOOKUP(#REF!,Source!$1:$1048576,54,FALSE) -> #REF! | M51: =VLOOKUP(M41,Source!$1:$1048576,54,FALSE) -> 1.3816685 | O51: =VLOOKUP(#REF!,Source!$1:$1048576,54,FALSE) -> #REF! | Q51: =VLOOKUP(M41,Source!$1:$1048576,55,FALSE) -> 5.7747375 | S51: =VLOOKUP(#REF!,Source!$1:$1048576,54,FALSE) -> #REF! | U51: =VLOOKUP(M41,Source!$1:$1048576,57,FALSE) -> 2.9509035 | W51: =VLOOKUP(#REF!,Source!$1:$1048576,54,FALSE) -> #REF!

Sheet Meat - P2
A1: 980383
A2: Bone-in Pork Loin Centre Chops Cut In-store by Your Local Butcher Value Pack Raised in Western Canada
A12: =VLOOKUP(A1,[3]Meat!$A:$E,4,0) -> 4725
A14: 3.49lb/7.69kg | I14: 4.49lb/9.90kg | Q14: 3.99lb/8.80kg
A16: =VLOOKUP(A1,[4]Source!$1:$1048576,54,FALSE) -> #N/A | I16: =VLOOKUP(F1,[4]Source!$1:$1048576,55,FALSE) -> #N/A | Q16: =VLOOKUP(A1,[4]Source!$1:$1048576,57,FALSE) -> #N/A
A17: 6250062 | G17: 6250088 | M17: 174177
A18: Boneless Beef Sirloin Tip Roast or Marinating Steak Cut In-store by Your Local Butcher From Canada AA Grade or Higher Aged 14 days Raised in Western Canada | G18: Boneless Stewing Beef Cut In-store by Your Local Butcher from Canada AA Grade or Higher Aged 14 Days Raised in Western Canada | M18: =VLOOKUP(M17,[3]Meat!$1:$1048576,5,0) -> Co-op Boneless Skinless Chicken Breasts Grain Fed, Free Run, Air Chilled Value Pack Raised in Western Canada
A22: 4440/4446 | G22: =VLOOKUP(G17,[3]Meat!$1:$1048576,4,0) -> 4481 | M22: =VLOOKUP(M17,[3]Meat!$1:$1048576,4,0) -> 5146
A24: 9.49lb/20.92kg | C24: 9.99lb/22.02kg | E24: 9.49lb/20.92kg | G24: 10.99lb/24.23kg | I24: 10.99lb/24.23kg | K24: 10.99lb/24.23kg | M24: 5.99lb/13.21kg | Q24: =VLOOKUP(M17,[4]Source!$1:$1048576,24,FALSE) -> #N/A | U24: 6.49lb/14.31kg
A26: =VLOOKUP(A17,[4]Source!$1:$1048576,54,FALSE) -> #N/A | C26: =VLOOKUP(A17,[4]Source!$1:$1048576,55,FALSE) -> #N/A | E26: =VLOOKUP(A17,[4]Source!$1:$1048576,57,FALSE) -> #N/A | F26: =VLOOKUP(F17,[4]Source!$1:$1048576,55,FALSE) -> #N/A | G26: =VLOOKUP(G17,[4]Source!$1:$1048576,54,FALSE) -> #N/A | I26: =VLOOKUP(G17,[4]Source!$1:$1048576,55,FALSE) -> #N/A | K26: =VLOOKUP(G17,[4]Source!$1:$1048576,57,FALSE) -> #N/A | L26: =VLOOKUP(L17,[4]Source!$1:$1048576,55,FALSE) -> #N/A | M26: =VLOOKUP(M17,[4]Source!$1:$1048576,54,FALSE) -> #N/A | Q26: =VLOOKUP(M17,[4]Source!$1:$1048576,55,FALSE) -> #N/A | U26: =VLOOKUP(M17,[4]Source!$1:$1048576,57,FALSE) -> #N/A
A27: 423749 | B27: no | M27: 6220263 | N27: canada | S27: 838441 | T27: canada-str
A28: Johnsonville Dinner Sausage 500 g Select Varieties | M28: =VLOOKUP(M27,[3]Meat!$1:$1048576,5,0) -> Schneiders Smoked Sausage, Juicy Jumbos or All Beef Wieners 375 - 450 g | S28: Harvest Garlic Sausage Ring or Wieners 1 kg
A32: =VLOOKUP(A27,[3]Meat!$1:$1048576,4,0) -> 7778219550 | M32: =VLOOKUP(M27,[3]Meat!$1:$1048576,4,0) -> 6200015806 | S32: 5739370013
A34: 6.49 | E34: 6.99 | I34: 6.79 | M34: 7.99 | O34: 8.99 | Q34: 8.49 | R34: =VLOOKUP(R27,[4]Source!$1:$1048576,24,FALSE) -> #N/A | S34: 14.99 | U34: =VLOOKUP(S27,[4]Source!$1:$1048576,24,FALSE) -> #N/A | W34: 15.49 | X34: =VLOOKUP(X27,[4]Source!$1:$1048576,24,FALSE) -> #N/A
A36: =VLOOKUP(A27,[4]Source!$1:$1048576,54,FALSE) -> #N/A | E36: =VLOOKUP(A27,[4]Source!$1:$1048576,55,FALSE) -> #N/A | I36: =VLOOKUP(A27,[4]Source!$1:$1048576,57,FALSE) -> #N/A | O36: =VLOOKUP(M27,[4]Source!$1:$1048576,55,FALSE) -> #N/A | Q36: =VLOOKUP(M27,[4]Source!$1:$1048576,57,FALSE) -> #N/A | R36: =VLOOKUP(R27,[4]Source!$1:$1048576,55,FALSE) -> #N/A | S36: =VLOOKUP(S27,[4]Source!$1:$1048576,54,FALSE) -> #N/A | U36: =VLOOKUP(S27,[4]Source!$1:$1048576,55,FALSE) -> #N/A | W36: =VLOOKUP(S27,[4]Source!$1:$1048576,57,FALSE) -> #N/A | X36: =VLOOKUP(X27,[4]Source!$1:$1048576,55,FALSE) -> #N/A
A37: 2429140 | B37: canada m5 | G37: 6293278 | H37: canada m4 | M37: 2474310 | N37: canada | S37: 944322 | T37: no
A38: =VLOOKUP(A37,[3]Meat!$1:$1048576,5,0) -> Co-op Gold Pork Back Ribs Fully Cooked 510 - 610 g | G38: =VLOOKUP(G37,[3]Meat!$1:$1048576,5,0) -> Schneiders Lunchmate Stackers or Kits 90 - 120 g | M38: =VLOOKUP(M37,[3]Meat!$1:$1048576,5,0) -> Co-op Gold Potstickers Frozen 454 g | S38: Co-op Centsibles Zesty Chicken Breast 1.13 kg ro Chicken Tenders 1.2 kg Frozen
A42: =VLOOKUP(A37,[3]Meat!$1:$1048576,4,0) -> 5731617819 | G42: =VLOOKUP(G37,[3]Meat!$1:$1048576,4,0) -> 6310032000 | M42: =VLOOKUP(M37,[3]Meat!$1:$1048576,4,0) -> 5731618118 | S42: 5731621865/6731616889
A44: 10.99 | C44: 11.99 | E44: 11.49 | F44: =VLOOKUP(F37,[4]Source!$1:$1048576,24,FALSE) -> #N/A | G44: 3/9.00 | I44: 2/7.00 | K44: 3/9.99 | L44: =VLOOKUP(L37,[4]Source!$1:$1048576,24,FALSE) -> #N/A | M44: 5.49 | O44: 5.99 | Q44: 5.79 | R44: =VLOOKUP(R37,[4]Source!$1:$1048576,24,FALSE) -> #N/A | S44: 16.99 | U44: 16.99 | W44: 16.99 | X44: =VLOOKUP(X37,[4]Source!$1:$1048576,24,FALSE) -> #N/A
A46: =VLOOKUP(A37,[4]Source!$1:$1048576,54,FALSE) -> #N/A | C46: =VLOOKUP(A37,[4]Source!$1:$1048576,55,FALSE) -> #N/A | E46: =VLOOKUP(A37,[4]Source!$1:$1048576,57,FALSE) -> #N/A | F46: =VLOOKUP(F37,[4]Source!$1:$1048576,55,FALSE) -> #N/A | G46: =VLOOKUP(G37,[4]Source!$1:$1048576,54,FALSE) -> #N/A | I46: =VLOOKUP(G37,[4]Source!$1:$1048576,55,FALSE) -> #N/A | K46: =VLOOKUP(G37,[4]Source!$1:$1048576,57,FALSE) -> #N/A | L46: =VLOOKUP(L37,[4]Source!$1:$1048576,55,FALSE) -> #N/A | M46: =VLOOKUP(M37,[4]Source!$1:$1048576,54,FALSE) -> #N/A | O46: =VLOOKUP(M37,[4]Source!$1:$1048576,55,FALSE) -> #N/A | Q46: =VLOOKUP(M37,[4]Source!$1:$1048576,57,FALSE) -> #N/A | R46: =VLOOKUP(R37,[4]Source!$1:$1048576,55,FALSE) -> #N/A | S46: =VLOOKUP(S37,[4]Source!$1:$1048576,54,FALSE) -> #N/A | U46: =VLOOKUP(S37,[4]Source!$1:$1048576,55,FALSE) -> #N/A | W46: =VLOOKUP(S37,[4]Source!$1:$1048576,57,FALSE) -> #N/A | X46: =VLOOKUP(X37,[4]Source!$1:$1048576,55,FALSE) -> #N/A
A47: 860627 | B47: canada m3 | M47: 590125 | N47: canada m 2
A48: =VLOOKUP(A47,[3]Meat!$1:$1048576,5,0) -> Co-op Gold Chicken, Beef or Pork Entrées Frozen 600 - 650 g | M48: =VLOOKUP(M47,[3]Meat!$1:$1048576,5,0) -> Co-op Centsibles Sausage Sticks 300 - 375 g
A58: =VLOOKUP(A47,[3]Meat!$1:$1048576,4,0) -> 5731616262 | M58: =VLOOKUP(M47,[3]Meat!$1:$1048576,4,0) -> 5731617370
A60: 9.99 | E60: 9.99 | I60: 9.99 | M60: 3.99 | Q60: 4.49 | U60: 4.19
A62: =VLOOKUP(A47,[4]Source!$1:$1048576,54,FALSE) -> #N/A | E62: =VLOOKUP(A47,[4]Source!$1:$1048576,55,FALSE) -> #N/A | I62: =VLOOKUP(A47,[4]Source!$1:$1048576,57,FALSE) -> #N/A | M62: =VLOOKUP(M47,[4]Source!$1:$1048576,54,FALSE) -> #N/A | Q62: =VLOOKUP(M47,[4]Source!$1:$1048576,55,FALSE) -> #N/A | U62: =VLOOKUP(M47,[4]Source!$1:$1048576,57,FALSE) -> #N/A
A63: Deli
M64: 124057 | N64: canada
A65: Deli image | M65: =VLOOKUP(M64,[3]Deli!$1:$1048576,5,0) -> Olivieri Pasta 280 - 350 g or Sauce 300 mL
A69: =VLOOKUP(A64,[4]Source!$1:$1048576,59,FALSE) -> #N/A | M69: =VLOOKUP(M64,[3]Deli!$1:$1048576,4,0) -> 5844100138
A71: =VLOOKUP(A64,[4]Source!$1:$1048576,23,FALSE) -> #N/A | E71: =VLOOKUP(A64,[4]Source!$1:$1048576,24,FALSE) -> #N/A | I71: =VLOOKUP(A64,[4]Source!$1:$1048576,26,FALSE) -> #N/A | M71: 5.99 | Q71: 6.49 | U71: 6.49
A73: =VLOOKUP(A64,[4]Source!$1:$1048576,54,FALSE) -> #N/A | E73: =VLOOKUP(A64,[4]Source!$1:$1048576,55,FALSE) -> #N/A | I73: =VLOOKUP(A64,[4]Source!$1:$1048576,57,FALSE) -> #N/A | M73: =VLOOKUP(M64,[4]Source!$1:$1048576,54,FALSE) -> #N/A | Q73: =VLOOKUP(M64,[4]Source!$1:$1048576,55,FALSE) -> #N/A | U73: =VLOOKUP(M64,[4]Source!$1:$1048576,57,FALSE) -> #N/A
A74: 197756 | B74: canada-str | M74: 926766 | N74: canada-str | S74: 682666 | T74: canada-str
A75: =VLOOKUP(A74,[3]Deli!$1:$1048576,5,0) -> The Laughing Cow Spreadable Cheese 128 - 133 g or Dippers Package of 4 Select Varieties | M75: =VLOOKUP(M74,[3]Deli!$1:$1048576,5,0) -> Castello Havarti Cheese 170 - 200 g | S75: =VLOOKUP(S74,[3]Deli!$1:$1048576,5,0) -> Tre Stelle Feta in Brine 200 g
A79: =VLOOKUP(A74,[3]Deli!$1:$1048576,4,0) -> 4175701157 | M79: =VLOOKUP(M74,[3]Deli!$1:$1048576,4,0) -> 6046616100 | S79: =VLOOKUP(S74,[3]Deli!$1:$1048576,4,0) -> 5944100366
A81: 2/6.00 | E81: 4.99 | I81: 2/7.00 | M81: 5.99 | O81: 7.49 | Q81: 5.99 | R81: =VLOOKUP(R74,[4]Source!$1:$1048576,24,FALSE) -> #N/A | S81: 5.99 | U81: 6.99 | W81: 5.99 | X81: =VLOOKUP(X74,[4]Source!$1:$1048576,24,FALSE) -> #N/A
A83: =VLOOKUP(A74,[4]Source!$1:$1048576,54,FALSE) -> #N/A | E83: =VLOOKUP(A74,[4]Source!$1:$1048576,55,FALSE) -> #N/A | I83: =VLOOKUP(A74,[4]Source!$1:$1048576,57,FALSE) -> #N/A | M83: =VLOOKUP(M74,[4]Source!$1:$1048576,54,FALSE) -> #N/A | O83: =VLOOKUP(M74,[4]Source!$1:$1048576,55,FALSE) -> #N/A | Q83: =VLOOKUP(M74,[4]Source!$1:$1048576,57,FALSE) -> #N/A | R83: =VLOOKUP(R74,[4]Source!$1:$1048576,55,FALSE) -> #N/A | S83: =VLOOKUP(S74,[4]Source!$1:$1048576,54,FALSE) -> #N/A | U83: =VLOOKUP(S74,[4]Source!$1:$1048576,55,FALSE) -> #N/A | W83: =VLOOKUP(S74,[4]Source!$1:$1048576,57,FALSE) -> #N/A | X83: =VLOOKUP(X74,[4]Source!$1:$1048576,55,FALSE) -> #N/A

Sheet Fresh - P3
B1: produce
A10: =VLOOKUP(A1,Source!$1:$1048576,59,FALSE) -> #N/A
A12: =VLOOKUP(A1,Source!$1:$1048576,23,FALSE) -> #N/A | I12: =VLOOKUP(A1,Source!$1:$1048576,24,FALSE) -> #N/A | Q12: =VLOOKUP(A1,Source!$1:$1048576,26,FALSE) -> #N/A
A14: =VLOOKUP(A1,Source!$1:$1048576,54,FALSE) -> #N/A | C14: =VLOOKUP(#REF!,Source!$1:$1048576,54,FALSE) -> #REF! | E14: =VLOOKUP(#REF!,Source!$1:$1048576,54,FALSE) -> #REF! | G14: =VLOOKUP(#REF!,Source!$1:$1048576,54,FALSE) -> #REF! | I14: =VLOOKUP(A1,Source!$1:$1048576,55,FALSE) -> #N/A | K14: =VLOOKUP(#REF!,Source!$1:$1048576,55,FALSE) -> #REF! | M14: =VLOOKUP(#REF!,Source!$1:$1048576,55,FALSE) -> #REF! | O14: =VLOOKUP(#REF!,Source!$1:$1048576,55,FALSE) -> #REF! | Q14: =VLOOKUP(A1,Source!$1:$1048576,57,FALSE) -> #N/A | R14: =VLOOKUP(#REF!,Source!#REF!,56,FALSE) -> #REF! | S14: =VLOOKUP(#REF!,Source!$1:$1048576,57,FALSE) -> #REF! | T14: =VLOOKUP(#REF!,Source!#REF!,56,FALSE) -> #REF! | U14: =VLOOKUP(#REF!,Source!$1:$1048576,57,FALSE) -> #REF! | V14: =VLOOKUP(#REF!,Source!#REF!,56,FALSE) -> #REF! | W14: =VLOOKUP(#REF!,Source!$1:$1048576,57,FALSE) -> #REF! | X14: =VLOOKUP(#REF!,Source!#REF!,56,FALSE) -> #REF!
A24: =VLOOKUP(A15,Source!$1:$1048576,59,FALSE) -> #N/A | G24: =VLOOKUP(G15,Source!$1:$1048576,59,FALSE) -> #N/A | M24: =VLOOKUP(M15,Source!$1:$1048576,59,FALSE) -> #N/A | S24: =VLOOKUP(S15,Source!$1:$1048576,59,FALSE) -> #N/A
A26: =VLOOKUP(A15,Source!$1:$1048576,23,FALSE) -> #N/A | C26: =VLOOKUP(A15,Source!$1:$1048576,24,FALSE) -> #N/A | E26: =VLOOKUP(A15,Source!$1:$1048576,26,FALSE) -> #N/A | G26: =VLOOKUP(G15,Source!$1:$1048576,23,FALSE) -> #N/A | I26: =VLOOKUP(G15,Source!$1:$1048576,24,FALSE) -> #N/A | K26: =VLOOKUP(G15,Source!$1:$1048576,26,FALSE) -> #N/A | M26: =VLOOKUP(M15,Source!$1:$1048576,23,FALSE) -> #N/A | O26: =VLOOKUP(M15,Source!$1:$1048576,24,FALSE) -> #N/A | Q26: =VLOOKUP(M15,Source!$1:$1048576,26,FALSE) -> #N/A | S26: =VLOOKUP(S15,Source!$1:$1048576,23,FALSE) -> #N/A | U26: =VLOOKUP(S15,Source!$1:$1048576,24,FALSE) -> #N/A | W26: =VLOOKUP(S15,Source!$1:$1048576,26,FALSE) -> #N/A
A28: =VLOOKUP(A15,Source!$1:$1048576,54,FALSE) -> #N/A | C28: =VLOOKUP(A15,Source!$1:$1048576,55,FALSE) -> #N/A | E28: =VLOOKUP(A15,Source!$1:$1048576,57,FALSE) -> #N/A | F28: =VLOOKUP(D15,Source!#REF!,56,FALSE) -> #REF! | G28: =VLOOKUP(G15,Source!$1:$1048576,54,FALSE) -> #N/A | I28: =VLOOKUP(G15,Source!$1:$1048576,55,FALSE) -> #N/A | K28: =VLOOKUP(G15,Source!$1:$1048576,57,FALSE) -> #N/A | L28: =VLOOKUP(J15,Source!#REF!,56,FALSE) -> #REF! | M28: =VLOOKUP(M15,Source!$1:$1048576,54,FALSE) -> #N/A | O28: =VLOOKUP(M15,Source!$1:$1048576,55,FALSE) -> #N/A | Q28: =VLOOKUP(M15,Source!$1:$1048576,57,FALSE) -> #N/A | R28: =VLOOKUP(P15,Source!#REF!,56,FALSE) -> #REF! | S28: =VLOOKUP(S15,Source!$1:$1048576,54,FALSE) -> #N/A | U28: =VLOOKUP(S15,Source!$1:$1048576,55,FALSE) -> #N/A | W28: =VLOOKUP(S15,Source!$1:$1048576,57,FALSE) -> #N/A | X28: =VLOOKUP(V15,Source!#REF!,56,FALSE) -> #REF!
N29: floral | T29: floral
A38: =VLOOKUP(A29,Source!$1:$1048576,59,FALSE) -> #N/A | G38: =VLOOKUP(G29,Source!$1:$1048576,59,FALSE) -> #N/A | M38: =VLOOKUP(M29,Source!$1:$1048576,59,FALSE) -> #N/A | S38: =VLOOKUP(S29,Source!$1:$1048576,59,FALSE) -> #N/A
A40: =VLOOKUP(A29,Source!$1:$1048576,23,FALSE) -> #N/A | C40: =VLOOKUP(A29,Source!$1:$1048576,24,FALSE) -> #N/A | E40: =VLOOKUP(A29,Source!$1:$1048576,26,FALSE) -> #N/A | G40: =VLOOKUP(G29,Source!$1:$1048576,23,FALSE) -> #N/A | I40: =VLOOKUP(G29,Source!$1:$1048576,24,FALSE) -> #N/A | K40: =VLOOKUP(G29,Source!$1:$1048576,26,FALSE) -> #N/A | M40: =VLOOKUP(M29,Source!$1:$1048576,23,FALSE) -> #N/A | O40: =VLOOKUP(M29,Source!$1:$1048576,24,FALSE) -> #N/A | Q40: =VLOOKUP(M29,Source!$1:$1048576,26,FALSE) -> #N/A | S40: =VLOOKUP(S29,Source!$1:$1048576,23,FALSE) -> #N/A | U40: =VLOOKUP(S29,Source!$1:$1048576,24,FALSE) -> #N/A | W40: =VLOOKUP(S29,Source!$1:$1048576,26,FALSE) -> #N/A
A42: =VLOOKUP(A29,Source!$1:$1048576,54,FALSE) -> #N/A | C42: =VLOOKUP(A29,Source!$1:$1048576,55,FALSE) -> #N/A | E42: =VLOOKUP(A29,Source!$1:$1048576,57,FALSE) -> #N/A | F42: =VLOOKUP(D29,Source!#REF!,56,FALSE) -> #REF! | G42: =VLOOKUP(G29,Source!$1:$1048576,54,FALSE) -> #N/A | I42: =VLOOKUP(G29,Source!$1:$1048576,55,FALSE) -> #N/A | K42: =VLOOKUP(G29,Source!$1:$1048576,57,FALSE) -> #N/A | L42: =VLOOKUP(J29,Source!#REF!,56,FALSE) -> #REF! | M42: =VLOOKUP(M29,Source!$1:$1048576,54,FALSE) -> #N/A | O42: =VLOOKUP(M29,Source!$1:$1048576,55,FALSE) -> #N/A | Q42: =VLOOKUP(M29,Source!$1:$1048576,57,FALSE) -> #N/A | R42: =VLOOKUP(P29,Source!#REF!,56,FALSE) -> #REF! | S42: =VLOOKUP(S29,Source!$1:$1048576,54,FALSE) -> #N/A | U42: =VLOOKUP(S29,Source!$1:$1048576,55,FALSE) -> #N/A | W42: =VLOOKUP(S29,Source!$1:$1048576,57,FALSE) -> #N/A | X42: =VLOOKUP(V29,Source!#REF!,56,FALSE) -> #REF!
A44: =VLOOKUP(A43,Source!$1:$1048576,62,FALSE) -> #N/A | M44: =VLOOKUP(M43,Source!$1:$1048576,62,FALSE) -> #N/A
A58: =VLOOKUP(A43,Source!$1:$1048576,59,FALSE) -> #N/A | M58: =VLOOKUP(M43,Source!$1:$1048576,59,FALSE) -> #N/A
A60: =VLOOKUP(A43,Source!$1:$1048576,23,FALSE) -> #N/A | E60: =VLOOKUP(A43,Source!$1:$1048576,24,FALSE) -> #N/A | I60: =VLOOKUP(A43,Source!$1:$1048576,26,FALSE) -> #N/A | M60: =VLOOKUP(M43,Source!$1:$1048576,23,FALSE) -> #N/A | Q60: =VLOOKUP(M43,Source!$1:$1048576,24,FALSE) -> #N/A | U60: =VLOOKUP(M43,Source!$1:$1048576,26,FALSE) -> #N/A
A62: =VLOOKUP(A43,Source!$1:$1048576,54,FALSE) -> #N/A | C62: =VLOOKUP(#REF!,Source!$1:$1048576,54,FALSE) -> #REF! | E62: =VLOOKUP(A43,Source!$1:$1048576,55,FALSE) -> #N/A | G62: =VLOOKUP(#REF!,Source!$1:$1048576,54,FALSE) -> #REF! | I62: =VLOOKUP(A43,Source!$1:$1048576,57,FALSE) -> #N/A | K62: =VLOOKUP(#REF!,Source!$1:$1048576,54,FALSE) -> #REF! | M62: =VLOOKUP(M43,Source!$1:$1048576,54,FALSE) -> #N/A | O62: =VLOOKUP(#REF!,Source!$1:$1048576,54,FALSE) -> #REF! | Q62: =VLOOKUP(M43,Source!$1:$1048576,55,FALSE) -> #N/A | S62: =VLOOKUP(#REF!,Source!$1:$1048576,54,FALSE) -> #REF! | U62: =VLOOKUP(M43,Source!$1:$1048576,57,FALSE) -> #N/A | W62: =VLOOKUP(#REF!,Source!$1:$1048576,54,FALSE) -> #REF!
A63: Bakery
M64: 271080 | N64: canada
A65: Bakery image | M65: =VLOOKUP(M64,Source!$1:$1048576,62,FALSE) -> Villaggio Bread 510 - 550 g or Buns Package of 6 - 8
A69: =VLOOKUP(A64,Source!$1:$1048576,59,FALSE) -> #N/A | M69: =VLOOKUP(M64,Source!$1:$1048576,59,FALSE) -> 0006872110354
A70: =VLOOKUP(A64,Source!$1:$1048576,23,FALSE) -> #N/A | E70: =VLOOKUP(A64,Source!$1:$1048576,24,FALSE) -> #N/A | I70: =VLOOKUP(A64,Source!$1:$1048576,26,FALSE) -> #N/A | M70: 3.49 | Q70: 4.49 | U70: 3.99
A72: =VLOOKUP(A64,Source!$1:$1048576,54,FALSE) -> #N/A | C72: =VLOOKUP(C64,Source!$1:$1048576,54,FALSE) -> #N/A | E72: =VLOOKUP(A64,Source!$1:$1048576,55,FALSE) -> #N/A | G72: =VLOOKUP(G64,Source!$1:$1048576,54,FALSE) -> #N/A | I72: =VLOOKUP(A64,Source!$1:$1048576,57,FALSE) -> #N/A | K72: =VLOOKUP(K64,Source!$1:$1048576,54,FALSE) -> #N/A | M72: =VLOOKUP(M64,Source!$1:$1048576,54,FALSE) -> 0 | O72: =VLOOKUP(O64,Source!$1:$1048576,54,FALSE) -> #N/A | Q72: =VLOOKUP(M64,Source!$1:$1048576,55,FALSE) -> 0 | S72: =VLOOKUP(S64,Source!$1:$1048576,54,FALSE) -> #N/A | U72: =VLOOKUP(M64,Source!$1:$1048576,57,FALSE) -> 0 | W72: =VLOOKUP(W64,Source!$1:$1048576,54,FALSE) -> #N/A
A73: 2465722 | B73: canada | M73: 6411730 | N73: canada
A74: two bite Cupcakes Package of 12 | M74: =VLOOKUP(M73,Source!$1:$1048576,62,FALSE) -> Dempster's Tortillas White or Whole Wheat 7" Package of 10
A78: 77098173491 | M78: =VLOOKUP(M73,Source!$1:$1048576,59,FALSE) -> 0006872103808
A79: 5.99 | E79: 6.49 | I79: 6.19 | M79: 3.49 | Q79: 4.19 | U79: 3.99
A81: =VLOOKUP(A73,Source!$1:$1048576,54,FALSE) -> #N/A | C81: =VLOOKUP(C73,Source!$1:$1048576,54,FALSE) -> #N/A | E81: =VLOOKUP(A73,Source!$1:$1048576,55,FALSE) -> #N/A | G81: =VLOOKUP(G73,Source!$1:$1048576,54,FALSE) -> #N/A | I81: =VLOOKUP(A73,Source!$1:$1048576,57,FALSE) -> #N/A | K81: =VLOOKUP(K73,Source!$1:$1048576,54,FALSE) -> #N/A | M81: =VLOOKUP(M73,Source!$1:$1048576,54,FALSE) -> 14.558739 | O81: =VLOOKUP(O73,Source!$1:$1048576,54,FALSE) -> #N/A | Q81: =VLOOKUP(M73,Source!$1:$1048576,55,FALSE) -> -19.367542 | S81: =VLOOKUP(S73,Source!$1:$1048576,54,FALSE) -> #N/A | U81: =VLOOKUP(M73,Source!$1:$1048576,57,FALSE) -> -2.3614776 | W81: =VLOOKUP(W73,Source!$1:$1048576,54,FALSE) -> #N/A
A82: 6384473 | B82: canada | G82: 6467971 | H82: canada | M82: 6523088 | N82: canada
A83: =VLOOKUP(A82,Source!$1:$1048576,62,FALSE) -> Buttery Flake Rolls Package of 12 In-Store Baked | G83: Co-op Gold Fruit Pies 620 g Select Varieties | M83: Hostess Snack Cakes 269 g
A87: =VLOOKUP(A82,Source!$1:$1048576,59,FALSE) -> 0059327034868 | G87: =VLOOKUP(G82,Source!$1:$1048576,59,FALSE) -> 0005731621537 | M87: 77755094321
A88: 3.99 | C88: 3.99 | E88: 3.99 | G88: 6.49 | I88: 7.49 | K88: 6.99 | M88: 4.99 | Q88: 5.79 | U88: 5.49
A90: =VLOOKUP(A82,Source!$1:$1048576,54,FALSE) -> 95.808781 | C90: =VLOOKUP(A82,Source!$1:$1048576,55,FALSE) -> 95.90967 | E90: =VLOOKUP(A82,Source!$1:$1048576,57,FALSE) -> 95.991449 | F90: =VLOOKUP(D82,Source!#REF!,56,FALSE) -> #REF! | G90: =VLOOKUP(G82,Source!$1:$1048576,54,FALSE) -> 28.00077 | I90: =VLOOKUP(G82,Source!$1:$1048576,55,FALSE) -> 34.528241 | K90: =VLOOKUP(G82,Source!$1:$1048576,57,FALSE) -> 32.367872 | L90: =VLOOKUP(J82,Source!#REF!,56,FALSE) -> #REF! | M90: =VLOOKUP(M82,Source!$1:$1048576,54,FALSE) -> 0 | O90: =VLOOKUP(O82,Source!$1:$1048576,54,FALSE) -> #N/A | Q90: =VLOOKUP(M82,Source!$1:$1048576,55,FALSE) -> 0 | S90: =VLOOKUP(S82,Source!$1:$1048576,54,FALSE) -> #N/A | U90: =VLOOKUP(M82,Source!$1:$1048576,57,FALSE) -> 0 | W90: =VLOOKUP(W82,Source!$1:$1048576,54,FALSE) -> #N/A

Sheet Grocery - P4
A1: 6541379 | B1: NEW@TGP-canada | M1: 6539811 | N1: NEW@TGP-no
A2: 7up Zero Sugar Watermelon Mini Cans* 6 x 222 mL | M2: Cheetos Puffs Cheesy Bacon 250 g
A16: 65400157891 | M16: 6041008545
A18: 2/10.00 | E18: =VLOOKUP(A1,Source!$1:$1048576,24,FALSE) -> 5.99 | I18: 2/10.00 | M18: 2/9.50 | Q18: 4.99 | U18: 2/9.50
A20: =VLOOKUP(A1,Source!$1:$1048576,54,FALSE) -> 21.216717 | C20: =VLOOKUP(#REF!,Source!$1:$1048576,54,FALSE) -> #REF! | E20: =VLOOKUP(A1,Source!$1:$1048576,55,FALSE) -> 18.662354 | G20: =VLOOKUP(#REF!,Source!$1:$1048576,54,FALSE) -> #REF! | I20: =VLOOKUP(A1,Source!$1:$1048576,57,FALSE) -> 27.351836 | K20: =VLOOKUP(#REF!,Source!$1:$1048576,54,FALSE) -> #REF! | M20: =VLOOKUP(M1,Source!$1:$1048576,54,FALSE) -> 12.180717 | O20: =VLOOKUP(#REF!,Source!$1:$1048576,54,FALSE) -> #REF! | Q20: =VLOOKUP(M1,Source!$1:$1048576,55,FALSE) -> 21.388889 | S20: =VLOOKUP(#REF!,Source!$1:$1048576,54,FALSE) -> #REF! | U20: =VLOOKUP(M1,Source!$1:$1048576,57,FALSE) -> 18.436898 | W20: =VLOOKUP(#REF!,Source!$1:$1048576,54,FALSE) -> #REF!
A21: 6284673 | B21: no | G21: 160804 | H21: canada | M21: 498493 | N21: no
A22: =VLOOKUP(A21,Source!$1:$1048576,62,FALSE) -> Budweiser Zero Alcohol Free Beer 12 x 355 mL PLUS DEPOSIT | G22: =VLOOKUP(G21,Source!$1:$1048576,62,FALSE) -> Hawkins Cheezies 210 g | M22: =VLOOKUP(M21,Source!$1:$1048576,62,FALSE) -> Hershey's Chocolate Bars 34 - 58 g or Twizzlers 60 - 90 g
A26: =VLOOKUP(A21,Source!$1:$1048576,59,FALSE) -> 0006206738153 | G26: =VLOOKUP(G21,Source!$1:$1048576,59,FALSE) -> 0005675721000 | M26: 0006800079282
A28: =VLOOKUP(A21,Source!$1:$1048576,23,FALSE) -> 1 /14.99 | C28: =VLOOKUP(A21,Source!$1:$1048576,24,FALSE) -> 21.99 | E28: =VLOOKUP(A21,Source!$1:$1048576,26,FALSE) -> 15.99 | G28: =VLOOKUP(G21,Source!$1:$1048576,23,FALSE) -> 3/11.00 | I28: =VLOOKUP(G21,Source!$1:$1048576,24,FALSE) -> 3.99 | K28: =VLOOKUP(G21,Source!$1:$1048576,26,FALSE) -> 3/11.00 | M28: =VLOOKUP(M21,Source!$1:$1048576,23,FALSE) -> 3/4.00 | Q28: =VLOOKUP(M21,Source!$1:$1048576,24,FALSE) -> 2/3.00 | U28: =VLOOKUP(M21,Source!$1:$1048576,26,FALSE) -> 2/3.00
A30: =VLOOKUP(A21,Source!$1:$1048576,54,FALSE) -> 9.0026684 | C30: =VLOOKUP(A21,Source!$1:$1048576,55,FALSE) -> 25.077308 | E30: =VLOOKUP(A21,Source!$1:$1048576,57,FALSE) -> 6.8136335 | F30: =VLOOKUP(D21,Source!#REF!,56,FALSE) -> #REF! | G30: =VLOOKUP(G21,Source!$1:$1048576,54,FALSE) -> 23.336364 | I30: =VLOOKUP(G21,Source!$1:$1048576,55,FALSE) -> 25.657895 | K30: =VLOOKUP(G21,Source!$1:$1048576,57,FALSE) -> 23.24 | L30: =VLOOKUP(J21,Source!#REF!,56,FALSE) -> #REF! | M30: =VLOOKUP(M21,Source!$1:$1048576,54,FALSE) -> 11.38 | Q30: =VLOOKUP(M21,Source!$1:$1048576,55,FALSE) -> 17.89 | U30: =VLOOKUP(M21,Source!$1:$1048576,57,FALSE) -> 19.45
A31: 208512 | B31: no | M31: 6262836 | N31: canada | S31: 6263008 | T31: canada
A32: =VLOOKUP(A31,Source!$1:$1048576,62,FALSE) -> Nature Valley Bars or General Mills, Betty Crocker or Mott's Snacks 120 - 226 g Select Varieties | M32: Ruffles Potato Chips 190 - 200 g | S32: Miss Vickies Kettle Cooked Potato Chips 190 - 200 g
A36: 0006563315739/0006563314637 | M36: 6041004723 | S36: 6041004667
A38: =VLOOKUP(A31,Source!$1:$1048576,23,FALSE) -> 3/9.00 | E38: =VLOOKUP(A31,Source!$1:$1048576,24,FALSE) -> 2/7.00 | I38: =VLOOKUP(A31,Source!$1:$1048576,26,FALSE) -> 2/7.00 | M38: 2/9.00 | O38: 4.99 | Q38: 2/9.00 | S38: 2/9.50 | U38: 4.99 | W38: 2/9.50
A40: =VLOOKUP(A31,Source!$1:$1048576,54,FALSE) -> 11.159444 | E40: =VLOOKUP(A31,Source!$1:$1048576,55,FALSE) -> 19.43 | I40: =VLOOKUP(A31,Source!$1:$1048576,57,FALSE) -> 21.76 | M40: =VLOOKUP(M31,Source!$1:$1048576,54,FALSE) -> #N/A | O40: =VLOOKUP(M31,Source!$1:$1048576,55,FALSE) -> #N/A | Q40: =VLOOKUP(M31,Source!$1:$1048576,57,FALSE) -> #N/A | R40: =VLOOKUP(P31,Source!#REF!,56,FALSE) -> #REF! | S40: =VLOOKUP(S31,Source!$1:$1048576,54,FALSE) -> 10.12882 | U40: =VLOOKUP(S31,Source!$1:$1048576,55,FALSE) -> 19.637978 | W40: =VLOOKUP(S31,Source!$1:$1048576,57,FALSE) -> 16.571532 | X40: =VLOOKUP(V31,Source!#REF!,56,FALSE) -> #REF!
A41: 481218 | B41: canada | G41: 623819 | H41: canada | M41: 706671 | N41: no | S41: 897736 | T41: canada
A42: =VLOOKUP(A41,Source!$1:$1048576,62,FALSE) -> Cracker Barrel Natural Cheese Slices 200 - 240 g | G42: Bear Paws 168 - 240 g | M42: =VLOOKUP(M41,Source!$1:$1048576,62,FALSE) -> Betty Crocker Gluten Free Mixes Selected Varieties & Sizes | S42: Old Dutch Crunchys, Cheese Pleesers, Cheesy Puffcorn or Humpty Dumpty Party Mix or Rings 200 - 290 g
A46: 0006820000647 | G46: 0006334800694 | M46: 0006563327275 | S46: =VLOOKUP(S41,Source!$1:$1048576,59,FALSE) -> 0006634335004
A48: =VLOOKUP(A41,Source!$1:$1048576,23,FALSE) -> 1 /5.49 | C48: =VLOOKUP(A41,Source!$1:$1048576,24,FALSE) -> 6.79 | E48: =VLOOKUP(A41,Source!$1:$1048576,26,FALSE) -> 5.99 | G48: =VLOOKUP(G41,Source!$1:$1048576,23,FALSE) -> 2/7.00 | I48: =VLOOKUP(G41,Source!$1:$1048576,24,FALSE) -> 3.79 | K48: =VLOOKUP(G41,Source!$1:$1048576,26,FALSE) -> 3.79 | M48: =VLOOKUP(M41,Source!$1:$1048576,23,FALSE) -> 1 /5.49 | O48: =VLOOKUP(M41,Source!$1:$1048576,24,FALSE) -> 6.49 | Q48: =VLOOKUP(M41,Source!$1:$1048576,26,FALSE) -> 5.99 | S48: 2/8.00 | U48: 2/9.00 | W48: 2/8.00
A50: =VLOOKUP(A41,Source!$1:$1048576,54,FALSE) -> 10.551002 | C50: =VLOOKUP(A41,Source!$1:$1048576,55,FALSE) -> 25.522828 | E50: =VLOOKUP(A41,Source!$1:$1048576,57,FALSE) -> 16.932387 | F50: =VLOOKUP(D41,Source!#REF!,56,FALSE) -> #REF! | G50: =VLOOKUP(G41,Source!$1:$1048576,54,FALSE) -> 16.621667 | I50: =VLOOKUP(G41,Source!$1:$1048576,55,FALSE) -> 19.184257 | K50: =VLOOKUP(G41,Source!$1:$1048576,57,FALSE) -> 21.304969 | L50: =VLOOKUP(J41,Source!#REF!,56,FALSE) -> #REF! | M50: =VLOOKUP(M41,Source!$1:$1048576,54,FALSE) -> 12.297511 | O50: =VLOOKUP(M41,Source!$1:$1048576,55,FALSE) -> 20.756292 | Q50: =VLOOKUP(M41,Source!$1:$1048576,57,FALSE) -> 17.184196 | R50: =VLOOKUP(P41,Source!#REF!,56,FALSE) -> #REF! | S50: =VLOOKUP(S41,Source!$1:$1048576,54,FALSE) -> 3.1852315 | U50: =VLOOKUP(S41,Source!$1:$1048576,55,FALSE) -> 15.730689 | W50: =VLOOKUP(S41,Source!$1:$1048576,57,FALSE) -> 5.9009547 | X50: =VLOOKUP(V41,Source!#REF!,56,FALSE) -> #REF!
A51: 6409502 | B51: canada | M51: 941344 | N51: canada
A52: =VLOOKUP(A51,Source!$1:$1048576,62,FALSE) -> Co-op Centsibles Vegetables Frozen 2 kg | M52: =VLOOKUP(M51,Source!$1:$1048576,62,FALSE) -> Cracker Barrel Cheese 400 g or Shreds 250 - 320 g
A66: =VLOOKUP(A51,Source!$1:$1048576,59,FALSE) -> 0005731621137 | M66: 0006820047736/0006820000539
A68: =VLOOKUP(A51,Source!$1:$1048576,23,FALSE) -> 1 /5.99 | E68: =VLOOKUP(A51,Source!$1:$1048576,24,FALSE) -> 7.99 | I68: =VLOOKUP(A51,Source!$1:$1048576,26,FALSE) -> 6.99 | M68: =VLOOKUP(M51,Source!$1:$1048576,23,FALSE) -> 1 /6.49 | Q68: =VLOOKUP(M51,Source!$1:$1048576,24,FALSE) -> 6.99 | U68: =VLOOKUP(M51,Source!$1:$1048576,26,FALSE) -> 6.79
A70: =VLOOKUP(A51,Source!$1:$1048576,54,FALSE) -> 5.9557596 | C70: =VLOOKUP(#REF!,Source!$1:$1048576,54,FALSE) -> #REF! | E70: =VLOOKUP(A51,Source!$1:$1048576,55,FALSE) -> 14.599499 | G70: =VLOOKUP(#REF!,Source!$1:$1048576,54,FALSE) -> #REF! | I70: =VLOOKUP(A51,Source!$1:$1048576,57,FALSE) -> 11.841917 | K70: =VLOOKUP(#REF!,Source!$1:$1048576,54,FALSE) -> #REF! | M70: =VLOOKUP(M51,Source!$1:$1048576,54,FALSE) -> 9.7971238 | O70: =VLOOKUP(#REF!,Source!$1:$1048576,54,FALSE) -> #REF! | Q70: =VLOOKUP(M51,Source!$1:$1048576,55,FALSE) -> 13.255842 | S70: =VLOOKUP(#REF!,Source!$1:$1048576,54,FALSE) -> #REF! | U70: =VLOOKUP(M51,Source!$1:$1048576,57,FALSE) -> 12.412862 | W70: =VLOOKUP(#REF!,Source!$1:$1048576,54,FALSE) -> #REF!
A71: 6352082 | B71: no | M71: 502484 | N71: no | S71: 432914 | T71: canada
A72: =VLOOKUP(A71,Source!$1:$1048576,62,FALSE) -> Pillsbury Pizza Pops Package of 4 or Toaster Strudel Pastries Package of 6 | M72: =VLOOKUP(M71,Source!$1:$1048576,62,FALSE) -> Swanson Frozen Dinner Entrées 280 - 345 g | S72: =VLOOKUP(S71,Source!$1:$1048576,62,FALSE) -> Wong Wing Appetizers or Entrées Frozen 284 - 680 g
A76: 0006905212949/0006905271016 | M76: =VLOOKUP(M71,Source!$1:$1048576,59,FALSE) -> 0006321106220 | S76: 0006945901501
A78: =VLOOKUP(A71,Source!$1:$1048576,23,FALSE) -> 2/7.00 | E78: =VLOOKUP(A71,Source!$1:$1048576,24,FALSE) -> 3.99 | I78: =VLOOKUP(A71,Source!$1:$1048576,26,FALSE) -> 3.79 | M78: =VLOOKUP(M71,Source!$1:$1048576,23,FALSE) -> 2/9.00 | O78: =VLOOKUP(M71,Source!$1:$1048576,24,FALSE) -> 4.79 | Q78: =VLOOKUP(M71,Source!$1:$1048576,26,FALSE) -> 2/9.00 | S78: =VLOOKUP(S71,Source!$1:$1048576,23,FALSE) -> 1 /6.99 | U78: =VLOOKUP(S71,Source!$1:$1048576,24,FALSE) -> 9.49 | W78: =VLOOKUP(S71,Source!$1:$1048576,26,FALSE) -> 7.49
A80: =VLOOKUP(A71,Source!$1:$1048576,54,FALSE) -> 23.945 | E80: =VLOOKUP(A71,Source!$1:$1048576,55,FALSE) -> 26.535088 | I80: =VLOOKUP(A71,Source!$1:$1048576,57,FALSE) -> 26.606201 | M80: =VLOOKUP(M71,Source!$1:$1048576,54,FALSE) -> 20.05037 | O80: =VLOOKUP(M71,Source!$1:$1048576,55,FALSE) -> 20.752436 | Q80: =VLOOKUP(M71,Source!$1:$1048576,57,FALSE) -> 18.09 | R80: =VLOOKUP(P71,Source!#REF!,56,FALSE) -> #REF! | S80: =VLOOKUP(S71,Source!$1:$1048576,54,FALSE) -> 6.5833333 | U80: =VLOOKUP(S71,Source!$1:$1048576,55,FALSE) -> 26.040569 | W80: =VLOOKUP(S71,Source!$1:$1048576,57,FALSE) -> 9.9182243 | X80: =VLOOKUP(V71,Source!#REF!,56,FALSE) -> #REF!
A81: 6509640 | B81: canada | G81: 6509194 | H81: canada | M81: 974634 | N81: danone insert-canada
A82: =VLOOKUP(A81,Source!$1:$1048576,62,FALSE) -> Activia Yogurt 12 x 100 g | G82: Activia Yogurt 650 g | M82: International Delight Coffee Creamer* 946 mL
A86: =VLOOKUP(A81,Source!$1:$1048576,59,FALSE) -> 0005680019560 | G86: =VLOOKUP(G81,Source!$1:$1048576,59,FALSE) -> 0005680009827 | M86: 0004127102564
A88: =VLOOKUP(A81,Source!$1:$1048576,23,FALSE) -> 1 /6.49 | C88: =VLOOKUP(A81,Source!$1:$1048576,24,FALSE) -> 7.49 | E88: =VLOOKUP(A81,Source!$1:$1048576,26,FALSE) -> 6.99 | G88: =VLOOKUP(G81,Source!$1:$1048576,23,FALSE) -> 1 /4.19 | I88: =VLOOKUP(G81,Source!$1:$1048576,24,FALSE) -> 4.79 | K88: =VLOOKUP(G81,Source!$1:$1048576,26,FALSE) -> 4.49 | M88: =VLOOKUP(M81,Source!$1:$1048576,23,FALSE) -> 1 /4.99 | Q88: =VLOOKUP(M81,Source!$1:$1048576,24,FALSE) -> 5.99 | U88: =VLOOKUP(M81,Source!$1:$1048576,26,FALSE) -> 5.49
A90: =VLOOKUP(A81,Source!$1:$1048576,54,FALSE) -> 6.4071649 | C90: =VLOOKUP(A81,Source!$1:$1048576,55,FALSE) -> 8.5931242 | E90: =VLOOKUP(A81,Source!$1:$1048576,57,FALSE) -> 8.1920601 | F90: =VLOOKUP(D81,Source!#REF!,56,FALSE) -> #REF! | G90: =VLOOKUP(G81,Source!$1:$1048576,54,FALSE) -> 12.837709 | I90: =VLOOKUP(G81,Source!$1:$1048576,55,FALSE) -> 15.046973 | K90: =VLOOKUP(G81,Source!$1:$1048576,57,FALSE) -> 14.532294 | L90: =VLOOKUP(J81,Source!#REF!,56,FALSE) -> #REF! | M90: =VLOOKUP(M81,Source!$1:$1048576,54,FALSE) -> 6.1863727 | Q90: =VLOOKUP(M81,Source!$1:$1048576,55,FALSE) -> 10.421536 | U90: =VLOOKUP(M81,Source!$1:$1048576,57,FALSE) -> 9.1894353
A91: 6509681 | B91: canada | G91: 6509400 | H91: canada | M91: 6521652 | N91: canada | S91: 6540843 | T91: no
A92: =VLOOKUP(A91,Source!$1:$1048576,62,FALSE) -> Oikos Yogurt 650 - 750 g | G92: Oikos Yogurt 12 x 100 g or Plain 1.5 kg | M92: Activia Expert Yogurt 750 g | S92: Silk Protein Soy Beverages* 1.42 L
A96: =VLOOKUP(A91,Source!$1:$1048576,59,FALSE) -> 0005680018771 | G96: =VLOOKUP(G91,Source!$1:$1048576,59,FALSE) -> 0005680074222 | M96: =VLOOKUP(M91,Source!$1:$1048576,59,FALSE) -> 0005680051136 | S96: =VLOOKUP(S91,Source!$1:$1048576,59,FALSE) -> 0005680051165
A98: =VLOOKUP(A91,Source!$1:$1048576,23,FALSE) -> 1 /6.99 | C98: =VLOOKUP(A91,Source!$1:$1048576,24,FALSE) -> 7.99 | E98: =VLOOKUP(A91,Source!$1:$1048576,26,FALSE) -> 7.49 | G98: =VLOOKUP(G91,Source!$1:$1048576,23,FALSE) -> 1 /10.49 | I98: =VLOOKUP(G91,Source!$1:$1048576,24,FALSE) -> 12.49 | K98: =VLOOKUP(G91,Source!$1:$1048576,26,FALSE) -> 11.49 | M98: =VLOOKUP(M91,Source!$1:$1048576,23,FALSE) -> 1 /4.99 | O98: =VLOOKUP(M91,Source!$1:$1048576,24,FALSE) -> 5.99 | Q98: =VLOOKUP(M91,Source!$1:$1048576,26,FALSE) -> 5.99 | S98: =VLOOKUP(S91,Source!$1:$1048576,23,FALSE) -> 1 /6.99 | U98: =VLOOKUP(S91,Source!$1:$1048576,24,FALSE) -> 7.99 | W98: =VLOOKUP(S91,Source!$1:$1048576,26,FALSE) -> 7.49
A100: =VLOOKUP(A91,Source!$1:$1048576,54,FALSE) -> 10.578684 | C100: =VLOOKUP(A91,Source!$1:$1048576,55,FALSE) -> 15.963705 | E100: =VLOOKUP(A91,Source!$1:$1048576,57,FALSE) -> 13.79506 | F100: =VLOOKUP(D91,Source!#REF!,56,FALSE) -> #REF! | G100: =VLOOKUP(G91,Source!$1:$1048576,54,FALSE) -> 9.1539561 | I100: =VLOOKUP(G91,Source!$1:$1048576,55,FALSE) -> 16.67534 | K100: =VLOOKUP(G91,Source!$1:$1048576,57,FALSE) -> 13.666232 | L100: =VLOOKUP(J91,Source!#REF!,56,FALSE) -> #REF! | M100: =VLOOKUP(M91,Source!$1:$1048576,54,FALSE) -> 8.8997996 | O100: =VLOOKUP(M91,Source!$1:$1048576,55,FALSE) -> 16.460768 | Q100: =VLOOKUP(M91,Source!$1:$1048576,57,FALSE) -> 20.709516 | R100: =VLOOKUP(P91,Source!#REF!,56,FALSE) -> #REF! | S100: =VLOOKUP(S91,Source!$1:$1048576,54,FALSE) -> 13.490701 | U100: =VLOOKUP(S91,Source!$1:$1048576,55,FALSE) -> 12.546934 | W100: =VLOOKUP(S91,Source!$1:$1048576,57,FALSE) -> 13.684913 | X100: =VLOOKUP(V91,Source!#REF!,56,FALSE) -> #REF!

Sheet Grocery - P5
A1: 6226328 | B1: family ad-canada ad | M1: 321950 | N1: canada
A2: Purex Bathroom Tissue Package of 12 Double or 8 Ultra Triple Rolls | M2: =VLOOKUP(M1,Source!$1:$1048576,62,FALSE) -> Scotties Facial Tissue Package of 6
M6: =VLOOKUP(M1,Source!$1:$1048576,59,FALSE) -> 0006132880136
M8: =VLOOKUP(M1,Source!$1:$1048576,23,FALSE) -> 1 /8.99 | Q8: =VLOOKUP(M1,Source!$1:$1048576,24,FALSE) -> 10.99 | U8: =VLOOKUP(M1,Source!$1:$1048576,26,FALSE) -> 9.99
M10: =VLOOKUP(M1,Source!$1:$1048576,54,FALSE) -> 5.9244994 | Q10: =VLOOKUP(M1,Source!$1:$1048576,55,FALSE) -> 16.789126 | U10: =VLOOKUP(M1,Source!$1:$1048576,57,FALSE) -> 12.282908
M11: 6507438 | N11: canada
M12: SpongeTowels Ultra Package of 3 Double Roll or UltraPRO
A16: =VLOOKUP(A1,Source!$1:$1048576,59,FALSE) -> 0006132848214 | M16: =VLOOKUP(M11,Source!$1:$1048576,59,FALSE) -> 0006132853351
A18: =VLOOKUP(A1,Source!$1:$1048576,23,FALSE) -> 1 /8.29 | E18: =VLOOKUP(A1,Source!$1:$1048576,24,FALSE) -> 9.49 | I18: =VLOOKUP(A1,Source!$1:$1048576,26,FALSE) -> 8.99 | M18: =VLOOKUP(M11,Source!$1:$1048576,23,FALSE) -> 1 /8.49 | Q18: =VLOOKUP(M11,Source!$1:$1048576,24,FALSE) -> 10.49 | U18: =VLOOKUP(M11,Source!$1:$1048576,26,FALSE) -> 9.49
A20: =VLOOKUP(A1,Source!$1:$1048576,54,FALSE) -> 5.0485525 | C20: =VLOOKUP(#REF!,Source!$1:$1048576,54,FALSE) -> #REF! | E20: =VLOOKUP(A1,Source!$1:$1048576,55,FALSE) -> 8.7473656 | G20: =VLOOKUP(#REF!,Source!$1:$1048576,54,FALSE) -> #REF! | I20: =VLOOKUP(A1,Source!$1:$1048576,57,FALSE) -> 8.5442158 | K20: =VLOOKUP(#REF!,Source!$1:$1048576,54,FALSE) -> #REF! | M20: =VLOOKUP(M11,Source!$1:$1048576,54,FALSE) -> 4.9210836 | Q20: =VLOOKUP(M11,Source!$1:$1048576,55,FALSE) -> 18.200071 | U20: =VLOOKUP(M11,Source!$1:$1048576,57,FALSE) -> 12.557956
A21: 344663 | B21: canada | G21: 6238919 | H21: canada | M21: 6238869 | N21: canada
A22: =VLOOKUP(A21,Source!$1:$1048576,62,FALSE) -> Kraft Grated Parmesan Cheese 250 g | G22: Tim Hortons Chili 425 g | M22: =VLOOKUP(M21,Source!$1:$1048576,62,FALSE) -> Tim Hortons Soup 540 mL
A26: =VLOOKUP(A21,Source!$1:$1048576,59,FALSE) -> 0006820047905 | G26: =VLOOKUP(G21,Source!$1:$1048576,59,FALSE) -> 0006320912634 | M26: 0006320912636
A28: =VLOOKUP(A21,Source!$1:$1048576,23,FALSE) -> 1 /8.99 | C28: =VLOOKUP(A21,Source!$1:$1048576,24,FALSE) -> 9.49 | E28: =VLOOKUP(A21,Source!$1:$1048576,26,FALSE) -> 9.19 | G28: =VLOOKUP(G21,Source!$1:$1048576,23,FALSE) -> 2/8.00 | I28: =VLOOKUP(G21,Source!$1:$1048576,24,FALSE) -> 4.79 | K28: =VLOOKUP(G21,Source!$1:$1048576,26,FALSE) -> 4.19 | M28: =VLOOKUP(M21,Source!$1:$1048576,23,FALSE) -> 3/9.99 | Q28: =VLOOKUP(M21,Source!$1:$1048576,24,FALSE) -> 3.99 | U28: =VLOOKUP(M21,Source!$1:$1048576,26,FALSE) -> 2/7.00
A30: =VLOOKUP(A21,Source!$1:$1048576,54,FALSE) -> 15.431591 | C30: =VLOOKUP(A21,Source!$1:$1048576,55,FALSE) -> 18.066386 | E30: =VLOOKUP(A21,Source!$1:$1048576,57,FALSE) -> 16.436344 | F30: =VLOOKUP(D21,Source!#REF!,56,FALSE) -> #REF! | G30: =VLOOKUP(G21,Source!$1:$1048576,54,FALSE) -> 10.194375 | I30: =VLOOKUP(G21,Source!$1:$1048576,55,FALSE) -> 19.608559 | K30: =VLOOKUP(G21,Source!$1:$1048576,57,FALSE) -> 11.524463 | L30: =VLOOKUP(J21,Source!#REF!,56,FALSE) -> #REF! | M30: =VLOOKUP(M21,Source!$1:$1048576,54,FALSE) -> 10.225976 | Q30: =VLOOKUP(M21,Source!$1:$1048576,55,FALSE) -> 16.622807 | U30: =VLOOKUP(M21,Source!$1:$1048576,57,FALSE) -> 10.3
A31: 2471720 | B31: no | M31: 2448835 | N31: no | S31: 560912 | T31: canada
A32: =VLOOKUP(A31,Source!$1:$1048576,62,FALSE) -> Christie Premium Plus Crackers 450 - 481 g | M32: =VLOOKUP(M31,Source!$1:$1048576,62,FALSE) -> Gold Seal Sockeye Salmon 213 g | S32: =VLOOKUP(S31,Source!$1:$1048576,62,FALSE) -> Holiday Luncheon Meat 340 g
A36: 0006672100783 | M36: =VLOOKUP(M31,Source!$1:$1048576,59,FALSE) -> 0006381606120 | S36: =VLOOKUP(S31,Source!$1:$1048576,59,FALSE) -> 0005707200195
A38: =VLOOKUP(A31,Source!$1:$1048576,23,FALSE) -> 1/5.49 | E38: =VLOOKUP(A31,Source!$1:$1048576,24,FALSE) -> 5.99 | I38: =VLOOKUP(A31,Source!$1:$1048576,26,FALSE) -> 5.79 | M38: =VLOOKUP(M31,Source!$1:$1048576,23,FALSE) -> 1/6.49 | O38: =VLOOKUP(M31,Source!$1:$1048576,24,FALSE) -> 6.99 | Q38: =VLOOKUP(M31,Source!$1:$1048576,26,FALSE) -> 6.79 | S38: =VLOOKUP(S31,Source!$1:$1048576,23,FALSE) -> 2/7.00 | U38: =VLOOKUP(S31,Source!$1:$1048576,24,FALSE) -> 3.99 | W38: =VLOOKUP(S31,Source!$1:$1048576,26,FALSE) -> 3.79
A40: =VLOOKUP(A31,Source!$1:$1048576,54,FALSE) -> 15.454007 | E40: =VLOOKUP(A31,Source!$1:$1048576,55,FALSE) -> 16.73414 | I40: =VLOOKUP(A31,Source!$1:$1048576,57,FALSE) -> 17.178325 | M40: =VLOOKUP(M31,Source!$1:$1048576,54,FALSE) -> 12.912173 | O40: =VLOOKUP(M31,Source!$1:$1048576,55,FALSE) -> 16.80794 | Q40: =VLOOKUP(M31,Source!$1:$1048576,57,FALSE) -> 15.692194 | R40: =VLOOKUP(P31,Source!#REF!,56,FALSE) -> #REF! | S40: =VLOOKUP(S31,Source!$1:$1048576,54,FALSE) -> 18.136071 | U40: =VLOOKUP(S31,Source!$1:$1048576,55,FALSE) -> 21.975251 | W40: =VLOOKUP(S31,Source!$1:$1048576,57,FALSE) -> 21.492414 | X40: =VLOOKUP(V31,Source!#REF!,56,FALSE) -> #REF!
A41: 197095 | B41: canada | G41: 6473946 | H41: canada | M41: 885632 | N41: canada | S41: 248435 | T41: no
A42: =VLOOKUP(A41,Source!$1:$1048576,62,FALSE) -> Renée's Dressing 350 - 355 mL Select Varieties | G42: =VLOOKUP(G41,Source!$1:$1048576,62,FALSE) -> Catelli Garden Select Pasta Sauce 600 mL | M42: =VLOOKUP(M41,Source!$1:$1048576,62,FALSE) -> SunRype Juice Boxes 5 x 200 mL PLUS DEPOSIT | S42: =VLOOKUP(S41,Source!$1:$1048576,62,FALSE) -> Kraft Miracle Whip or Mayo 650 - 890 mL
A46: 0006228711207 | G46: 0006420001014 | M46: =VLOOKUP(M41,Source!$1:$1048576,59,FALSE) -> 0005796100385 | S46: 0006810004974
A48: =VLOOKUP(A41,Source!$1:$1048576,23,FALSE) -> 2/9.00 | C48: =VLOOKUP(A41,Source!$1:$1048576,24,FALSE) -> 4.99 | E48: =VLOOKUP(A41,Source!$1:$1048576,26,FALSE) -> 4.79 | G48: =VLOOKUP(G41,Source!$1:$1048576,23,FALSE) -> 2/6.00 | I48: =VLOOKUP(G41,Source!$1:$1048576,24,FALSE) -> 3.99 | K48: =VLOOKUP(G41,Source!$1:$1048576,26,FALSE) -> 3.79 | M48: =VLOOKUP(M41,Source!$1:$1048576,23,FALSE) -> 3/8.00 | O48: =VLOOKUP(M41,Source!$1:$1048576,24,FALSE) -> 4.19 | Q48: =VLOOKUP(M41,Source!$1:$1048576,26,FALSE) -> 2/7.00 | S48: =VLOOKUP(S41,Source!$1:$1048576,23,FALSE) -> 2/9.98 | U48: =VLOOKUP(S41,Source!$1:$1048576,24,FALSE) -> 5.99 | W48: =VLOOKUP(S41,Source!$1:$1048576,26,FALSE) -> 5.49
A50: =VLOOKUP(A41,Source!$1:$1048576,54,FALSE) -> 16.632222 | C50: =VLOOKUP(A41,Source!$1:$1048576,55,FALSE) -> 20.435872 | E50: =VLOOKUP(A41,Source!$1:$1048576,57,FALSE) -> 19.650313 | F50: =VLOOKUP(D41,Source!#REF!,56,FALSE) -> #REF! | G50: =VLOOKUP(G41,Source!$1:$1048576,54,FALSE) -> 20.080556 | I50: =VLOOKUP(G41,Source!$1:$1048576,55,FALSE) -> 24.79741 | K50: =VLOOKUP(G41,Source!$1:$1048576,57,FALSE) -> 29.667986 | L50: =VLOOKUP(J41,Source!#REF!,56,FALSE) -> #REF! | M50: =VLOOKUP(M41,Source!$1:$1048576,54,FALSE) -> 8.6846875 | O50: =VLOOKUP(M41,Source!$1:$1048576,55,FALSE) -> 26.079952 | Q50: =VLOOKUP(M41,Source!$1:$1048576,57,FALSE) -> #VALUE! | R50: =VLOOKUP(P41,Source!#REF!,56,FALSE) -> #REF! | S50: =VLOOKUP(S41,Source!$1:$1048576,54,FALSE) -> 14.51002 | U50: =VLOOKUP(S41,Source!$1:$1048576,55,FALSE) -> 21.483723 | W50: =VLOOKUP(S41,Source!$1:$1048576,57,FALSE) -> 18.756831 | X50: =VLOOKUP(V41,Source!#REF!,56,FALSE) -> #REF!
A51: 154187 | B51: canada | M51: 2485191 | N51: canada
A52: =VLOOKUP(A51,Source!$1:$1048576,62,FALSE) -> Kraft Peanut Butter 2 kg | M52: =VLOOKUP(M51,Source!$1:$1048576,62,FALSE) -> Co-opertive Coffee Pods Package of 30 - 40
A66: 0006810008427 | M66: 0005731618243
A68: =VLOOKUP(A51,Source!$1:$1048576,23,FALSE) -> 1 /10.99 | E68: =VLOOKUP(A51,Source!$1:$1048576,24,FALSE) -> 12.99 | I68: =VLOOKUP(A51,Source!$1:$1048576,26,FALSE) -> 11.99 | M68: =VLOOKUP(M51,Source!$1:$1048576,23,FALSE) -> 1 /20.49 | Q68: =VLOOKUP(M51,Source!$1:$1048576,24,FALSE) -> 21.99 | U68: =VLOOKUP(M51,Source!$1:$1048576,26,FALSE) -> 20.99
A70: =VLOOKUP(A51,Source!$1:$1048576,54,FALSE) -> 6.022293 | C70: =VLOOKUP(#REF!,Source!$1:$1048576,54,FALSE) -> #REF! | E70: =VLOOKUP(A51,Source!$1:$1048576,55,FALSE) -> 10.712086 | G70: =VLOOKUP(#REF!,Source!$1:$1048576,54,FALSE) -> #REF! | I70: =VLOOKUP(A51,Source!$1:$1048576,57,FALSE) -> 9.1513761 | K70: =VLOOKUP(#REF!,Source!$1:$1048576,54,FALSE) -> #REF! | M70: =VLOOKUP(M51,Source!$1:$1048576,54,FALSE) -> 5.65 | O70: =VLOOKUP(#REF!,Source!$1:$1048576,54,FALSE) -> #REF! | Q70: =VLOOKUP(M51,Source!$1:$1048576,55,FALSE) -> 9.99 | S70: =VLOOKUP(#REF!,Source!$1:$1048576,54,FALSE) -> #REF! | U70: =VLOOKUP(M51,Source!$1:$1048576,57,FALSE) -> 6.92 | W70: =VLOOKUP(#REF!,Source!$1:$1048576,54,FALSE) -> #REF!
A71: 724831 | B71: canada | M71: 6453690 | N71: canada | S71: 306746 | T71: no
A72: =VLOOKUP(A71,Source!$1:$1048576,62,FALSE) -> McCain Hashbrown Patties Frozen 1.3 kg | M72: Co-op Gold Table Syrup 710 mL | S72: Co-op Gold Pancake Mix 905 g
A76: =VLOOKUP(A71,Source!$1:$1048576,59,FALSE) -> 0005577302231 | M76: =VLOOKUP(M71,Source!$1:$1048576,59,FALSE) -> 0005731621499 | S76: =VLOOKUP(S71,Source!$1:$1048576,59,FALSE) -> 0005731614592
A78: =VLOOKUP(A71,Source!$1:$1048576,23,FALSE) -> 1 /5.99 | E78: =VLOOKUP(A71,Source!$1:$1048576,24,FALSE) -> 6.99 | I78: =VLOOKUP(A71,Source!$1:$1048576,26,FALSE) -> 6.49 | M78: =VLOOKUP(M71,Source!$1:$1048576,23,FALSE) -> 1 /3.99 | O78: =VLOOKUP(M71,Source!$1:$1048576,24,FALSE) -> 4.99 | Q78: =VLOOKUP(M71,Source!$1:$1048576,26,FALSE) -> 4.49 | S78: =VLOOKUP(S71,Source!$1:$1048576,23,FALSE) -> 1 /3.99 | U78: =VLOOKUP(S71,Source!$1:$1048576,24,FALSE) -> 5.79 | W78: =VLOOKUP(S71,Source!$1:$1048576,26,FALSE) -> 4.49
A80: =VLOOKUP(A71,Source!$1:$1048576,54,FALSE) -> 14.775042 | E80: =VLOOKUP(A71,Source!$1:$1048576,55,FALSE) -> 15.076896 | I80: =VLOOKUP(A71,Source!$1:$1048576,57,FALSE) -> 15.649076 | M80: =VLOOKUP(M71,Source!$1:$1048576,54,FALSE) -> 12.092732 | O80: =VLOOKUP(M71,Source!$1:$1048576,55,FALSE) -> 16.633267 | Q80: =VLOOKUP(M71,Source!$1:$1048576,57,FALSE) -> 15.423163 | R80: =VLOOKUP(P71,Source!#REF!,56,FALSE) -> #REF! | S80: =VLOOKUP(S71,Source!$1:$1048576,54,FALSE) -> 8.6873434 | U80: =VLOOKUP(S71,Source!$1:$1048576,55,FALSE) -> 26.58247 | W80: =VLOOKUP(S71,Source!$1:$1048576,57,FALSE) -> 12.842428 | X80: =VLOOKUP(V71,Source!#REF!,56,FALSE) -> #REF!
A81: 772475 | B81: canada | G81: 729814 | H81: canada | M81: 107714 | N81: no | S81: 196584 | T81: canada
A82: Heinz Ketchup 375 mL | G82: =VLOOKUP(G81,Source!$1:$1048576,62,FALSE) -> Minute Maid or Five Alive Juices 1 L PLUS DEPOSIT | M82: Kellogg's Family Size Cereal 480 - 650 g Select Varieties | S82: =VLOOKUP(S81,Source!$1:$1048576,62,FALSE) -> Swift Premium Canned Ham 680 g
A86: =VLOOKUP(A81,Source!$1:$1048576,59,FALSE) -> 0005700024376 | G86: =VLOOKUP(G81,Source!$1:$1048576,59,FALSE) -> 0005960004814 | M86: 0006410044886 | S86: =VLOOKUP(S81,Source!$1:$1048576,59,FALSE) -> 0005707200202
A88: =VLOOKUP(A81,Source!$1:$1048576,23,FALSE) -> 2/6.00 | C88: =VLOOKUP(A81,Source!$1:$1048576,24,FALSE) -> 3.79 | E88: =VLOOKUP(A81,Source!$1:$1048576,26,FALSE) -> 3.49 | G88: =VLOOKUP(G81,Source!$1:$1048576,23,FALSE) -> 3/5.00 | I88: =VLOOKUP(G81,Source!$1:$1048576,24,FALSE) -> 2.99 | K88: =VLOOKUP(G81,Source!$1:$1048576,26,FALSE) -> 1.99 | M88: =VLOOKUP(M81,Source!$1:$1048576,23,FALSE) -> 1 /5.99 | O88: =VLOOKUP(M81,Source!$1:$1048576,24,FALSE) -> 6.99 | Q88: =VLOOKUP(M81,Source!$1:$1048576,26,FALSE) -> 6.49 | S88: =VLOOKUP(S81,Source!$1:$1048576,23,FALSE) -> 1/11.49 | U88: =VLOOKUP(S81,Source!$1:$1048576,24,FALSE) -> 12.49 | W88: =VLOOKUP(S81,Source!$1:$1048576,26,FALSE) -> 11.99
A90: =VLOOKUP(A81,Source!$1:$1048576,54,FALSE) -> 8.8547222 | C90: =VLOOKUP(A81,Source!$1:$1048576,55,FALSE) -> 20.248461 | E90: =VLOOKUP(A81,Source!$1:$1048576,57,FALSE) -> 17.981137 | F90: =VLOOKUP(D81,Source!#REF!,56,FALSE) -> #REF! | G90: =VLOOKUP(G81,Source!$1:$1048576,54,FALSE) -> 8.8025 | I90: =VLOOKUP(G81,Source!$1:$1048576,55,FALSE) -> 28.433668 | K90: =VLOOKUP(G81,Source!$1:$1048576,57,FALSE) -> 9.7759631 | L90: =VLOOKUP(J81,Source!#REF!,56,FALSE) -> #REF! | M90: =VLOOKUP(M81,Source!$1:$1048576,54,FALSE) -> 9.6648581 | O90: =VLOOKUP(M81,Source!$1:$1048576,55,FALSE) -> 16.30186 | Q90: =VLOOKUP(M81,Source!$1:$1048576,57,FALSE) -> 13.615177 | R90: =VLOOKUP(P81,Source!#REF!,56,FALSE) -> #REF! | S90: =VLOOKUP(S81,Source!$1:$1048576,54,FALSE) -> 12.837322 | U90: =VLOOKUP(S81,Source!$1:$1048576,55,FALSE) -> 15.865359 | W90: =VLOOKUP(S81,Source!$1:$1048576,57,FALSE) -> 14.643105 | X90: =VLOOKUP(V81,Source!#REF!,56,FALSE) -> #REF!
A91: 474015 | B91: no | G91: 737080 | H91: no | M91: 685925 | N91: no
A92: Fancy Feast Cat Food 85 g | G92: Fleecy Fabric Softener Sheets Package of 80 | M92: Pine-Sol 1.41 L or Clorox Bleach Wipes Package of 75 Select Varieties
A96: 0006500000294 | G96: 0005800000663 | M96: 0005550040154
A98: =VLOOKUP(A91,Source!$1:$1048576,23,FALSE) -> 5/5.00 | C98: =VLOOKUP(A91,Source!$1:$1048576,24,FALSE) -> 1.19 | E98: =VLOOKUP(A91,Source!$1:$1048576,26,FALSE) -> 1.19 | G98: =VLOOKUP(G91,Source!$1:$1048576,23,FALSE) -> 1 /5.49 | I98: =VLOOKUP(G91,Source!$1:$1048576,24,FALSE) -> 6.99 | K98: =VLOOKUP(G91,Source!$1:$1048576,26,FALSE) -> 6.99 | M98: =VLOOKUP(M91,Source!$1:$1048576,23,FALSE) -> 1/5.99 | Q98: =VLOOKUP(M91,Source!$1:$1048576,24,FALSE) -> 7.99 | U98: =VLOOKUP(M91,Source!$1:$1048576,26,FALSE) -> 7.49
A100: =VLOOKUP(A91,Source!$1:$1048576,54,FALSE) -> 9.56875 | C100: =VLOOKUP(A91,Source!$1:$1048576,55,FALSE) -> 18.807773 | E100: =VLOOKUP(A91,Source!$1:$1048576,57,FALSE) -> 21.696429 | F100: =VLOOKUP(D91,Source!#REF!,56,FALSE) -> #REF! | G100: =VLOOKUP(G91,Source!$1:$1048576,54,FALSE) -> 10.476624 | I100: =VLOOKUP(G91,Source!$1:$1048576,55,FALSE) -> 26.211254 | K100: =VLOOKUP(G91,Source!$1:$1048576,57,FALSE) -> 28.142585 | L100: =VLOOKUP(J91,Source!#REF!,56,FALSE) -> #REF! | M100: =VLOOKUP(M91,Source!$1:$1048576,54,FALSE) -> 16.857262 | Q100: =VLOOKUP(M91,Source!$1:$1048576,55,FALSE) -> 26.26408 | U100: =VLOOKUP(M91,Source!$1:$1048576,57,FALSE) -> 28.100801

Sheet BP-P6
A1: Breakfast theme
A2: 784090 | B2: canada-M1 | N2: produce
A3: Co-op Gold or Burns Sliced Side Bacon 375 g | M3: =VLOOKUP(M2,Source!$1:$1048576,62,FALSE) -> #N/A
A8: =VLOOKUP(A2,[3]Meat!$1:$1048576,4,0) -> 5731616191 | M8: =VLOOKUP(M2,Source!$1:$1048576,59,FALSE) -> #N/A
A10: 5.99 | E10: 6.49 | I10: 6.19 | M10: =VLOOKUP(M2,Source!$1:$1048576,23,FALSE) -> #N/A | Q10: =VLOOKUP(M2,Source!$1:$1048576,24,FALSE) -> #N/A | U10: =VLOOKUP(M2,Source!$1:$1048576,26,FALSE) -> #N/A
A12: =VLOOKUP(A2,[4]Source!$1:$1048576,54,FALSE) -> #N/A | E12: =VLOOKUP(A2,[4]Source!$1:$1048576,55,FALSE) -> #N/A | I12: =VLOOKUP(A2,[4]Source!$1:$1048576,57,FALSE) -> #N/A | M12: =VLOOKUP(M2,Source!#REF!,54,FALSE) -> #REF! | Q12: =VLOOKUP(M2,Source!#REF!,55,FALSE) -> #REF! | U12: =VLOOKUP(M2,Source!#REF!,57,FALSE) -> #REF!
A13: 355685 | B13: canada | M13: 692418 | N13: canada
A14: Co-op Gold Large Eggs Package of 12 | M14: =VLOOKUP(M13,Source!$1:$1048576,62,FALSE) -> Dairyland Cottage Cheese 750 g or Dry 600 g
A19: =VLOOKUP(A13,Source!$1:$1048576,59,FALSE) -> 0005731602928 | M19: =VLOOKUP(M13,Source!$1:$1048576,59,FALSE) -> 0006870004877
A21: =VLOOKUP(A13,Source!$1:$1048576,23,FALSE) -> 1 /3.99 | E21: =VLOOKUP(A13,Source!$1:$1048576,24,FALSE) -> 4.99 | I21: =VLOOKUP(A13,Source!$1:$1048576,26,FALSE) -> 4.49 | M21: =VLOOKUP(M13,Source!$1:$1048576,23,FALSE) -> 1 /4.99 | Q21: =VLOOKUP(M13,Source!$1:$1048576,24,FALSE) -> 5.99 | U21: =VLOOKUP(M13,Source!$1:$1048576,26,FALSE) -> 5.49
A23: =VLOOKUP(A13,Source!$1:$1048576,54,FALSE) -> 1.245614 | C23: =VLOOKUP(#REF!,Source!$1:$1048576,54,FALSE) -> #REF! | E23: =VLOOKUP(A13,Source!$1:$1048576,55,FALSE) -> 10.376754 | G23: =VLOOKUP(#REF!,Source!$1:$1048576,54,FALSE) -> #REF! | I23: =VLOOKUP(A13,Source!$1:$1048576,57,FALSE) -> 6.9777283 | K23: =VLOOKUP(#REF!,Source!$1:$1048576,54,FALSE) -> #REF! | M23: =VLOOKUP(M13,Source!$1:$1048576,54,FALSE) -> 3.6873747 | O23: =VLOOKUP(#REF!,Source!$1:$1048576,54,FALSE) -> #REF! | Q23: =VLOOKUP(M13,Source!$1:$1048576,55,FALSE) -> 12.065943 | S23: =VLOOKUP(#REF!,Source!$1:$1048576,54,FALSE) -> #REF! | U23: =VLOOKUP(M13,Source!$1:$1048576,57,FALSE) -> 8.7249545 | W23: =VLOOKUP(#REF!,Source!$1:$1048576,54,FALSE) -> #REF!
A24: 204727 | B24: no | M24: 2465540 | N24: no
A25: =VLOOKUP(A24,Source!$1:$1048576,62,FALSE) -> Co-op Gold Frozen Fruit 300 - 600 g Select Varieties | M25: =VLOOKUP(M24,Source!$1:$1048576,62,FALSE) -> General Mills Family Size Cereal 455 - 778 g Select Varieties
A30: =VLOOKUP(A24,Source!$1:$1048576,59,FALSE) -> 0005731602880 | M30: =VLOOKUP(M24,Source!$1:$1048576,59,FALSE) -> 0006563313465
A32: =VLOOKUP(A24,Source!$1:$1048576,23,FALSE) -> 1 /5.49 | E32: =VLOOKUP(A24,Source!$1:$1048576,24,FALSE) -> 6.49 | I32: =VLOOKUP(A24,Source!$1:$1048576,26,FALSE) -> 5.99 | M32: =VLOOKUP(M24,Source!$1:$1048576,23,FALSE) -> 1 /5.49 | Q32: =VLOOKUP(M24,Source!$1:$1048576,24,FALSE) -> 6.49 | U32: =VLOOKUP(M24,Source!$1:$1048576,26,FALSE) -> 5.99
A34: =VLOOKUP(A24,Source!$1:$1048576,54,FALSE) -> 1.4212204 | C34: =VLOOKUP(#REF!,Source!$1:$1048576,54,FALSE) -> #REF! | E34: =VLOOKUP(A24,Source!$1:$1048576,55,FALSE) -> 10.824345 | G34: =VLOOKUP(#REF!,Source!$1:$1048576,54,FALSE) -> #REF! | I34: =VLOOKUP(A24,Source!$1:$1048576,57,FALSE) -> 6.8635225 | K34: =VLOOKUP(#REF!,Source!$1:$1048576,54,FALSE) -> #REF! | M34: =VLOOKUP(M24,Source!$1:$1048576,54,FALSE) -> 4.1260474 | O34: =VLOOKUP(#REF!,Source!$1:$1048576,54,FALSE) -> #REF! | Q34: =VLOOKUP(M24,Source!$1:$1048576,55,FALSE) -> 11.946841 | S34: =VLOOKUP(#REF!,Source!$1:$1048576,54,FALSE) -> #REF! | U34: =VLOOKUP(M24,Source!$1:$1048576,57,FALSE) -> 8.7813022 | W34: =VLOOKUP(#REF!,Source!$1:$1048576,54,FALSE) -> #REF!
A35: 6404735 | B35: canada | N35: produce
A36: Co-op Centsibles English Muffins Package of 6 | M36: =VLOOKUP(M35,Source!$1:$1048576,62,FALSE) -> #N/A
A41: 5731615495 | M41: =VLOOKUP(M35,Source!$1:$1048576,59,FALSE) -> #N/A
A43: 2/5.00 | E43: 2.79 | I43: 2/5.00 | M43: =VLOOKUP(M35,Source!$1:$1048576,23,FALSE) -> #N/A | Q43: =VLOOKUP(M35,Source!$1:$1048576,24,FALSE) -> #N/A | U43: =VLOOKUP(M35,Source!$1:$1048576,26,FALSE) -> #N/A
A45: =VLOOKUP(A35,Source!$1:$1048576,54,FALSE) -> #N/A | C45: =VLOOKUP(#REF!,Source!$1:$1048576,54,FALSE) -> #REF! | E45: =VLOOKUP(A35,Source!$1:$1048576,55,FALSE) -> #N/A | G45: =VLOOKUP(#REF!,Source!$1:$1048576,54,FALSE) -> #REF! | I45: =VLOOKUP(A35,Source!$1:$1048576,57,FALSE) -> #N/A | K45: =VLOOKUP(#REF!,Source!$1:$1048576,54,FALSE) -> #REF! | M45: =VLOOKUP(M35,Source!#REF!,54,FALSE) -> #REF! | Q45: =VLOOKUP(M35,Source!#REF!,55,FALSE) -> #REF! | U45: =VLOOKUP(M35,Source!#REF!,57,FALSE) -> #REF!

Sheet Digital
A1: DIGITAL CAMPAIGN INFORMATION:
A2: Items | B2: Top Description | C2: Bottom Description | D2: email subject | E2: Facebook | F2: Digital Blade
A3: brisket | B3: red hot | D3: Local goodness, great savings - Check out this week's flyer | E3: Vaisakhi Apr 14 2026 | F3: NEW@TGP x 2 | G3: Instagram Landscape Photo | H3: 1080 X 608 (1.91:1 ratio)
A4: produce | E4: National Pet Day April 11th | F4: coupon x1 | G4: Instagram Portrait | H4: 1080 x 1350 (4:5 ratio)
A5: kraft singles | D5: https://web.tgp.crs/weeklyad/index.aspx?&flyer_run_id=1165720 | E5: April 15 National Laundry Day
A6: CG ice cream
A7: dr oetker | D7: TGP Weekly Grocery Deals April 9 to April 15, 2026
A8: split wings
F10: 6541379 | G10: NEW@TGP
F11: 7up Zero Sugar Watermelon Mini Cans* 6 x 222 mL
F25: 65400157891
F27: 2/10.00 | J27: =VLOOKUP(F10,Source!$1:$1048576,24,FALSE) -> 5.99 | N27: 2/10.00
F29: =VLOOKUP(F10,Source!$1:$1048576,54,FALSE) -> 21.216717 | H29: =VLOOKUP(#REF!,Source!$1:$1048576,54,FALSE) -> #REF! | J29: =VLOOKUP(F10,Source!$1:$1048576,55,FALSE) -> 18.662354 | L29: =VLOOKUP(#REF!,Source!$1:$1048576,54,FALSE) -> #REF! | N29: =VLOOKUP(F10,Source!$1:$1048576,57,FALSE) -> 27.351836 | P29: =VLOOKUP(#REF!,Source!$1:$1048576,54,FALSE) -> #REF!
F30: 6539811 | G30: NEW@TGP
F31: Cheetos Puffs Cheesy Bacon 250 g
F45: 6041008545
F47: 2/9.50 | J47: 4.99 | N47: 2/9.50
F49: =VLOOKUP(F30,Source!$1:$1048576,54,FALSE) -> 12.180717 | H49: =VLOOKUP(#REF!,Source!$1:$1048576,54,FALSE) -> #REF! | J49: =VLOOKUP(F30,Source!$1:$1048576,55,FALSE) -> 21.388889 | L49: =VLOOKUP(#REF!,Source!$1:$1048576,54,FALSE) -> #REF! | N49: =VLOOKUP(F30,Source!$1:$1048576,57,FALSE) -> 18.436898 | P49: =VLOOKUP(#REF!,Source!$1:$1048576,54,FALSE) -> #REF!

Sheet YR
B1: Proposed 6-Page Flyer (sept 2021)
C2: Grocery | D2: Meat | E2: Bakery | F2: Deli | G2: Produce | H2: Total
B3: FP | C3: 5 | D3: 1 | G3: 1 | H3: =SUM(C3:G3) -> 7
B4: P2 | D4: 13 | F4: 4 | H4: =SUM(C4:G4) -> 17
B5: P3 | E5: 7 | G5: 11 | H5: =SUM(C5:G5) -> 18
B6: P4 | C6: 24 | H6: =SUM(C6:G6) -> 24
B7: P5 | C7: 24 | H7: =SUM(C7:G7) -> 24
B8: BP | C8: 6 | D8: 1 | G8: 1 | H8: =SUM(C8:G8) -> 8
B9: Total | C9: =SUM(C3:C8) -> 59 | D9: =SUM(D3:D8) -> 15 | E9: =SUM(E3:E8) -> 7 | F9: =SUM(F3:F8) -> 4 | G9: =SUM(G3:G8) -> 13 | H9: =SUM(C9:G9) -> 98
B11: exsisting 4-Page Flyer
C12: Grocery | D12: Meat | E12: Bakery | F12: Deli | G12: Produce | H12: Total
B13: FP | C13: 12 | D13: 2 | G13: 1 | H13: =SUM(C13:G13) -> 15
B14: P2 | D14: 12 | E14: 3 | F14: 3 | H14: =SUM(C14:G14) -> 18
B15: P3 | C15: 26 | H15: =SUM(C15:G15) -> 26
B16: BP | C16: 3 | D16: 1 | G16: 9 | H16: =SUM(C16:G16) -> 13 | I16: meat is optional on BP
B17: Total | C17: =SUM(C13:C16) -> 41 | D17: =SUM(D13:D16) -> 15 | E17: =SUM(E13:E16) -> 3 | F17: =SUM(F13:F16) -> 3 | G17: =SUM(G13:G16) -> 10 | H17: =SUM(C17:G17) -> 72
B19: Existing 8-Page Flyer
C20: Grocery | D20: Meat | E20: Bakery | F20: Deli | G20: Produce | H20: Total
B21: FP | C21: 4 | D21: 1 | G21: 1 | H21: =SUM(C21:G21) -> 6
B22: P2 | D22: 14 | H22: =SUM(C22:G22) -> 14
B23: P3 | G23: 13 | H23: =SUM(C23:G23) -> 13
B24: P4 | E24: 8 | F24: 6 | H24: =SUM(C24:G24) -> 14
B25: P5 | C25: 19 | H25: =SUM(C25:G25) -> 19
B26: P6 | C26: 19 | H26: =SUM(C26:G26) -> 19
B27: P7 | C27: 19 | H27: =SUM(C27:G27) -> 19
B28: BP | C28: 6 | D28: 1 | G28: 1 | H28: =SUM(C28:G28) -> 8
B29: Total | C29: =SUM(C21:C28) -> 67 | D29: =SUM(D21:D28) -> 16 | E29: =SUM(E21:E28) -> 8 | F29: =SUM(F21:F28) -> 6 | G29: =SUM(G21:G28) -> 15 | H29: =SUM(H21:H28) -> 112
B31: Existing Yukon Flyer
C32: Grocery | D32: Meat | E32: Bakery | F32: Deli | G32: Produce | H32: Total
B33: FP | C33: 3 | D33: 1 | G33: 1 | H33: =SUM(C33:G33) -> 5
B34: P2 | D34: 10 | H34: =SUM(C34:G34) -> 10
B35: P3 | E35: 6 | F35: 5 | H35: =SUM(C35:G35) -> 11
B36: P4 | G36: 10 | H36: =SUM(C36:G36) -> 10
B37: P5 | C37: 10 | H37: =SUM(C37:G37) -> 10
B38: P6 | C38: 6 | H38: =SUM(C38:G38) -> 6
B39: P7 | C39: 6 | H39: =SUM(C39:G39) -> 6
B40: BP | C40: 3 | D40: 1 | G40: 1 | H40: =SUM(C40:G40) -> 5
B41: Total | C41: =SUM(C33:C40) -> 28 | D41: =SUM(D33:D40) -> 12 | E41: =SUM(E33:E40) -> 6 | F41: =SUM(F33:F40) -> 5 | G41: =SUM(G33:G40) -> 12 | H41: =SUM(H33:H40) -> 63
B43: Proposed Yukon Flyer
C44: Grocery | D44: Meat | E44: Bakery | F44: Deli | G44: Produce | H44: Total
B45: FP | C45: 3 | D45: 1 | G45: 1 | H45: =SUM(C45:G45) -> 5
B46: P2 | D46: 10 | H46: =SUM(C46:G46) -> 10
B47: P3 | H47: =SUM(C47:G47) -> 0
B48: P4 | G48: 10 | H48: =SUM(C48:G48) -> 10
B49: P5 | C49: 10 | H49: =SUM(C49:G49) -> 10
B50: P6 | C50: 6 | H50: =SUM(C50:G50) -> 6
B51: P7 | C51: 6 | H51: =SUM(C51:G51) -> 6
B52: BP | C52: 3 | D52: 1 | G52: 1 | H52: =SUM(C52:G52) -> 5
B53: Total | C53: =SUM(C45:C52) -> 28 | D53: =SUM(D45:D52) -> 12 | E53: =SUM(E45:E52) -> 0 | F53: =SUM(F45:F52) -> 0 | G53: =SUM(G45:G52) -> 12 | H53: =SUM(H45:H52) -> 52
B55: Existing 4-Page Flyer
C56: Grocery | D56: Meat | E56: Bakery | F56: Deli | G56: Produce | H56: Total
B57: FP | C57: 6 | D57: 1 | G57: 1 | H57: =SUM(C57:G57) -> 8
B58: P2 | C58: 12 | H58: =SUM(C58:G58) -> 12
B59: P3 | C59: 12 | H59: =SUM(C59:G59) -> 12
B60: BP | D60: 4 | G60: 4 | H60: =SUM(C60:G60) -> 8
B61: Total | C61: =SUM(C57:C60) -> 30 | D61: =SUM(D57:D60) -> 5 | E61: =SUM(E57:E60) -> 0 | F61: =SUM(F57:F60) -> 0 | G61: =SUM(G57:G60) -> 5 | H61: =SUM(C61:G61) -> 40
